Workbook
Name _Hlk126580657: 'Registru unic-CLIENTI'!#REF!
Name Slicer_CUSTOMER: #N/A
Name Slicer_CUSTOMER1: #N/A
Name Slicer_CUSTOMER11: #N/A
Name Slicer_CUSTOMER12: #N/A
Name Slicer_CUSTOMER2: #N/A
Name Slicer_CUSTOMER21: #N/A
Name Slicer_Month: #N/A
Name Slicer_Month11: #N/A
Name Slicer_Months__Dată_de_livrare: #N/A
Name Slicer_Months__Dată_de_livrare1: #N/A
Name Slicer_Order_Finished_YES_NO: #N/A
Name Slicer_Part_Number: #N/A
Name Slicer_Part_Number1: #N/A
Name Slicer_Part_Number2: #N/A
Name Slicer_Product_Family: #N/A
Name Slicer_Product_Family1: #N/A
Name Slicer_Product_Family2: #N/A
Name Slicer_Product_Family3: #N/A
Name Slicer_Product_Family4: #N/A
Name Slicer_YEAR: #N/A
Name Slicer_YEAR11: #N/A
Name Slicer_Years__ETA_As_requested_dd.mm.yyyy1: #N/A

Sheet Backlog+Comenzi de produs (2)
B9: Order Type | C9: (All)
B10: Order Finished YES/NO | C10: No
B11: Quarters (ETA As requested dd.mm.yyyy) | C11: (All)
E13: Years | F13: Months | G13: ETA | H13: Values
E14: 2024 | G14: 2025 | S14: 2025 Quantity | T14: 2025 Price/Order | U14: 2026 | AS14: 2026 Quantity | AT14: 2026 Price/Order | AU14: Total Quantity | AV14: Total Price/Order
G15: Mar | I15: Jul | K15: Sep | M15: Oct | O15: Nov | Q15: Dec | U15: Jan | W15: Feb | Y15: Mar | AA15: Apr | AC15: May | AE15: Jun | AG15: Jul | AI15: Aug | AK15: Sep | AM15: Oct | AO15: Nov | AQ15: Dec
B17: CUSTOMER | C17: Product Family | D17: Part Number | E17: Quantity | F17: Price/Order | G17: Quantity | H17: Price/Order | I17: Quantity | J17: Price/Order | K17: Quantity | L17: Price/Order | M17: Quantity | N17: Price/Order | O17: Quantity | P17: Price/Order | Q17: Quantity | R17: Price/Order | U17: Quantity | V17: Price/Order | W17: Quantity | X17: Price/Order | Y17: Quantity | Z17: Price/Order | AA17: Quantity | AB17: Price/Order | AC17: Quantity | AD17: Price/Order | AE17: Quantity | AF17: Price/Order | AG17: Quantity | AH17: Price/Order | AI17: Quantity | AJ17: Price/Order | AK17: Quantity | AL17: Price/Order | AM17: Quantity | AN17: Price/Order | AO17: Quantity | AP17: Price/Order | AQ17: Quantity | AR17: Price/Order
B18: BOSCH Blaj | E18: 2 | F18: 176.06 | M18: 683 | N18: 4180.54 | O18: 240 | P18: 4171.2 | Q18: 500 | R18: 7395.2 | S18: 1423 | T18: 15746.94 | U18: 340 | V18: 0 | W18: 580 | X18: 0 | Y18: 340 | Z18: 0 | AA18: 1080 | AB18: 0 | AC18: 340 | AD18: 0 | AE18: 240 | AF18: 0 | AG18: 340 | AH18: 0 | AI18: 240 | AJ18: 0 | AK18: 340 | AL18: 0 | AS18: 3840 | AT18: 0 | AU18: 5265 | AV18: 15923
B19: BOSCH Homburg | M19: 23 | N19: 122.13 | O19: 195 | P19: 2039.15 | Q19: 100 | R19: 97 | S19: 318 | T19: 2258.28 | U19: 396 | V19: 0 | W19: 120 | X19: 0 | Y19: 345 | Z19: 0 | AA19: 430 | AB19: 0 | AC19: 340 | AD19: 0 | AE19: 415 | AF19: 0 | AG19: 135 | AH19: 0 | AI19: 230 | AJ19: 0 | AK19: 630 | AL19: 0 | AM19: 130 | AN19: 0 | AO19: 69 | AP19: 0 | AQ19: 496 | AR19: 0 | AS19: 3736 | AT19: 0 | AU19: 4054 | AV19: 2258.28
B20: BOSCH Lohr | K20: 86 | L20: 499.66 | M20: 159 | N20: 9780.11 | O20: 1581 | P20: 16557.34 | Q20: 742 | R20: 13342.66 | S20: 2568 | T20: 40179.77 | U20: 2221 | V20: 2311.32 | W20: 872 | X20: 0 | Y20: 2209 | Z20: 0 | AA20: 1198 | AB20: 0 | AE20: 632 | AF20: 0 | AG20: 660 | AH20: 0 | AK20: 660 | AL20: 0 | AO20: 660 | AP20: 0 | AS20: 9112 | AT20: 2311.32 | AU20: 11680 | AV20: 42491.09
B21: Elbit | G21: 752 | H21: 79332.24 | K21: 15 | L21: 16506.15 | S21: 767 | T21: 95838.39 | AU21: 767 | AV21: 95838.39
B22: Orbit | K22: 14 | L22: 7696.65 | Q22: 9 | R22: 6465.6 | S22: 23 | T22: 14162.25 | AU22: 23 | AV22: 14162.25
B23: Schaeffler DE | E23: 102 | F23: 856.9 | Q23: 143 | R23: 2199.34 | S23: 143 | T23: 2199.34 | U23: 437 | V23: 8297.61 | Y23: 956 | Z23: 14360.98 | AA23: 30 | AB23: 0 | AS23: 1423 | AT23: 22658.59 | AU23: 1668 | AV23: 25714.83
B24: Schaeffler RO | I24: 5 | J24: 6.8 | M24: 794 | N24: 4384.76 | O24: 13372 | P24: 60319.77 | Q24: 14644 | R24: 47248.45 | S24: 28815 | T24: 111959.78 | AU24: 28815 | AV24: 111959.78
B25: Sadev | O25: 97 | P25: 97 | S25: 97 | T25: 97 | AU25: 97 | AV25: 97
B26: Grand Total | E26: 104 | F26: 1032.96 | G26: 752 | H26: 79332.24 | I26: 5 | J26: 6.8 | K26: 115 | L26: 24702.46 | M26: 1659 | N26: 18467.54 | O26: 15485 | P26: 83184.46 | Q26: 16138 | R26: 76748.25 | S26: 34154 | T26: 282441.75 | U26: 3394 | V26: 10608.93 | W26: 1572 | X26: 0 | Y26: 3850 | Z26: 14360.98 | AA26: 2738 | AB26: 0 | AC26: 680 | AD26: 0 | AE26: 1287 | AF26: 0 | AG26: 1135 | AH26: 0 | AI26: 470 | AJ26: 0 | AK26: 1630 | AL26: 0 | AM26: 130 | AN26: 0 | AO26: 729 | AP26: 0 | AQ26: 496 | AR26: 0 | AS26: 18111 | AT26: 24969.91 | AU26: 52369 | AV26: 308444.62

Sheet Orders
B9: Order Type | C9: (All)
B10: Order Finished YES/NO | C10: (All)
B11: Quarters (ETA As requested dd.mm.yyyy) | C11: (All)
B13: Sum of Quantity | E13: CUSTOMER | F13: CUSTOMER PO# | G13: Product Family | H13: Part Number
E14: Schaeffler DE | F14: Grand Total
B17: Years ) | C17: Months | D17: ETA
B18: 2024 | C18: May | E18: 225 | F18: 225
C19: Jun | E19: 308 | F19: 308
C20: Aug | E20: 63667 | F20: 63667
C21: Oct | E21: 363 | F21: 363
B22: 2024 Total | E22: 64563 | F22: 64563
B23: 2025 | C23: Jun | E23: 62 | F23: 62
C24: Dec | E24: 143 | F24: 143
B25: 2025 Total | E25: 205 | F25: 205
B26: Grand Total | E26: 64768 | F26: 64768

Sheet Livrari (2)
B6: Order Finished YES/NO | C6: (All)
B7: Order Type | C7: (All)
B8: Months (ETA As requested dd.mm.yyyy) | C8: (All)
B9: Years (ETA As requested dd.mm.yyyy) | C9: (All)
B10: Quarters (ETA As requested dd.mm.yyyy) | C10: (All)
B11: Date PO dd.mm.yyyy | C11: (All)
E13: Years | F13: Months | G13: Days | H13: Values
E14: 2025 | G14: 2025 Sum of OK | H14: 2025 Sum of Sales | I14: Total Sum of OK | J14: Total Sum of Sales
E15: Oct
B17: CUSTOMER | C17: Product Family | D17: Part Number | E17: Sum of OK | F17: Sum of Sales
B18: BOSCH Blaj | C18: Drosselboltzen | E18: 420 | F18: 7299.6 | G18: 420 | H18: 7299.6 | I18: 420 | J18: 7299.6
C19: Z2S 22 | E19: 300 | F19: 26409 | G19: 300 | H19: 26409 | I19: 300 | J19: 26409
B20: BOSCH Blaj Total | E20: 720 | F20: 33708.6 | G20: 720 | H20: 33708.6 | I20: 720 | J20: 33708.6
B21: BOSCH Homburg | E21: 10 | F21: 3000 | G21: 10 | H21: 3000 | I21: 10 | J21: 3000
B22: BOSCH Lohr | E22: 2856 | F22: 58859.57 | G22: 2856 | H22: 58859.57 | I22: 2856 | J22: 58859.57
B23: Elbit | C23: YAW PLATE | E23: 5 | F23: 2520.65 | G23: 5 | H23: 2520.65 | I23: 5 | J23: 2520.65
C24: CAMERA CLAMP | E24: 5 | F24: 2530.55 | G24: 5 | H24: 2530.55 | I24: 5 | J24: 2530.55
C25: BENCH ADAPTOR | E25: 5 | F25: 2511.9 | G25: 5 | H25: 2511.9 | I25: 5 | J25: 2511.9
B26: Elbit Total | E26: 15 | F26: 7563.1 | G26: 15 | H26: 7563.1 | I26: 15 | J26: 7563.1
B27: IGW | E27: 10 | F27: 5226 | G27: 10 | H27: 5226 | I27: 10 | J27: 5226
B28: Orbit | C28: AZIMUTH TURNTABLE, AL-4018-1RF | E28: 6 | F28: 4792.14 | G28: 6 | H28: 4792.14 | I28: 6 | J28: 4792.14
C29: EL. DRIVE (RIGHT) TURNTABLE, AL-4018-1RF | E29: 6 | F29: 3114.72 | G29: 6 | H29: 3114.72 | I29: 6 | J29: 3114.72
C30: PANEL ACCESS ELEVATION, AL-4018-1RF #30315 | E30: 6 | F30: 1458.66 | G30: 6 | H30: 1458.66 | I30: 6 | J30: 1458.66
B31: Orbit Total | E31: 18 | F31: 9365.52 | G31: 18 | H31: 9365.52 | I31: 18 | J31: 9365.52
B32: Schaeffler RO | E32: 23644 | F32: 51051.567 | G32: 23644 | H32: 51051.567 | I32: 23644 | J32: 51051.567
B33: Grand Total | E33: 27273 | F33: 168774.36 | G33: 27273 | H33: 168774.36 | I33: 27273 | J33: 168774.36

Sheet Livrari
B4: Order Finished YES/NO | C4: Yes
B5: Order Type | C5: (All)
B6: Months (ETA As requested dd.mm.yyyy) | C6: (All)
B7: Years (ETA As requested dd.mm.yyyy) | C7: (All)
B8: Quarters (ETA As requested dd.mm.yyyy) | C8: (All)
B9: Date PO dd.mm.yyyy | C9: (All)
B10: Product Family | C10: (All)
B11: AVIZ OLSTRAL | C11: (All)
B13: Sum of OK | G13: CUSTOMER
B14: Years | C14: Months | D14: Days | E14: CUSTOMER PO# | F14: Part Number | G14: Schaeffler RO | H14: Grand Total
B15: 2025 | C15: Sep | G15: 8222 | H15: 8222
C16: Oct | G16: 4185 | H16: 4185
B17: 2025 Total | G17: 12407 | H17: 12407
B18: Grand Total | G18: 12407 | H18: 12407

Sheet Sheet2
A1: Nr.comanda interna | B1: Data routing | C1: Ora | D1: Utilaj | E1: Reper | F1: Sarja | G1: Cantitate
A2: 240201 | E2: PBE 1400062752 | F2: 89466930 | G2: 10 bucati
A3: 240202 | E3: KUH 6036 | F3: 88821241 | G3: 42 calupi
A4: 240203 | E4: RKDK ZL | F4: 88962011 | G4: 924 bucati
A5: 240204 | E5: EDS F-607694-1038-ISB 000 AB | F5: 84159615 | G5: 298 bucati
A6: 240205 | E6: RKDK N222 | F6: 89151373 | G6: 22 calupi
A7: 240206 | E7: RB00690513 (1535100044) | F7: 3075576
A8: 240207 | E8: 1818509725 | F8: 279676
A9: 240208/1 | E9: EDS F-607694-1038-ISB 000 AB | F9: 84159615 | G9: 192 bucati
A10: 240209 | E10: KUH 6036 capete | F10: 88821241 | G10: 210 bucati = 42 calupi
A11: 240301 | E11: AUKB 2045B | G11: 6 bare
A12: 240302 | E12: KUH.6317 | F12: 89293208 | G12: 36 calupi
A13: 240303 | E13: R901469360/R900126765
A14: 240304 | E14: RKDK.N317-EA-M3-0042 | F14: 89288511 | G14: 48 calupi = 672 bucati
A15: 240305 | E15: B8C000021 | G15: 1 bara
A16: 240306 | E16: KWVE 30 BAS | F16: 86937618 | G16: 650 bucati
A17: 240307 | E17: KUH.6317 | F17: 89293208 | G17: capete
A18: 240308 | E18: EDS F-607694-1038-ISB 000 AB | F18: 2644388 | G18: 150 bucati
A19: 240309 | E19: 1818509284
A20: 240310 | E20: RB00690513 (1535100044) | F20: 3075576
A21: 240311 | E21: F 586360 | G21: 35 bucati
A22: 240312 | E22: AUKB 3068 | F22: 873065802 | G22: 5 + 5 bare (22.01)
A23: 240313 | E23: AUKB 2045B | G23: 15 bare
A24: 240314 | E24: KUH 6215 | F24: 89293273
A25: 240315 | E25: RKDK.N317-EA-M3-0042
A26: 240401 | E26: AUKB 2045B | G26: 15 bare
A27: 240402 | E27: R900145251 | G27: 105 bucati
A28: 240403 | E28: R900692452 | G28: 1 bucati
A29: 240404 | E29: R900305232 | F29: 2021050331 | G29: 40 bucati
A30: 240405 | E30: R901469360/R900126765 | F30: 2021050331 | G30: 3 bucati
A31: 240406 | E31: RKDK.N317-EA-M3-0042 | F31: 86971634 | G31: 8 + 32 bucati | H31: capete
A32: 240407 | E32: KWVE 30 BAS | F32: 8697618 | G32: 150 bucati
A33: 240408 | E33: EDS F-607694-1038-ISB 000 AB | F33: 2644388 | G33: 150 bucati
A34: 240409 | E34: KWVE 30 BAH | F34: 86937618 | G34: 250 bucati
A35: 240410 | E35: R900628302 | G35: 100 bucati
A36: 240411 | E36: AUKB 3068 | F36: 87306802 | G36: 15 bare = 450 piese
A37: 240412 | E37: 1813218042
A38: 240413 | E38: KWVE 30 BAS | F38: 86937618
A39: 240414 | E39: AUKB 2045B
A40: 240415 | E40: KWVE 30 BAS | F40: 86937618 | G40: 144 bucati
A41: 240416 | E41: RA60190295 / R900172405 | F41: CDA 4508720546
A42: 240417 | E42: EDS F-607694-1038-ISB 000 AB | F42: 2644388
A43: 240418 | E43: KWVE 30 BAS | F43: 86937618 | G43: 144 bucati
A44: 240419 | E44: EDS F-607694-1038-ISB 000 AB | F44: 2644388 | G44: 144 bucati
A45: 240420 | E45: B85300050
A46: 240421 | E46: AUKB 3068 | F46: 87306802 | G46: 14 bare = 420 piese
A47: 240422 | E47: B8C000023
A48: 240501 | E48: RKDK N222 capete | G48: 22 capete
A49: 240502 | E49: R 900145251 | F49: nu are | G49: 140 bucati
A50: 240503 | E50: KWSE 20 | F50: 87632366 | G50: 500 bucati
A51: 240504 | E51: AUKB 3068 | F51: 81737681
A52: 240505 | E52: F - 556440 | F52: 81795123 | G52: 200
A53: 240506 | E53: R900601576 | G53: 400
A54: 240507 | E54: F 235905 | F54: 81795123 | G54: 200
A55: 240508 | E55: AUKB 3068 | F55: 81737681
A56: 240509 | E56: AUKB 2045B
A57: 240510 | E57: KWVE 30 BAS | G57: 144
A58: 240511 | E58: AUKB 3068 | F58: 88215374
A59: 240512 | E59: S4673-08BAA | F59: 518274 | G59: 25 bucati
A60: 240513 | E60: AUKB 3068 | F60: 88215374 | G60: 15 bare
A61: 240514 | E61: AUKB 2045B | F61: 87306797 | G61: 27 bare
A62: 240515 | E62: KWVE 30 BAS | F62: 86937618 | G62: 144 bucati
A63: 240516 | E63: KWSE 20 | F63: 8191522 | G63: 64 bucati
A64: 240601 | E64: R 900305232 | F64: 2021050331 | G64: 20 bucati | H64: Iacob
A65: 240602 | E65: F-625593.03 | F65: 689208 | G65: 105 bucati | H65: Iacob
A66: 240603 | E66: R 900305231 | F66: 2021050331 | G66: 3 bucati | H66: Iacob
A67: 240604 | E67: R 900305231 | F67: 2021050331 | G67: 100 bucati | H67: Iacob
A68: 240605 | E68: 181509289 | F68: 95692 | G68: 30 bucati | H68: Iacob
A69: 240606 | E69: KWVE 30 BAH | F69: 86937618 | G69: 144 | H69: Iacob
A70: 240607 | E70: KUH 6217 | F70: 90843302
A71: 240608 | E71: 181321050 | G71: 1010 bucati | H71: Iacob
A72: 240609 | E72: 557809 | G72: 1250 bucati | H72: Iacob
A73: 240610 | E73: KWVE 30 BAH | F73: 86937618 | G73: 144 | H73: Valentina
A74: 240611 | E74: KUH 6217 | F74: 90843302 | G74: capete | H74: Valentina
A75: 240612 | E75: KWSE 20 | F75: 89632366 | G75: 144 | H75: Valentina
A76: 240613 | E76: F-625593.03 | F76: 689208 | G76: 5 bucati | H76: Radu
A77: 240614 | E77: R900147181 | F77: lipsa numar sarja | G77: 96 bucati | H77: Valentina
A78: 240615 | E78: 1818509289 | F78: 95692 | G78: 30 bucati | H78: Radu
A79: 240616 | E79: 1818509519 | F79: 28388TC | G79: 30 bucati | H79: Radu
A80: 240617 | E80: 1818509665 | F80: 28388TC | G80: 30 bucati | H80: Radu
A81: 240618 | E81: KUH 6315 | F81: 90887829 | G81: 762 piese | H81: Radu
A82: 240619 | E82: KWVE 30 BAH | F82: 86937618 | G82: 62 bucati | H82: Radu
A83: 240620 | E83: KWVE 30 BAH | F83: 81764496 | G83: 26 bucati | H83: Iacob
A84: 240621 | E84: KWVE 30 BAH | F84: 86937618 | G84: 100 bucati | H84: Iacob
A85: 240622 | E85: KWSE 20 | F85: 89632366 | G85: 144 bucati | H85: Iacob
A86: 240623 | E86: 1818509519 | F86: 28388TC | G86: 5 bucati | H86: Iacob
A87: 240624 | E87: R900601678 | F87: lipsa numar sarja | G87: 706 bucati | H87: Iacob
A88: 240701/1 | E88: KUH.6317
A89: 240701/2 | E89: KUH.6317
A90: 240701/3 | E90: KUH.6317
A91: 240702/1 | E91: EDP KUH.6220-A-M-3001 004
A92: 240702/2 | E92: EDP KUH.6220-A-M-3001 004
A93: 240702/3 | E93: EDP KUH.6220-A-M-3001 004
A94: 240702/4 | E94: EDP KUH.6220-A-M-3001 004
A95: 240703/1 | E95: EDP KUH.6220-A-M-3001 004
A96: 240703/2 | E96: EDP KUH.6220-A-M-3001 004
A97: 240703/3 | E97: EDP KUH.6220-A-M-3001 004
A98: 240703/4 | E98: EDP KUH.6220-A-M-3001 004
A99: 240704 | E99: 1818509554 | G99: 30 | H99: v1
A100: 240705 | E100: 1818509555
...

Sheet OTD
K1: 2024 | L1: Livrari-Delivery Data Analysis
L4: F_Q_300 REV.00-21/01/21
A6: KPI 5 | B6: KPI - Livrari - OTD = On Time Delivery TOTAL
A8: 2024 | B8: January | C8: February | D8: March | E8: April | F8: May | G8: June | H8: July | I8: August | J8: September | K8: October | L8: November | M8: December | N8: TOTAL | O8: Media
B9: Ianuarie | C9: Februarie | D9: Martie | E9: Aprilie | F9: Mai | G9: Iunie | H9: Iulie | I9: Agust | J9: Septembrie | K9: Octombrie | L9: Noiembrie | M9: Decembrie
A10: nr. de livrari | F10: =F24+F37+F50+F63 -> 304 | G10: =G24+G37+G50+G63 -> 284 | H10: =H24+H37+H50+H63 -> 312 | I10: =I24+I37+I50+I63 -> 248 | J10: =J24+J37+J50+J63 -> 0 | K10: =K24+K37+K50+K63 -> 0 | L10: =L24+L37+L50+L63 -> 0 | M10: =M24+M37+M50+M63 -> 0 | N10: =SUM(B10:M10) -> 1148 | O10: =AVERAGE(B10:M10) -> 143.5
A11: nr. de livrari la timp | F11: =F25+F38+F51+F64 -> 228 | G11: =G25+G38+G51+G64 -> 208 | H11: =H25+H38+H51+H64 -> 220 | I11: =I25+I38+I51+I64 -> 136 | J11: =J25+J38+J51+J64 -> 0 | K11: =K25+K38+K51+K64 -> 0 | L11: =L25+L38+L51+L64 -> 0 | M11: =M25+M38+M51+M64 -> 0 | N11: =SUM(B11:M11) -> 792 | O11: =AVERAGE(B11:M11) -> 99
A12: OTD Cda % | F12: =F11/F10 -> 0.75 | G12: =G11/G10 -> 0.73239437 | H12: =H11/H10 -> 0.70512821 | I12: =I11/I10 -> 0.5483871 | N12: =N11/N10 -> 0.68989547 | O12: =O11/O10 -> 0.68989547
A13: nr. de piese comandate | F13: =F27+F40+F53+F66 -> 1534 | G13: =G27+G40+G53+G66 -> 1068 | H13: =H27+H40+H53+H66 -> 3176 | I13: =I27+I40+I53+I66 -> 5708 | J13: =J27+J40+J53+J66 -> 0 | K13: =K27+K40+K53+K66 -> 0 | L13: =L27+L40+L53+L66 -> 0 | M13: =M27+M40+M53+M66 -> 0 | N13: =SUM(B13:M13) -> 11486 | O13: =AVERAGE(B13:M13) -> 1435.75
A14: Nr piese expediate | F14: =F28+F41+F54+F67 -> 684 | G14: =G28+G41+G54+G67 -> 386 | H14: =H28+H41+H54+H67 -> 2044 | I14: =I28+I41+I54+I67 -> 3594 | J14: =J28+J41+J54+J67 -> 0 | K14: =K28+K41+K54+K67 -> 0 | L14: =L28+L41+L54+L67 -> 0 | M14: =M28+M41+M54+M67 -> 0 | N14: =SUM(B14:M14) -> 6708 | O14: =AVERAGE(B14:M14) -> 838.5
A15: % de rebut | F15: =F14/F13 -> 0.44589309 | G15: =G14/G13 -> 0.36142322 | N15: =N14/N13 -> 0.58401532 | O15: =N15 -> 0.58401532
A16: OTD Qty % | B16: =B14/B13 -> #DIV/0! | C16: =C14/C13 -> #DIV/0! | D16: =D14/D13 -> #DIV/0! | E16: =E14/E13 -> #DIV/0! | F16: =F14/F13 -> 0.44589309 | G16: =G14/G13 -> 0.36142322 | H16: =H14/H13 -> 0.64357683 | I16: =I14/I13 -> 0.62964261 | N16: =(N14/N13) -> 0.58401532 | O16: =(O14/O13) -> 0.58401532
A17: Target >80% | B17: 0.8 | C17: 0.8 | D17: 0.8 | E17: 0.8 | F17: 0.8 | G17: 0.8 | H17: 0.8 | I17: 0.8 | J17: 0.8 | K17: 0.8 | L17: 0.8 | M17: 0.8
A20: KPI 5 | B20: KPI - Livrari - OTD= On Time Delivery BOSCH
A22: 2024 | B22: January | C22: February | D22: March | E22: April | F22: May | G22: June | H22: July | I22: August | J22: September | K22: October | L22: November | M22: December | N22: TOTAL | O22: Media
B23: Ianuarie | C23: Februarie | D23: Martie | E23: Aprilie | F23: Mai | G23: Iunie | H23: Iulie | I23: Agust | J23: Septembrie | K23: Octombrie | L23: Noiembrie | M23: Decembrie
A24: nr. de livrari | F24: 76 | G24: 71 | H24: 78 | I24: 62 | N24: =SUM(B24:M24) -> 287 | O24: =AVERAGE(B24:M24) -> 71.75
A25: nr. de livrari la timp | F25: 57 | G25: 52 | H25: 55 | I25: 34 | N25: =SUM(B25:M25) -> 198 | O25: =AVERAGE(B25:M25) -> 49.5
A26: OTD Cda % | F26: =F25/F24 -> 0.75 | G26: =G25/G24 -> 0.73239437 | H26: =H25/H24 -> 0.70512821 | I26: =I25/I24 -> 0.5483871 | N26: =N25/N24 -> 0.68989547 | O26: =O25/O24 -> 0.68989547
A27: nr. de piese comandate | F27: =F40+F53+F66 -> 767 | G27: =G40+G53+G66 -> 534 | H27: =H40+H53+H66 -> 1588 | I27: =I40+I53+I66 -> 2854 | N27: =SUM(B27:M27) -> 5743 | O27: =AVERAGE(B27:M27) -> 1435.75
A28: Nr piese expediate | F28: =F41+F54+F67 -> 342 | G28: =G41+G54+G67 -> 193 | H28: =H41+H54+H67 -> 1022 | I28: =I41+I54+I67 -> 1797 | N28: =SUM(B28:M28) -> 3354 | O28: =AVERAGE(B28:M28) -> 838.5
A29: OTD Qty % | B29: =B28/B27 -> #DIV/0! | C29: =C28/C27 -> #DIV/0! | D29: =D28/D27 -> #DIV/0! | E29: =E28/E27 -> #DIV/0! | F29: =F28/F27 -> 0.44589309 | G29: =G28/G27 -> 0.36142322 | H29: =H28/H27 -> 0.64357683 | I29: =I28/I27 -> 0.62964261 | N29: =(N28/N27) -> 0.58401532 | O29: =(O28/O27) -> 0.58401532
A30: Target >80% | B30: 0.8 | C30: 0.8 | D30: 0.8 | E30: 0.8 | F30: 0.8 | G30: 0.8 | H30: 0.8 | I30: 0.8 | J30: 0.8 | K30: 0.8 | L30: 0.8 | M30: 0.8
A33: KPI 5 | B33: KPI - Livrari - OTD= On Time Delivery BOSCH Lohr
A35: 2024 | B35: January | C35: February | D35: March | E35: April | F35: May | G35: June | H35: July | I35: August | J35: September | K35: October | L35: November | M35: December | N35: TOTAL | O35: Media
B36: Ianuarie | C36: Februarie | D36: Martie | E36: Aprilie | F36: Mai | G36: Iunie | H36: Iulie | I36: Agust | J36: Septembrie | K36: Octombrie | L36: Noiembrie | M36: Decembrie
A37: nr. de livrari | F37: 76 | G37: 71 | H37: 78 | I37: 62 | N37: =SUM(B37:M37) -> 287 | O37: =AVERAGE(B37:M37) -> 71.75
A38: nr. de livrari la timp | F38: 57 | G38: 52 | H38: 55 | I38: 34 | N38: =SUM(B38:M38) -> 198 | O38: =AVERAGE(B38:M38) -> 49.5
A39: OTD Cda % | F39: =F38/F37 -> 0.75 | G39: =G38/G37 -> 0.73239437 | H39: =H38/H37 -> 0.70512821 | I39: =I38/I37 -> 0.5483871 | N39: =N38/N37 -> 0.68989547 | O39: =O38/O37 -> 0.68989547
A40: nr. de piese comandate | F40: 164 | G40: 294 | H40: 271 | I40: 240 | N40: =SUM(B40:M40) -> 969 | O40: =AVERAGE(B40:M40) -> 242.25
A41: Nr piese expediate | F41: 102 | G41: 126 | H41: 144 | I41: 198 | N41: =SUM(B41:M41) -> 570 | O41: =AVERAGE(B41:M41) -> 142.5
A42: OTD Qty % | B42: =B41/B40 -> #DIV/0! | C42: =C41/C40 -> #DIV/0! | D42: =D41/D40 -> #DIV/0! | E42: =E41/E40 -> #DIV/0! | F42: =F41/F40 -> 0.62195122 | G42: =G41/G40 -> 0.42857143 | H42: =H41/H40 -> 0.53136531 | I42: =I41/I40 -> 0.825 | N42: =(N41/N40) -> 0.58823529 | O42: =(O41/O40) -> 0.58823529
A43: Target >80% | B43: 0.8 | C43: 0.8 | D43: 0.8 | E43: 0.8 | F43: 0.8 | G43: 0.8 | H43: 0.8 | I43: 0.8 | J43: 0.8 | K43: 0.8 | L43: 0.8 | M43: 0.8
A46: KPI 5 | B46: KPI - Livrari - OTD= On Time Delivery BOSCH Blaj
A48: 2024 | B48: January | C48: February | D48: March | E48: April | F48: May | G48: June | H48: July | I48: August | J48: September | K48: October | L48: November | M48: December | N48: TOTAL | O48: Media
B49: Ianuarie | C49: Februarie | D49: Martie | E49: Aprilie | F49: Mai | G49: Iunie | H49: Iulie | I49: Agust | J49: Septembrie | K49: Octombrie | L49: Noiembrie | M49: Decembrie
A50: nr. de livrari | F50: 76 | G50: 71 | H50: 78 | I50: 62 | N50: =SUM(B50:M50) -> 287 | O50: =AVERAGE(B50:M50) -> 71.75
A51: nr. de livrari la timp | F51: 57 | G51: 52 | H51: 55 | I51: 34 | N51: =SUM(B51:M51) -> 198 | O51: =AVERAGE(B51:M51) -> 49.5
A52: OTD Cda % | F52: =F51/F50 -> 0.75 | G52: =G51/G50 -> 0.73239437 | H52: =H51/H50 -> 0.70512821 | I52: =I51/I50 -> 0.5483871 | N52: =N51/N50 -> 0.68989547 | O52: =O51/O50 -> 0.68989547
A53: nr. de piese comandate | F53: 603 | G53: 240 | H53: 1317 | I53: 2598 | N53: =SUM(B53:M53) -> 4758 | O53: =AVERAGE(B53:M53) -> 1189.5
A54: Nr piese expediate | F54: 240 | G54: 67 | H54: 878 | I54: 1599 | N54: =SUM(B54:M54) -> 2784 | O54: =AVERAGE(B54:M54) -> 696
A55: OTD Qty % | B55: =B54/B53 -> #DIV/0! | C55: =C54/C53 -> #DIV/0! | D55: =D54/D53 -> #DIV/0! | E55: =E54/E53 -> #DIV/0! | F55: =F54/F53 -> 0.39800995 | G55: =G54/G53 -> 0.27916667 | H55: =H54/H53 -> 0.66666667 | I55: =I54/I53 -> 0.61547344 | N55: =(N54/N53) -> 0.5851198 | O55: =(O54/O53) -> 0.5851198
A56: Target >80% | B56: 0.8 | C56: 0.8 | D56: 0.8 | E56: 0.8 | F56: 0.8 | G56: 0.8 | H56: 0.8 | I56: 0.8 | J56: 0.8 | K56: 0.8 | L56: 0.8 | M56: 0.8
A59: KPI 5 | B59: KPI - Livrari - OTD= On Time Delivery BOSCH Homburg
A61: 2024 | B61: January | C61: February | D61: March | E61: April | F61: May | G61: June | H61: July | I61: August | J61: September | K61: October | L61: November | M61: December | N61: TOTAL | O61: Media
B62: Ianuarie | C62: Februarie | D62: Martie | E62: Aprilie | F62: Mai | G62: Iunie | H62: Iulie | I62: Agust | J62: Septembrie | K62: Octombrie | L62: Noiembrie | M62: Decembrie
A63: nr. de livrari | F63: 76 | G63: 71 | H63: 78 | I63: 62 | N63: =SUM(B63:M63) -> 287 | O63: =AVERAGE(B63:M63) -> 71.75
A64: nr. de livrari la timp | F64: 57 | G64: 52 | H64: 55 | I64: 34 | N64: =SUM(B64:M64) -> 198 | O64: =AVERAGE(B64:M64) -> 49.5
A65: OTD Cda % | F65: =F64/F63 -> 0.75 | G65: =G64/G63 -> 0.73239437 | H65: =H64/H63 -> 0.70512821 | I65: =I64/I63 -> 0.5483871 | N65: =N64/N63 -> 0.68989547 | O65: =O64/O63 -> 0.68989547
A66: nr. de piese comandate | F66: 0 | G66: 0 | H66: 0 | I66: 16 | N66: =SUM(B66:M66) -> 16 | O66: =AVERAGE(B66:M66) -> 4
A67: Nr piese expediate | F67: 0 | G67: 0 | H67: 0 | I67: 0 | N67: =SUM(B67:M67) -> 0 | O67: =AVERAGE(B67:M67) -> 0
A68: OTD Qty % | B68: =B67/B66 -> #DIV/0! | C68: =C67/C66 -> #DIV/0! | D68: =D67/D66 -> #DIV/0! | E68: =E67/E66 -> #DIV/0! | F68: =F67/F66 -> #DIV/0! | G68: =G67/G66 -> #DIV/0! | H68: =H67/H66 -> #DIV/0! | I68: =I67/I66 -> 0 | N68: =(N67/N66) -> 0 | O68: =(O67/O66) -> 0
A69: Target >80% | B69: 0.8 | C69: 0.8 | D69: 0.8 | E69: 0.8 | F69: 0.8 | G69: 0.8 | H69: 0.8 | I69: 0.8 | J69: 0.8 | K69: 0.8 | L69: 0.8 | M69: 0.8

Sheet LOP_SupplyChain
B1: LOP SUPPLY CHAIN
B3: Data | C3: Client | D3: Prio | E3: Produs | F3: Problema | G3: Termen | H3: Cine | I3: Status
B4: 45534 | C4: Schaeffler RO | E4: EDS F-801632-1031.RKKM.ZL-M3A 000 | F4: Inchis cda cu clientul | G4: 45541
E5: F-801632-1042.D140.RKDK.ZL-M3AA | F5: material de client in w36! | G5: 45541
B6: 45538 | E6: Danfoss_NEW | F6: Proiect nou > cda, PPAP, etc | G6: 45541 | H6: Popa
B7: 45540 | E7: B85300050 | F7: material de achizitionat!
B8: 45540 | E8: F-801632-1042.D140.RKDK.ZL-M3AA | F8: inchidere cda | H8: Madalina
B9: 45541 | E9: F-320745-1701.HUE.ACT | F9: MP de achizitionat | H9: Madalina | I9: comandat
B10: 45541 | E10: F-320745-9001.VSHR.ACT | F10: MP de achizitionat | H10: Madalina | I10: comandat
B11: 45547 | E11: R900172405 | F11: MP de achizitionat
B13: 45551 | C13: Schaeffler RO | F13: Livrari Sept Ghidaje din stoc | G13: 45554 | H13: Madalina
B14: 45551 | C14: Bosch Lohr | E14: Plate | F14: Inventar + cda materiale | G14: 45551 | H14: Popa/Madalina
B15: 45551 | F15: HEC204 > capacitate disponibila w39 Ce se transfera? Housing Schaeffler de pe Matsura? DBD-uri? | H15: Popa
B16: 45551 | F16: Operatori Rectificare | H16: Popa
B17: 45551
B18: 45551
B19: 45551

Sheet Registru unic-FURNIZORI
K1: REGISTRU UNIC FURNIZORI | N1: din aceste date obtinem KPI 7
A7: NR CRT | B7: CUSTOMER | C7: PART NUMBER | D7: RAW MATERIAL | E7: DIMENSIONS (mm) | F7: FAMILY | G7: SUPPLIER | H7: OBS
A8: 1 | B8: Edwards | C8: B85300050 | D8: AlSiMgMn T6 | E8: Ø140x15x160 | F8: Teava | G8: Tehnodistcom | H8: 3 piese
A9: 2 | B9: Walterscheid | C9: 557809 | D9: 16/20MnCr5 laminat | E9: Ø105 (+6) x 100 | F9: Bara | G9: Tehnodistcom | H9: Dimensiune dupa debitare
A10: 3 | B10: Bosch Lohr | C10: R900305241 | D10: EN-GJS-400-15C | E10: 130x90x1575 | F10: Bara | G10: ACO Guss Gmbh | H10: Debitare la 184 - Vectra
A11: 4 | B11: Bosch Lohr | C11: R900305244 | D11: EN-GJS-400-15C | E11: 130x90x1575 | F11: Bara | G11: ACO Guss Gmbh | H11: Debitare la 184 - Vectra
A12: 5 | B12: Bosch Lohr | C12: R900305248 | D12: EN-GJS-400-15C | E12: 130x90x1575 | F12: Bara | G12: ACO Guss Gmbh | H12: Debitare la 184 - Vectra
A13: 6 | B13: Bosch Lohr | C13: R901157146 | D13: EN-GJS-400-15C | E13: 130x90x1575 | F13: Bara | G13: ACO Guss Gmbh | H13: Debitare la 184 - Vectra
A14: 7 | B14: Bosch Lohr | C14: R901469368 | D14: EN-GJS-400-15C | E14: 130x90x1575 | F14: Bara | G14: ACO Guss Gmbh | H14: Debitare la 184 - Vectra
A15: 8 | B15: Bosch Lohr | C15: R901157145 | D15: EN-GJS-400-15C | E15: 130x90x1575 | F15: Bara | G15: ACO Guss Gmbh | H15: Debitare la 184 - Vectra
A16: 9 | B16: Bosch Lohr | C16: R901469366 | D16: EN-GJS-400-15C | E16: 130x90x1575 | F16: Bara | G16: ACO Guss Gmbh | H16: Debitare la 184 - Vectra
A17: 10 | B17: Bosch Homburg | C17: 1813218050 | D17: 100Cr6 | E17: Ø16x3000 | F17: Bara | G17: Tehnodistcom
A18: 11 | B18: Liebherr | C18: 39267-13 | D18: Aluminiu (T351 25.4X) | E18: 130x80x25.4 | F18: Tabla | G18: Gilinox
A19: 12 | B19: Liebherr | C19: 39267-13 | D19: Al 2024 | E19: 130x80x25 | F19: Placa debitata | G19: Tehnodistcom
A20: 13 | B20: Bosch Lohr | C20: R900305231 | D20: 11SMn30+C | E20: 80x60x2900 | F20: Bara | G20: Heine + Beisswenger | H20: Debitare la 104 - Vectra
A21: 14 | B21: Bosch Lohr | C21: R900305247 | D21: EN-GJS-400-15C | E21: 130x90x1575 | F21: Bara | G21: Heine + Beisswenger | H21: Debitare la 184 - Vectra
A22: 15 | B22: Bosch Lohr | C22: R901190149 | D22: 11SMn30+C | E22: 80x60x2900 | F22: Bara | G22: Heine + Beisswenger | H22: Debitare la 104 - Vectra
A23: 16 | B23: Bosch Lohr | C23: R901190153 | D23: 11SMn30+C | E23: 80x60x2900 | F23: Bara | G23: Heine + Beisswenger | H23: Debitare la 104 - Vectra
A24: 17 | B24: Bosch Lohr | C24: R900305228 | D24: 11SMn30+C | E24: 80x60x2900 | F24: Bara | G24: Heine + Beisswenger | H24: Debitare la 104 - Vectra
A25: 18 | B25: Bosch Lohr | C25: R900305232 | D25: 11SMn30+C | E25: 80x60x2900 | F25: Bara | G25: Heine + Beisswenger | H25: Debitare la 104 - Vectra
A26: 19 | B26: Bosch Lohr | C26: R901469358 | D26: 11SMn30+C | E26: 80x60x2900 | F26: Bara | G26: Heine + Beisswenger | H26: Debitare la 104 - Vectra
A27: 20 | B27: Bosch Lohr | C27: R900305223 | D27: 11SMn30+C | E27: 80x60x2900 | F27: Bara | G27: Heine + Beisswenger | H27: Debitare la 104 - Vectra
A28: 21 | B28: Bosch Lohr | C28: R900305233 | D28: 11SMn30+C | E28: 100x70x2900 | F28: Bara | G28: Heine + Beisswenger | H28: Debitare la 139 - Vectra
A29: 22 | B29: Bosch Lohr | C29: R900305236 | D29: 11SMn30+C | E29: 100x70x2900 | F29: Bara | G29: Heine + Beisswenger | H29: Debitare la 139 - Vectra
A30: 23 | B30: Bosch Lohr | C30: R900305239 | D30: 11SMn30+C | E30: 100x70x2900 | F30: Bara | G30: Heine + Beisswenger | H30: Debitare la 139 - Vectra
A31: 24 | B31: Bosch Lohr | C31: R900305240 | D31: 11SMn30+C | E31: 100x70x2900 | F31: Bara | G31: Heine + Beisswenger | H31: Debitare la 139 - Vectra
... A35: 28 | B35: Bosch Lohr | C35: R901469362 | D35: 11SMn30+C | E35: 100x70x2900 | F35: Bara | G35: Heine + Beisswenger | H35: Debitare la 139 - Vectra
A36: 29 | B36: Liebherr | C36: S4673-08BA | D36: Inox W1.4
A37: 30
A38: 31
A39: 32
A40: 33
A41: 34
A42: 35
A43: 36
A44: 37
A45: 38
A46: 39
A47: 40
A48: 41
... A122: 115
C188: 1

Sheet list
A1: Customer | E1: Subcontractare | G1: tip
A2: Schaeffler RO | E2: yes | G2: approved
A3: Schaeffler DE | E3: no | G3: project
A4: BOSCH Homburg
A5: BOSCH Lohr
A6: BOSCH Blaj
A7: IGW
A8: PAS Technologies
A9: Edwards
A10: Walterscheid
A11: Zeiss
A12: Alfons Haar
A13: Elbit
A14: Orbit
A15: Sadev

Sheet Database_Routing
A1: EDP KUH.6214-A-M-3001 004
A2: Item Name | B2: Links | C2: Client | D2: OK/NOK | E2: Spalte1
A4: EDP KU7208-B-MP-0031 000 | B4: \\192.168.0.252\4.productie\CLIENTI\SCHAEFFLER\01_Alama\EDP KU7208-B-MP-0031 000 | C4: SCHAEFFLER
A5: EDP KU7220-B-MP-0031 000 | B5: \\192.168.0.252\4.productie\CLIENTI\SCHAEFFLER\01_Alama\EDP KU7220-B-MP-0031 000 | C5: SCHAEFFLER
A6: EDP KUH.6030-M-3001 004 | B6: \\192.168.0.252\4.productie\CLIENTI\SCHAEFFLER\01_Alama\EDP KUH.6030-M-3001 004 | C6: SCHAEFFLER
A7: EDP KUH.6036-A-M-3001B | B7: \\192.168.0.252\4.productie\CLIENTI\SCHAEFFLER\01_Alama\EDP KUH.6036-A-M-3001B | C7: SCHAEFFLER
A8: EDP KUH.6214-A-M-3001 004 | B8: \\192.168.0.252\4.productie\CLIENTI\SCHAEFFLER\01_Alama\EDP KUH.6214-A-M-3001 004 | C8: SCHAEFFLER
A9: EDP KUH.6215-A-M-3001 004 | B9: \\192.168.0.252\4.productie\CLIENTI\SCHAEFFLER\01_Alama\EDP KUH.6215-A-M-3001 004 | C9: SCHAEFFLER
A10: EDP KUH.6217-B-M-3001 004 | B10: \\192.168.0.252\4.productie\CLIENTI\SCHAEFFLER\01_Alama\EDP KUH.6217-B-M-3001 004 | C10: SCHAEFFLER
A11: EDP KUH.6220-A-M-3001 004 | B11: \\192.168.0.252\4.productie\CLIENTI\SCHAEFFLER\01_Alama\EDP KUH.6220-A-M-3001 004 | C11: SCHAEFFLER | D11: OK
A13: EDP KUH.6222-A-M-3001B | B13: \\192.168.0.252\4.productie\CLIENTI\SCHAEFFLER\01_Alama\EDP KUH.6222-A-M-3001B | C13: SCHAEFFLER
A14: EDP KUH.6312-M-3001 004 | B14: \\192.168.0.252\4.productie\CLIENTI\SCHAEFFLER\01_Alama\EDP KUH.6312-M-3001 004 | C14: SCHAEFFLER | F14: B853000050
A15: EDP KUH.6315-A-M-3001 004 | B15: \\192.168.0.252\4.productie\CLIENTI\SCHAEFFLER\01_Alama\EDP KUH.6315-A-M-3001 004 | C15: SCHAEFFLER | D15: OK | F15: CZR0015562
A16: EDP KUH.6316-A-M-3001 004 | B16: \\192.168.0.252\4.productie\CLIENTI\SCHAEFFLER\01_Alama\EDP KUH.6316-A-M-3001 004 | C16: SCHAEFFLER | F16: XR100548
A17: EDP KUH.6317-A-M-3001 004 | B17: \\192.168.0.252\4.productie\CLIENTI\SCHAEFFLER\01_Alama\EDP KUH.6317-A-M-3001 004 | C17: SCHAEFFLER | D17: OK | F17: XR100546
A18: EDP KUH.6326-M-3001 004 | B18: \\192.168.0.252\4.productie\CLIENTI\SCHAEFFLER\01_Alama\EDP KUH.6326-M-3001 004 | C18: SCHAEFFLER
A19: EDP KUK.QJ205-C-MPA-3001 004 | B19: \\192.168.0.252\4.productie\CLIENTI\SCHAEFFLER\01_Alama\EDP KUK.QJ205-C-MPA-3001 004 | C19: SCHAEFFLER
A20: EDP KUK.QJ206-C-MPA-3001 004 | B20: \\192.168.0.252\4.productie\CLIENTI\SCHAEFFLER\01_Alama\EDP KUK.QJ206-C-MPA-3001 004 | C20: SCHAEFFLER
A21: EDP KUK.QJ207-C-MPA-3001 004 | B21: \\192.168.0.252\4.productie\CLIENTI\SCHAEFFLER\01_Alama\EDP KUK.QJ207-C-MPA-3001 004 | C21: SCHAEFFLER
A22: EDP KUK.QJ212-C-MPA-0031 000 | B22: \\192.168.0.252\4.productie\CLIENTI\SCHAEFFLER\01_Alama\EDP KUK.QJ212-C-MPA-0031 000 | C22: SCHAEFFLER
A23: EDP KUK.QJ213-CA-MPA-3001 | B23: \\192.168.0.252\4.productie\CLIENTI\SCHAEFFLER\01_Alama\EDP KUK.QJ213-CA-MPA-3001 | C23: SCHAEFFLER
A24: EDP KUK.QJ218-C-MPA-3001 | B24: \\192.168.0.252\4.productie\CLIENTI\SCHAEFFLER\01_Alama\EDP KUK.QJ218-C-MPA-3001 | C24: SCHAEFFLER
A25: EDP KUQJ213-CA-MPA-0031 000 | B25: \\192.168.0.252\4.productie\CLIENTI\SCHAEFFLER\01_Alama\EDP KUQJ213-CA-MPA-0031 000 | C25: SCHAEFFLER
A26: EDP KUQJ308-C-MPA-0031-000 | B26: \\192.168.0.252\4.productie\CLIENTI\SCHAEFFLER\01_Alama\EDP KUQJ308-C-MPA-0031-000 | C26: SCHAEFFLER
A27: EDP RKKM.N2220-EB-M3-0031 000 | B27: \\192.168.0.252\4.productie\CLIENTI\SCHAEFFLER\01_Alama\EDP RKKM.N2220-EB-M3-0031 000 | C27: SCHAEFFLER
A28: EDP RKKM.N416-M3-1031 000 | B28: \\192.168.0.252\4.productie\CLIENTI\SCHAEFFLER\01_Alama\EDP RKKM.N416-M3-1031 000 | C28: SCHAEFFLER
A29: EDS F-801631-1032.RKKM.ZL-M3A | B29: \\192.168.0.252\4.productie\CLIENTI\SCHAEFFLER\01_Alama\EDS F-801631-1032.RKKM.ZL-M3A | C29: SCHAEFFLER | D29: OK
A30: EDS KUH.6030-M-3001 | B30: \\192.168.0.252\4.productie\CLIENTI\SCHAEFFLER\01_Alama\EDS KUH.6030-M-3001 | C30: SCHAEFFLER
A31: EDS KUK.QJ205-C-MPA-3002 004 | B31: \\192.168.0.252\4.productie\CLIENTI\SCHAEFFLER\01_Alama\EDS KUK.QJ205-C-MPA-3002 004 | C31: SCHAEFFLER
A32: EDS KUK.QJ215-C-MPA-3001B | B32: \\192.168.0.252\4.productie\CLIENTI\SCHAEFFLER\01_Alama\EDS KUK.QJ215-C-MPA-3001B | C32: SCHAEFFLER
A33: EDS KUK.QJ215-C-MPA-3002 004 | B33: \\192.168.0.252\4.productie\CLIENTI\SCHAEFFLER\01_Alama\EDS KUK.QJ215-C-MPA-3002 004 | C33: SCHAEFFLER
A34: EDS_F-801632-1032_RKKM_ZL-M3A_000_AC | B34: \\192.168.0.252\4.productie\CLIENTI\SCHAEFFLER\01_Alama\EDS_F-801632-1032_RKKM_ZL-M3A_000_AC | C34: SCHAEFFLER | D34: OK
A35: EDS_RKDK_N217-E-Y3-1042_000_AA | B35: \\192.168.0.252\4.productie\CLIENTI\SCHAEFFLER\01_Alama\EDS_RKDK_N217-E-Y3-1042_000_AA | C35: SCHAEFFLER | D35: OK
A36: F-801632-0042.D140.RKDK.ZL-M3AA | B36: \\192.168.0.252\4.productie\CLIENTI\SCHAEFFLER\01_Alama\F-801632-0042.D140.RKDK.ZL-M3AA | C36: SCHAEFFLER | D36: OK
A37: RKDK.N222-EA-M3-0042 | B37: \\192.168.0.252\4.productie\CLIENTI\SCHAEFFLER\01_Alama\RKDK.N222-EA-M3-0042 | C37: SCHAEFFLER | D37: OK
A38: RKDK.N316-EA-M3-0042 | B38: \\192.168.0.252\4.productie\CLIENTI\SCHAEFFLER\01_Alama\RKDK.N316-EA-M3-0042 | C38: SCHAEFFLER | D38: OK
A39: RKDK.N317-EA-M3-0042 | B39: \\192.168.0.252\4.productie\CLIENTI\SCHAEFFLER\01_Alama\RKDK.N317-EA-M3-0042 | C39: SCHAEFFLER | D39: OK
A40: EDP_KUH_6015-A-M-3001_004_AD | B40: \\192.168.0.252\4.productie\CLIENTI\SCHAEFFLER\01_Alama\COLIVII ALAMA\EDP_KUH_6015-A-M-3001_004_AD | C40: SCHAEFFLER
A41: EDP_RKKM_N1012-M3-1031_000_AC | B41: \\192.168.0.252\4.productie\CLIENTI\SCHAEFFLER\01_Alama\COLIVII ALAMA\EDP_RKKM_N1012-M3-1031_000_AC | C41: SCHAEFFLER
A42: EDP_RKKM_N1014-M3-1031_000_AE | B42: \\192.168.0.252\4.productie\CLIENTI\SCHAEFFLER\01_Alama\COLIVII ALAMA\EDP_RKKM_N1014-M3-1031_000_AE | C42: SCHAEFFLER
A43: EDP_RKKM_N214-EA-M3-1031_000_AD | B43: \\192.168.0.252\4.productie\CLIENTI\SCHAEFFLER\01_Alama\COLIVII ALAMA\EDP_RKKM_N214-EA-M3-1031_000_AD | C43: SCHAEFFLER
A44: EDP_RKKM_N215-E-M3-1031_000_AE | B44: \\192.168.0.252\4.productie\CLIENTI\SCHAEFFLER\01_Alama\COLIVII ALAMA\EDP_RKKM_N215-E-M3-1031_000_AE | C44: SCHAEFFLER
A45: EDP_RKKM_N312-EA-M3-1031_000_AH | B45: \\192.168.0.252\4.productie\CLIENTI\SCHAEFFLER\01_Alama\COLIVII ALAMA\EDP_RKKM_N312-EA-M3-1031_000_AH | C45: SCHAEFFLER
A46: F-625620-3001_RK_N-MPBX_31_04 | B46: \\192.168.0.252\4.productie\CLIENTI\SCHAEFFLER\01_Alama\COLIVII ALAMA\F-625620-3001_RK_N-MPBX_31_04 | C46: SCHAEFFLER
A47: KU7220-B-MP-0031_000_AC | B47: \\192.168.0.252\4.productie\CLIENTI\SCHAEFFLER\01_Alama\COLIVII ALAMA\KU7220-B-MP-0031_000_AC | C47: SCHAEFFLER
A48: EDS_1C304695-350L_000_AH | B48: \\192.168.0.252\4.productie\CLIENTI\SCHAEFFLER\02_Ghidaje_Liniare\EDS_1C304695-350L_000_AH | C48: SCHAEFFLER
A49: EDS_F-319149_01-0038-ISB_000_00 | B49: \\192.168.0.252\4.productie\CLIENTI\SCHAEFFLER\02_Ghidaje_Liniare\EDS_F-319149_01-0038-ISB_000_00 | C49: SCHAEFFLER
A50: EDS_F-607694-1038-ISB_000_AA | B50: \\192.168.0.252\4.productie\CLIENTI\SCHAEFFLER\02_Ghidaje_Liniare\EDS_F-607694-1038-ISB_000_AA | C50: SCHAEFFLER | D50: OK | F50: 204 | G50: 205
A51: EDS_KWSE20-A-0038-ISB_000_AA | B51: \\192.168.0.252\4.productie\CLIENTI\SCHAEFFLER\02_Ghidaje_Liniare\EDS_KWSE20-A-0038-ISB_000_AA | C51: SCHAEFFLER | D51: OK | F51: 204
A52: EDS_KWSE25-A-H-0038-ISB_000_AA | B52: \\192.168.0.252\4.productie\CLIENTI\SCHAEFFLER\02_Ghidaje_Liniare\EDS_KWSE25-A-H-0038-ISB_000_AA | C52: SCHAEFFLER
A53: EDS_KWSE25-A-L-0038-ISB_000_AA | B53: \\192.168.0.252\4.productie\CLIENTI\SCHAEFFLER\02_Ghidaje_Liniare\EDS_KWSE25-A-L-0038-ISB_000_AA | C53: SCHAEFFLER
A54: EDS_KWVE15B-A-ESC-0038-ISB_000_00 | B54: \\192.168.0.252\4.productie\CLIENTI\SCHAEFFLER\02_Ghidaje_Liniare\EDS_KWVE15B-A-ESC-0038-ISB_000_00 | C54: SCHAEFFLER | D54: OK
A55: EDS_KWVE15B-A-H-0038-ISB_000_00 | B55: \\192.168.0.252\4.productie\CLIENTI\SCHAEFFLER\02_Ghidaje_Liniare\EDS_KWVE15B-A-H-0038-ISB_000_00 | C55: SCHAEFFLER
A56: EDS_KWVE20B-A-L-0038-ISB_000_AA | B56: \\192.168.0.252\4.productie\CLIENTI\SCHAEFFLER\02_Ghidaje_Liniare\EDS_KWVE20B-A-L-0038-ISB_000_AA | C56: SCHAEFFLER | D56: OK
A57: EDS_KWVE20B-A-NL-0038-ISB_000_AA | B57: \\192.168.0.252\4.productie\CLIENTI\SCHAEFFLER\02_Ghidaje_Liniare\EDS_KWVE20B-A-NL-0038-ISB_000_AA | C57: SCHAEFFLER
A58: EDS_KWVE30B-A-H-0038-ISB_000_00 | B58: \\192.168.0.252\4.productie\CLIENTI\SCHAEFFLER\02_Ghidaje_Liniare\EDS_KWVE30B-A-H-0038-ISB_000_00 | C58: SCHAEFFLER | D58: OK | F58: SW
A59: TK.KWVE30-B-A-S-0038-WW1 | B59: \\192.168.0.252\4.productie\CLIENTI\SCHAEFFLER\02_Ghidaje_Liniare\EDS_KWVE30B-A-S-0038-ISB_000_00 | C59: SCHAEFFLER | D59: OK
A60: TK.KWVE30-B-A-SL-0038-WW1 | B60: \\192.168.0.252\4.productie\CLIENTI\SCHAEFFLER\02_Ghidaje_Liniare\EDS_KWVE30B-A-SL-0038-ISB_000_00 | C60: SCHAEFFLER | D60: OK
A61: EDS AU.KB2045B-0208-ISB 000 | B61: \\192.168.0.252\4.productie\CLIENTI\SCHAEFFLER\03_AUKB\EDS AU.KB2045B-0208-ISB 000 | C61: SCHAEFFLER | D61: OK
A62: EDS_AU_KB1232B-0208-ISB_000_00 | B62: \\192.168.0.252\4.productie\CLIENTI\SCHAEFFLER\03_AUKB\EDS_AU_KB1232B-0208-ISB_000_00 | C62: SCHAEFFLER
A63: EDS_AU_KB1636B-0208-ISB_000_00 | B63: \\192.168.0.252\4.productie\CLIENTI\SCHAEFFLER\03_AUKB\EDS_AU_KB1636B-0208-ISB_000_00 | C63: SCHAEFFLER
A64: EDS_AU_KB2558B-0208-ISB_000_00 | B64: \\192.168.0.252\4.productie\CLIENTI\SCHAEFFLER\03_AUKB\EDS_AU_KB2558B-0208-ISB_000_00 | C64: SCHAEFFLER
A65: EDS_AU_KB3068B-0208-ISB_000_00 | B65: \\192.168.0.252\4.productie\CLIENTI\SCHAEFFLER\03_AUKB\EDS_AU_KB3068B-0208-ISB_000_00 | C65: SCHAEFFLER | D65: OK
A66: EDS_KB4080B-0208_000_AC | B66: \\192.168.0.252\4.productie\CLIENTI\SCHAEFFLER\03_AUKB\EDS_KB4080B-0208_000_AC | C66: SCHAEFFLER
A67: EDS_KB50100B-0208_000_AE | B67: \\192.168.0.252\4.productie\CLIENTI\SCHAEFFLER\03_AUKB\EDS_KB50100B-0208_000_AE | C67: SCHAEFFLER
A68: EDP F-586360-0191 A00 | B68: \\192.168.0.252\4.productie\CLIENTI\SCHAEFFLER\04_Inele\EDP F-586360-0191 A00 | C68: SCHAEFFLER
A69: EDP F-625593.03 | B69: \\192.168.0.252\4.productie\CLIENTI\SCHAEFFLER\04_Inele\EDP F-625593.03 | C69: SCHAEFFLER
A70: EDS AU.XU120222-12-ISB 004 | B70: \\192.168.0.252\4.productie\CLIENTI\SCHAEFFLER\04_Inele\EDS AU.XU120222-12-ISB 004 | C70: SCHAEFFLER
A71: EDS F-552668.01-0012-ISB 004 | B71: \\192.168.0.252\4.productie\CLIENTI\SCHAEFFLER\04_Inele\EDS F-552668.01-0012-ISB 004 | C71: SCHAEFFLER
A72: EDS F-556440-0012-ISB 004 AA | B72: \\192.168.0.252\4.productie\CLIENTI\SCHAEFFLER\04_Inele\EDS F-556440-0012-ISB 004 AA | C72: SCHAEFFLER
A73: EDS F-556440-0043.IR.XU-WW1 | B73: \\192.168.0.252\4.productie\CLIENTI\SCHAEFFLER\04_Inele\EDS F-556440-0043.IR.XU-WW1 | C73: SCHAEFFLER
A74: EDS F-674222-0151GHRGSPG-3006 | B74: \\192.168.0.252\4.productie\CLIENTI\SCHAEFFLER\04_Inele\EDS F-674222-0151GHRGSPG-3006 | C74: SCHAEFFLER
A75: EDS F-674222-0261.GHTSPG-3006 | B75: \\192.168.0.252\4.productie\CLIENTI\SCHAEFFLER\04_Inele\EDS F-674222-0261.GHTSPG-3006 | C75: SCHAEFFLER
A76: EDS F-674366-0151GHRGSPG-3006 | B76: \\192.168.0.252\4.productie\CLIENTI\SCHAEFFLER\04_Inele\EDS F-674366-0151GHRGSPG-3006 | C76: SCHAEFFLER
A77: EDS F-674366-0261 | B77: \\192.168.0.252\4.productie\CLIENTI\SCHAEFFLER\04_Inele\EDS F-674366-0261 | C77: SCHAEFFLER
... A87: F-153924-12-WW1 | B87: \\192.168.0.252\4.productie\CLIENTI\SCHAEFFLER\04_Inele\F-153924-12-WW1 | C87: SCHAEFFLER
A88: F-155077-13-WW1 | B88: \\192.168.0.252\4.productie\CLIENTI\SCHAEFFLER\04_Inele\F-155077-13-WW1 | C88: SCHAEFFLER | D88: OK
A89: F-155077-43-WW1 | B89: \\192.168.0.252\4.productie\CLIENTI\SCHAEFFLER\04_Inele\F-155077-43-WW1 | C89: SCHAEFFLER | D89: OK
A90: F-229209-0022-WW1 | B90: \\192.168.0.252\4.productie\CLIENTI\SCHAEFFLER\04_Inele\F-229209-0022-WW1 | C90: SCHAEFFLER
A91: F-229209-12-WW1 | B91: \\192.168.0.252\4.productie\CLIENTI\SCHAEFFLER\04_Inele\F-229209-12-WW1 | C91: SCHAEFFLER | D91: OK
A92: F-229461-12-WW1 | B92: \\192.168.0.252\4.productie\CLIENTI\SCHAEFFLER\04_Inele\F-229461-12-WW1 | C92: SCHAEFFLER | D92: OK
A93: F-235905-0013-WW1 | B93: \\192.168.0.252\4.productie\CLIENTI\SCHAEFFLER\04_Inele\F-235905-0013-WW1 | C93: SCHAEFFLER
A94: F-235905-0042-WW1 | B94: \\192.168.0.252\4.productie\CLIENTI\SCHAEFFLER\04_Inele\F-235905-0042-WW1 | C94: SCHAEFFLER | D94: OK | F94: GS
A95: F-552663-0012.AU.VU | B95: \\192.168.0.252\4.productie\CLIENTI\SCHAEFFLER\04_Inele\F-552663-0012.AU.VU | C95: SCHAEFFLER
A96: F-552668-0024 | B96: \\192.168.0.252\4.productie\CLIENTI\SCHAEFFLER\04_Inele\F-552668-0024 | C96: SCHAEFFLER | D96: OK
A97: F-552668-0044 | B97: \\192.168.0.252\4.productie\CLIENTI\SCHAEFFLER\04_Inele\F-552668-0044 | C97: SCHAEFFLER | D97: OK
A98: F-552668.01-0014 | B98: \\192.168.0.252\4.productie\CLIENTI\SCHAEFFLER\04_Inele\F-552668.01-0014 | C98: SCHAEFFLER | D98: OK
A99: F-552669-0023-ISB-HEAT | B99: \\192.168.0.252\4.productie\CLIENTI\SCHAEFFLER\04_Inele\F-552669-0023-ISB-HEAT | C99: SCHAEFFLER
A100: F-556440-0013.AU.XU-WW1 | B100: \\192.168.0.252\4.productie\CLIENTI\SCHAEFFLER\04_Inele\F-556440-0013.AU.XU-WW1 | C100: SCHAEFFLER
A101: XU160260ZT-43-WW1 | B101: \\192.168.0.252\4.productie\CLIENTI\SCHAEFFLER\04_Inele\XU160260ZT-43-WW1 | C101: SCHAEFFLER
A102: 19.F-556440-0010.AU.XU- strunjire dura | B102: \\192.168.0.252\4.productie\CLIENTI\SCHAEFFLER\05_Strunjire _Dura\19.F-556440-0010.AU.XU- strunjire dura | C102: SCHAEFFLER
A103: 1535100044 | B103: \\192.168.0.252\4.productie\CLIENTI\BOSCH GERMANIA\1535100044 | C103: BOSCH GERMANIA
A104: 1535100045 | B104: \\192.168.0.252\4.productie\CLIENTI\BOSCH GERMANIA\1535100045 | C104: BOSCH GERMANIA
A105: 1535100046 | B105: \\192.168.0.252\4.productie\CLIENTI\BOSCH GERMANIA\1535100046 | C105: BOSCH GERMANIA
A106: 1810326006 | B106: \\192.168.0.252\4.productie\CLIENTI\BOSCH GERMANIA\1810326006 | C106: BOSCH GERMANIA
A107: 1813218040 | B107: \\192.168.0.252\4.productie\CLIENTI\BOSCH GERMANIA\1813218040 | C107: BOSCH GERMANIA
A108: 1813218042 | B108: \\192.168.0.252\4.productie\CLIENTI\BOSCH GERMANIA\1813218042 | C108: BOSCH GERMANIA
A109: 1813218044 | B109: \\192.168.0.252\4.productie\CLIENTI\BOSCH GERMANIA\1813218044 | C109: BOSCH GERMANIA
A110: 1813218046 | B110: \\192.168.0.252\4.productie\CLIENTI\BOSCH GERMANIA\1813218046 | C110: BOSCH GERMANIA
A111: 1813218050 | B111: \\192.168.0.252\4.productie\CLIENTI\BOSCH GERMANIA\1813218050 | C111: BOSCH GERMANIA
...

Sheet Backlog+Comenzi de produs
B9: Order Type | C9: (All)
B10: Order Finished YES/NO | C10: No
B11: Quarters (ETA As requested dd.mm.yyyy) | C11: (All)
B13: Sum of Quantity | F13: Years | G13: Months | H13: ETA
F14: 2025 | G14: 2025 Total | H14: 2026 | K14: 2026 Total | L14: Grand Total
F15: Dec | H15: Jan | I15: Mar | J15: Apr
B16: CUSTOMER | C16: Product Family | D16: CUSTOMER PO# | E16: Part Number
B17: Schaeffler DE | C17: 0 | D17: 50589962 | E17: EDP PL.LFDL52-B-0021 000 | J17: 30 | K17: 30 | L17: 30
C18: 0 Total | J18: 30 | K18: 30 | L18: 30
C19: Adapterplatte | D19: 6049234 | E19: F-320745-0321.APL.ACT | I19: 260 | K19: 260 | L19: 260
D20: 50483888 | E20: F-320745-0321.APL.ACT | H20: 148 | K20: 148 | L20: 148
C21: Adapterplatte Total | H21: 148 | I21: 260 | K21: 408 | L21: 408
C22: Cover | D22: 6049233 | E22: F-320745-1901.DL.ACT15 | I22: 148 | K22: 148 | L22: 148
D23: 50483896 | E23: F-320745-1901.DL.ACT15 | H23: 146 | K23: 146 | L23: 146
C24: Cover Total | H24: 146 | I24: 148 | K24: 294 | L24: 294
C25: Druckstuck | D25: 6049236 | E25: F-320745-1401.BZ.ACT | I25: 143 | K25: 143 | L25: 143
D26: 50483858 | E26: F-320745-1401.BZ.ACT | F26: 143 | G26: 143 | L26: 143
C27: Druckstuck Total | F27: 143 | G27: 143 | I27: 143 | K27: 143 | L27: 286
C28: Sealing screw | D28: 6049232 | E28: F-320745-9001.VSHR.ACT | I28: 145 | K28: 145 | L28: 145
C29: Sealing screw Total | I29: 145 | K29: 145 | L29: 145
C30: sleeve | D30: 6049235 | E30: F-320745-1701.HUE.ACT | I30: 260 | K30: 260 | L30: 260
D31: 50483907 | E31: F-320745-1701.HUE.ACT | H31: 143 | K31: 143 | L31: 143
C32: sleeve Total | H32: 143 | I32: 260 | K32: 403 | L32: 403
B33: Schaeffler DE Total | F33: 143 | G33: 143 | H33: 437 | I33: 956 | J33: 30 | K33: 1423 | L33: 1566
B34: Grand Total | F34: 143 | G34: 143 | H34: 437 | I34: 956 | J34: 30 | K34: 1423 | L34: 1566

Sheet Registru unic-CLIENTI
Z1: REGISTRU UNIC DE LIVRARI la CLIENTI | AC1: din aceste date obtinem KPI 5
AL2: =TODAY() -> 45967
A8: SO DATA | J8: SC INPUT | K8: DATABASE FINISHED GOODS | S8: SC INPUT | AB8: DELIVERY INPUT | AJ8: ACCOUNTING
A9: CUSTOMER | B9: Order Type | C9: CUSTOMER PO# | D9: Date PO dd.mm.yyyy | E9: Part Number | F9: Part Description | G9: Drawing Revision | H9: Price/Unit EUR | I9: Quantity | J9: Price/Order | K9: ETA As requested dd.mm.yyyy | L9: ETA Confirmed dd.mm.yyyy | M9: ETA Planned dd.mm.yyyy | N9: Leadtime Contract days | O9: Product Family | P9: MOQ pcs | Q9: Frozen Zone days | R9: Status PPAP (approved/project) | S9: Mfg Lead Time days | T9: Subcontract | U9: Stock Warehouse pcs | V9: Scrap Rate | W9: Raw Material Status | X9: Incomming Date | Y9: Planned YES/NO | Z9: Work Order | AA9: Order Finished YES/NO | AB9: Dată de livrare | AC9: AVIZ OLSTRAL | AD9: COMANDĂ | AE9: REPER | AF9: OK | AG9: Sales | AH9: NOK | AI9: Observații | AJ9: Factură/Serie | AK9: OTD | AL9: Month | AM9: YEAR | AN9: Column1
A10: Schaeffler RO | B10: firm | C10: 7000971923 | D10: 45833 | E10: 154805.12 | F10: =IFERROR(VLOOKUP(Table1[[#This Row],[Part Number]],DATABASE_FG!$C$6:D9999,2,FALSE)," ") -> bucsa | G10: =IFERROR(_xlfn.XLOOKUP(Table1[[#This Row],[Part Number]],Table3[Part number],Table3[Drawing Revision]),"") -> 0 | H10: {=IFERROR(INDEX(PDB!$C:$AT,MATCH(E10,PDB!$B:$B,0),MATCH(YEAR(K10),0+PDB!$C$1:$AT$1,0)),"")} -> 5.32 | I10: 5 | J10: =IFERROR(Table1[[#This Row],[Quantity]]*Table1[[#This Row],[Price/Unit EUR]]," ") -> 26.6 | K10: 45838 | L10: =WEEKNUM(Table1[[#This Row],[ETA As requested dd.mm.yyyy]]) -> 27 | M10: =YEAR(Table1[[#This Row],[ETA As requested dd.mm.yyyy]]) -> 2025 | N10: =IFERROR(INDEX(DATABASE_FG!$H$5:$H$367, MATCH(E10, DATABASE_FG!$C$5:$C$367, 0)), " ") -> 0 | O10: =IF(E10<>"", _xlfn.XLOOKUP(E10, DATABASE_FG!C:C, DATABASE_FG!F:F), " ") -> Strunjire moale | P10: =IFERROR(INDEX(DATABASE_FG!$G$5:$G$367, MATCH(E10, DATABASE_FG!$C$5:$C$367, 0)), "Not Found") -> 0 | R10: approved | S10: =IFERROR(INDEX(DATABASE_FG!$L$5:$L$367, MATCH(E10, DATABASE_FG!$C$5:$C$367, 0)), " ") -> 0 | T10: no | AA10: Yes | AB10: 45835 | AC10: 26000 | AD10: =IF(NOT(ISBLANK(AC10)), C10, "") -> 7000971923 | AE10: =IF(NOT(ISBLANK(AC10)), E10, "") -> 154805.12 | AF10: 5 | AG10: =AF10*H10 -> 26.6 | AJ10: 20250802-27.06.2025 | AK10: =IF(AB10="", IF(K10 < TODAY(), "Late", ""), IF(AB10 <= K10 + 2, "On Time", "Late")) -> On Time | AL10: =TEXT(K10,"mmmm") -> June | AM10: =YEAR(Table1[[#This Row],[ETA As requested dd.mm.yyyy]]) -> 2025
A11: Schaeffler RO | B11: firm | C11: 7000971923 | D11: 45833 | E11: 154805.12 | F11: =IFERROR(VLOOKUP(Table1[[#This Row],[Part Number]],DATABASE_FG!$C$6:D10000,2,FALSE)," ") -> bucsa | G11: =IFERROR(_xlfn.XLOOKUP(Table1[[#This Row],[Part Number]],Table3[Part number],Table3[Drawing Revision]),"") -> 0 | H11: {=IFERROR(INDEX(PDB!$C:$AT,MATCH(E11,PDB!$B:$B,0),MATCH(YEAR(K11),0+PDB!$C$1:$AT$1,0)),"")} -> 5.32 | I11: 500 | J11: =IFERROR(Table1[[#This Row],[Quantity]]*Table1[[#This Row],[Price/Unit EUR]]," ") -> 2660 | K11: 45838 | L11: =WEEKNUM(Table1[[#This Row],[ETA As requested dd.mm.yyyy]]) -> 27 | M11: =YEAR(Table1[[#This Row],[ETA As requested dd.mm.yyyy]]) -> 2025 | N11: =IFERROR(INDEX(DATABASE_FG!$H$5:$H$367, MATCH(E11, DATABASE_FG!$C$5:$C$367, 0)), " ") -> 0 | O11: =IF(E11<>"", _xlfn.XLOOKUP(E11, DATABASE_FG!C:C, DATABASE_FG!F:F), " ") -> Strunjire moale | P11: =IFERROR(INDEX(DATABASE_FG!$G$5:$G$367, MATCH(E11, DATABASE_FG!$C$5:$C$367, 0)), "Not Found") -> 0 | R11: approved | S11: =IFERROR(INDEX(DATABASE_FG!$L$5:$L$367, MATCH(E11, DATABASE_FG!$C$5:$C$367, 0)), " ") -> 0 | T11: no | AA11: Yes | AB11: 45835 | AC11: 260002 | AD11: =IF(NOT(ISBLANK(AC11)), C11, "") -> 7000971923 | AE11: =IF(NOT(ISBLANK(AC11)), E11, "") -> 154805.12 | AF11: 500 | AG11: =AF11*H11 -> 2660 | AJ11: 20250803-27.06.2025 | AK11: =IF(AB11="", IF(K11 < TODAY(), "Late", ""), IF(AB11 <= K11 + 2, "On Time", "Late")) -> On Time | AL11: =TEXT(K11,"mmmm") -> June | AM11: =YEAR(Table1[[#This Row],[ETA As requested dd.mm.yyyy]]) -> 2025
A12: Walterscheid | B12: firm | C12: 5500000781 | D12: 45320 | E12: 557809 | F12: =IFERROR(VLOOKUP(Table1[[#This Row],[Part Number]],DATABASE_FG!$C$6:D10001,2,FALSE)," ") -> ANLAUFSCHEIBE | G12: =IFERROR(_xlfn.XLOOKUP(Table1[[#This Row],[Part Number]],Table3[Part number],Table3[Drawing Revision]),"") -> e | H12: {=IFERROR(INDEX(PDB!$C:$AT,MATCH(E12,PDB!$B:$B,0),MATCH(YEAR(K12),0+PDB!$C$1:$AT$1,0)),"")} -> 10.79 | I12: 100 | J12: =IFERROR(Table1[[#This Row],[Quantity]]*Table1[[#This Row],[Price/Unit EUR]]," ") -> 1079 | K12: 45392 | L12: =WEEKNUM(Table1[[#This Row],[ETA As requested dd.mm.yyyy]]) -> 15 | M12: =YEAR(Table1[[#This Row],[ETA As requested dd.mm.yyyy]]) -> 2024 | N12: =IFERROR(INDEX(DATABASE_FG!$H$5:$H$367, MATCH(E12, DATABASE_FG!$C$5:$C$367, 0)), " ") -> 0 | O12: =IF(E12<>"", _xlfn.XLOOKUP(E12, DATABASE_FG!C:C, DATABASE_FG!F:F), " ") -> 0 | P12: =IFERROR(INDEX(DATABASE_FG!$G$5:$G$367, MATCH(E12, DATABASE_FG!$C$5:$C$367, 0)), "Not Found") -> 200 | R12: approved | S12: =IFERROR(INDEX(DATABASE_FG!$L$5:$L$367, MATCH(E12, DATABASE_FG!$C$5:$C$367, 0)), " ") -> 56 | T12: yes | Z12: 240609 | AA12: Yes | AB12: 45404 | AC12: 2024387 | AD12: =IF(NOT(ISBLANK(AC12)), C12, "") -> 5500000781 | AE12: =IF(NOT(ISBLANK(AC12)), E12, "") -> 557809 | AF12: 100 | AG12: =AF12*H12 -> 1079 | AJ12: 20240425-22.04.2025 | AK12: =IF(AB12="", IF(K12 < TODAY(), "Late", ""), IF(AB12 <= K12 + 2, "On Time", "Late")) -> Late | AL12: =TEXT(K12,"mmmm") -> April | AM12: =YEAR(Table1[[#This Row],[ETA As requested dd.mm.yyyy]]) -> 2024
A13: Walterscheid | B13: firm | C13: 5500000781 | D13: 45320 | E13: 557809 | F13: =IFERROR(VLOOKUP(Table1[[#This Row],[Part Number]],DATABASE_FG!$C$6:D10002,2,FALSE)," ") -> ANLAUFSCHEIBE | G13: =IFERROR(_xlfn.XLOOKUP(Table1[[#This Row],[Part Number]],Table3[Part number],Table3[Drawing Revision]),"") -> e | H13: {=IFERROR(INDEX(PDB!$C:$AT,MATCH(E13,PDB!$B:$B,0),MATCH(YEAR(K13),0+PDB!$C$1:$AT$1,0)),"")} -> 10.79 | I13: 100 | J13: =IFERROR(Table1[[#This Row],[Quantity]]*Table1[[#This Row],[Price/Unit EUR]]," ") -> 1079 | K13: 45406 | L13: =WEEKNUM(Table1[[#This Row],[ETA As requested dd.mm.yyyy]]) -> 17 | M13: =YEAR(Table1[[#This Row],[ETA As requested dd.mm.yyyy]]) -> 2024 | N13: =IFERROR(INDEX(DATABASE_FG!$H$5:$H$367, MATCH(E13, DATABASE_FG!$C$5:$C$367, 0)), " ") -> 0 | O13: =IF(E13<>"", _xlfn.XLOOKUP(E13, DATABASE_FG!C:C, DATABASE_FG!F:F), " ") -> 0 | P13: =IFERROR(INDEX(DATABASE_FG!$G$5:$G$367, MATCH(E13, DATABASE_FG!$C$5:$C$367, 0)), "Not Found") -> 200 | R13: approved | S13: =IFERROR(INDEX(DATABASE_FG!$L$5:$L$367, MATCH(E13, DATABASE_FG!$C$5:$C$367, 0)), " ") -> 56 | T13: yes | Z13: 240609 | AA13: Yes | AB13: 45404 | AC13: 2024387 | AD13: =IF(NOT(ISBLANK(AC13)), C13, "") -> 5500000781 | AE13: =IF(NOT(ISBLANK(AC13)), E13, "") -> 557809 | AF13: 100 | AG13: =AF13*H13 -> 1079 | AJ13: 20240425-22.04.2025 | AK13: =IF(AB13="", IF(K13 < TODAY(), "Late", ""), IF(AB13 <= K13 + 2, "On Time", "Late")) -> On Time | AL13: =TEXT(K13,"mmmm") -> April | AM13: =YEAR(Table1[[#This Row],[ETA As requested dd.mm.yyyy]]) -> 2024
A14: Walterscheid | B14: firm | C14: 5500000781 | D14: 45320 | E14: 557809 | F14: =IFERROR(VLOOKUP(Table1[[#This Row],[Part Number]],DATABASE_FG!$C$6:D10003,2,FALSE)," ") -> ANLAUFSCHEIBE | G14: =IFERROR(_xlfn.XLOOKUP(Table1[[#This Row],[Part Number]],Table3[Part number],Table3[Drawing Revision]),"") -> e | H14: {=IFERROR(INDEX(PDB!$C:$AT,MATCH(E14,PDB!$B:$B,0),MATCH(YEAR(K14),0+PDB!$C$1:$AT$1,0)),"")} -> 10.79 | I14: 100 | J14: =IFERROR(Table1[[#This Row],[Quantity]]*Table1[[#This Row],[Price/Unit EUR]]," ") -> 1079 | K14: 45427 | L14: =WEEKNUM(Table1[[#This Row],[ETA As requested dd.mm.yyyy]]) -> 20 | M14: =YEAR(Table1[[#This Row],[ETA As requested dd.mm.yyyy]]) -> 2024 | N14: =IFERROR(INDEX(DATABASE_FG!$H$5:$H$367, MATCH(E14, DATABASE_FG!$C$5:$C$367, 0)), " ") -> 0 | O14: =IF(E14<>"", _xlfn.XLOOKUP(E14, DATABASE_FG!C:C, DATABASE_FG!F:F), " ") -> 0 | P14: =IFERROR(INDEX(DATABASE_FG!$G$5:$G$367, MATCH(E14, DATABASE_FG!$C$5:$C$367, 0)), "Not Found") -> 200 | R14: approved | S14: =IFERROR(INDEX(DATABASE_FG!$L$5:$L$367, MATCH(E14, DATABASE_FG!$C$5:$C$367, 0)), " ") -> 56 | T14: yes | Z14: 240609 | AA14: Yes | AB14: 45404 | AC14: 2024387 | AD14: =IF(NOT(ISBLANK(AC14)), C14, "") -> 5500000781 | AE14: =IF(NOT(ISBLANK(AC14)), E14, "") -> 557809 | AF14: 100 | AG14: =AF14*H14 -> 1079 | AJ14: 20240425-22.04.2025 | AK14: =IF(AB14="", IF(K14 < TODAY(), "Late", ""), IF(AB14 <= K14 + 2, "On Time", "Late")) -> On Time | AL14: =TEXT(K14,"mmmm") -> May | AM14: =YEAR(Table1[[#This Row],[ETA As requested dd.mm.yyyy]]) -> 2024
A15: Walterscheid | B15: firm | C15: 5500000781 | D15: 45320 | E15: 557809 | F15: =IFERROR(VLOOKUP(Table1[[#This Row],[Part Number]],DATABASE_FG!$C$6:D10004,2,FALSE)," ") -> ANLAUFSCHEIBE | G15: =IFERROR(_xlfn.XLOOKUP(Table1[[#This Row],[Part Number]],Table3[Part number],Table3[Drawing Revision]),"") -> e | H15: {=IFERROR(INDEX(PDB!$C:$AT,MATCH(E15,PDB!$B:$B,0),MATCH(YEAR(K15),0+PDB!$C$1:$AT$1,0)),"")} -> 10.79 | I15: 100 | J15: =IFERROR(Table1[[#This Row],[Quantity]]*Table1[[#This Row],[Price/Unit EUR]]," ") -> 1079 | K15: 45434 | L15: =WEEKNUM(Table1[[#This Row],[ETA As requested dd.mm.yyyy]]) -> 21 | M15: =YEAR(Table1[[#This Row],[ETA As requested dd.mm.yyyy]]) -> 2024 | N15: =IFERROR(INDEX(DATABASE_FG!$H$5:$H$367, MATCH(E15, DATABASE_FG!$C$5:$C$367, 0)), " ") -> 0 | O15: =IF(E15<>"", _xlfn.XLOOKUP(E15, DATABASE_FG!C:C, DATABASE_FG!F:F), " ") -> 0 | P15: =IFERROR(INDEX(DATABASE_FG!$G$5:$G$367, MATCH(E15, DATABASE_FG!$C$5:$C$367, 0)), "Not Found") -> 200 | R15: approved | S15: =IFERROR(INDEX(DATABASE_FG!$L$5:$L$367, MATCH(E15, DATABASE_FG!$C$5:$C$367, 0)), " ") -> 56 | T15: yes | Z15: 240609 | AA15: Yes | AB15: 45404 | AC15: 2024387 | AD15: =IF(NOT(ISBLANK(AC15)), C15, "") -> 5500000781 | AE15: =IF(NOT(ISBLANK(AC15)), E15, "") -> 557809 | AF15: 100 | AG15: =AF15*H15 -> 1079 | AJ15: 20240425-22.04.2025 | AK15: =IF(AB15="", IF(K15 < TODAY(), "Late", ""), IF(AB15 <= K15 + 2, "On Time", "Late")) -> On Time | AL15: =TEXT(K15,"mmmm") -> May | AM15: =YEAR(Table1[[#This Row],[ETA As requested dd.mm.yyyy]]) -> 2024
A16: Walterscheid | B16: firm | C16: 5500000781 | D16: 45320 | E16: 557809 | F16: =IFERROR(VLOOKUP(Table1[[#This Row],[Part Number]],DATABASE_FG!$C$6:D10005,2,FALSE)," ") -> ANLAUFSCHEIBE | G16: =IFERROR(_xlfn.XLOOKUP(Table1[[#This Row],[Part Number]],Table3[Part number],Table3[Drawing Revision]),"") -> e | H16: {=IFERROR(INDEX(PDB!$C:$AT,MATCH(E16,PDB!$B:$B,0),MATCH(YEAR(K16),0+PDB!$C$1:$AT$1,0)),"")} -> 10.79 | I16: 100 | J16: =IFERROR(Table1[[#This Row],[Quantity]]*Table1[[#This Row],[Price/Unit EUR]]," ") -> 1079 | K16: 45771 | L16: =WEEKNUM(Table1[[#This Row],[ETA As requested dd.mm.yyyy]]) -> 17 | M16: =YEAR(Table1[[#This Row],[ETA As requested dd.mm.yyyy]]) -> 2025 | N16: =IFERROR(INDEX(DATABASE_FG!$H$5:$H$367, MATCH(E16, DATABASE_FG!$C$5:$C$367, 0)), " ") -> 0 | P16: =IFERROR(INDEX(DATABASE_FG!$G$5:$G$367, MATCH(E16, DATABASE_FG!$C$5:$C$367, 0)), "Not Found") -> 200 | S16: =Table1[[#This Row],[Quantity]]/48 -> 2.0833333 | T16: yes | AA16: Yes | AB16: 45776 | AC16: 25687 | AD16: =IF(NOT(ISBLANK(AC16)), C16, "") -> 5500000781 | AE16: =IF(NOT(ISBLANK(AC16)), E16, "") -> 557809 | AF16: 100 | AG16: =AF16*H16 -> 1079 | AJ16: 20250565-29.04.2025 | AK16: =IF(AB16="", IF(K16 < TODAY(), "Late", ""), IF(AB16 <= K16 + 2, "On Time", "Late")) -> Late | AL16: =TEXT(K16,"mmmm") -> April | AM16: =YEAR(Table1[[#This Row],[ETA As requested dd.mm.yyyy]]) -> 2025
A17: Edwards | B17: firm | C17: 7018632237 | D17: 45125 | E17: 32166161 | F17: =IFERROR(VLOOKUP(Table1[[#This Row],[Part Number]],DATABASE_FG!$C$6:D10006,2,FALSE)," ") -> HV-ROTOR D8B PRE-MACHINED (6524466) | G17: =IFERROR(_xlfn.XLOOKUP(Table1[[#This Row],[Part Number]],Table3[Part number],Table3[Drawing Revision]),"") -> A1 | H17: {=IFERROR(INDEX(PDB!$C:$AT,MATCH(E17,PDB!$B:$B,0),MATCH(YEAR(K17),0+PDB!$C$1:$AT$1,0)),"")} | I17: 50 | J17: =IFERROR(Table1[[#This Row],[Quantity]]*Table1[[#This Row],[Price/Unit EUR]]," ") | K17: 45261 | L17: =WEEKNUM(Table1[[#This Row],[ETA As requested dd.mm.yyyy]]) -> 48 | M17: =YEAR(Table1[[#This Row],[ETA As requested dd.mm.yyyy]]) -> 2023 | N17: =IFERROR(INDEX(DATABASE_FG!$H$5:$H$367, MATCH(E17, DATABASE_FG!$C$5:$C$367, 0)), " ") -> 0 | O17: =IF(E17<>"", _xlfn.XLOOKUP(E17, DATABASE_FG!C:C, DATABASE_FG!F:F), " ") -> Rotor | P17: =IFERROR(INDEX(DATABASE_FG!$G$5:$G$367, MATCH(E17, DATABASE_FG!$C$5:$C$367, 0)), "Not Found") -> 50 | R17: project | S17: =IFERROR(INDEX(DATABASE_FG!$L$5:$L$367, MATCH(E17, DATABASE_FG!$C$5:$C$367, 0)), " ") -> 56 | T17: yes | AA17: Yes | AD17: =IF(NOT(ISBLANK(AC17)), C17, "") | AE17: =IF(NOT(ISBLANK(AC17)), E17, "") | AG17: =AF17*H17 -> #VALUE! | AI17: Proiect Anulat | AK17: =IF(AB17="", IF(K17 < TODAY(), "Late", ""), IF(AB17 <= K17 + 2, "On Time", "Late")) -> Late | AL17: =TEXT(K17,"mmmm") -> December | AM17: =YEAR(Table1[[#This Row],[ETA As requested dd.mm.yyyy]]) -> 2023
A18: Edwards | B18: firm | C18: 7018632237 | D18: 45125 | E18: 32166162 | F18: =IFERROR(VLOOKUP(Table1[[#This Row],[Part Number]],DATABASE_FG!$C$6:D10007,2,FALSE)," ") -> HV-ROTOR D16B PRE-MACHINED (6524201) | G18: =IFERROR(_xlfn.XLOOKUP(Table1[[#This Row],[Part Number]],Table3[Part number],Table3[Drawing Revision]),"") -> A0 | H18: {=IFERROR(INDEX(PDB!$C:$AT,MATCH(E18,PDB!$B:$B,0),MATCH(YEAR(K18),0+PDB!$C$1:$AT$1,0)),"")} | I18: 50 | J18: =IFERROR(Table1[[#This Row],[Quantity]]*Table1[[#This Row],[Price/Unit EUR]]," ") | K18: 45261 | L18: =WEEKNUM(Table1[[#This Row],[ETA As requested dd.mm.yyyy]]) -> 48 | M18: =YEAR(Table1[[#This Row],[ETA As requested dd.mm.yyyy]]) -> 2023 | N18: =IFERROR(INDEX(DATABASE_FG!$H$5:$H$367, MATCH(E18, DATABASE_FG!$C$5:$C$367, 0)), " ") -> 0 | O18: =IF(E18<>"", _xlfn.XLOOKUP(E18, DATABASE_FG!C:C, DATABASE_FG!F:F), " ") -> Rotor | P18: =IFERROR(INDEX(DATABASE_FG!$G$5:$G$367, MATCH(E18, DATABASE_FG!$C$5:$C$367, 0)), "Not Found") -> 50 | R18: project | S18: =IFERROR(INDEX(DATABASE_FG!$L$5:$L$367, MATCH(E18, DATABASE_FG!$C$5:$C$367, 0)), " ") -> 56 | T18: yes | AA18: Yes | AD18: =IF(NOT(ISBLANK(AC18)), C18, "") | AE18: =IF(NOT(ISBLANK(AC18)), E18, "") | AG18: =AF18*H18 -> #VALUE! | AI18: Proiect Anulat | AK18: =IF(AB18="", IF(K18 < TODAY(), "Late", ""), IF(AB18 <= K18 + 2, "On Time", "Late")) -> Late | AL18: =TEXT(K18,"mmmm") -> December | AM18: =YEAR(Table1[[#This Row],[ETA As requested dd.mm.yyyy]]) -> 2023
A19: BOSCH Homburg | B19: firm | C19: 4509573576 | D19: 45369 | E19: 1535100044 | F19: =IFERROR(VLOOKUP(Table1[[#This Row],[Part Number]],DATABASE_FG!$C$6:D10008,2,FALSE)," ") -> VALVE BODY . | G19: =IFERROR(_xlfn.XLOOKUP(Table1[[#This Row],[Part Number]],Table3[Part number],Table3[Drawing Revision]),"") -> AB | H19: {=IFERROR(INDEX(PDB!$C:$AT,MATCH(E19,PDB!$B:$B,0),MATCH(YEAR(K19),0+PDB!$C$1:$AT$1,0)),"")} -> 8.25 | I19: 509 | J19: =H19*I19 -> 4199.25 | K19: 45238 | L19: =WEEKNUM(Table1[[#This Row],[ETA As requested dd.mm.yyyy]]) -> 45 | M19: =YEAR(Table1[[#This Row],[ETA As requested dd.mm.yyyy]]) -> 2023 | N19: =IFERROR(INDEX(DATABASE_FG!$H$5:$H$367, MATCH(E19, DATABASE_FG!$C$5:$C$367, 0)), " ") -> 0 | O19: =IF(E19<>"", _xlfn.XLOOKUP(E19, DATABASE_FG!C:C, DATABASE_FG!F:F), " ") -> Ventilkoerper | P19: =IFERROR(INDEX(DATABASE_FG!$G$5:$G$367, MATCH(E19, DATABASE_FG!$C$5:$C$367, 0)), "Not Found") -> 550 | Q19: 60 | R19: approved | S19: =IFERROR(INDEX(DATABASE_FG!$L$5:$L$367, MATCH(E19, DATABASE_FG!$C$5:$C$367, 0)), " ") -> 56 | T19: yes | AA19: Yes | AB19: 45393 | AC19: 2024332 | AD19: =IF(NOT(ISBLANK(AC19)), C19, "") -> 4509573576 | AE19: =IF(NOT(ISBLANK(AC19)), E19, "") -> 1535100044 | AF19: 90 | AG19: =AF19*H19 -> 742.5 | AI19: livrata toata comanda, comanda inchisa in supplyon | AK19: =IF(AB19="", IF(K19 < TODAY(), "Late", ""), IF(AB19 <= K19 + 2, "On Time", "Late")) -> Late | AL19: =TEXT(K19,"mmmm") -> November | AM19: =YEAR(Table1[[#This Row],[ETA As requested dd.mm.yyyy]]) -> 2023
A20: BOSCH Homburg | B20: firm | C20: 5500495155 | D20: 45491 | E20: 1535100044 | F20: =IFERROR(VLOOKUP(Table1[[#This Row],[Part Number]],DATABASE_FG!$C$6:D10009,2,FALSE)," ") -> VALVE BODY . | G20: =IFERROR(_xlfn.XLOOKUP(Table1[[#This Row],[Part Number]],Table3[Part number],Table3[Drawing Revision]),"") -> AB | H20: {=IFERROR(INDEX(PDB!$C:$AT,MATCH(E20,PDB!$B:$B,0),MATCH(YEAR(K20),0+PDB!$C$1:$AT$1,0)),"")} -> 8.25 | I20: 5 | J20: =H20*I20 -> 41.25 | K20: 45403 | L20: =WEEKNUM(Table1[[#This Row],[ETA As requested dd.mm.yyyy]]) -> 17 | M20: =YEAR(Table1[[#This Row],[ETA As requested dd.mm.yyyy]]) -> 2024 | N20: =IFERROR(INDEX(DATABASE_FG!$H$5:$H$367, MATCH(E20, DATABASE_FG!$C$5:$C$367, 0)), " ") -> 0 | O20: =IF(E20<>"", _xlfn.XLOOKUP(E20, DATABASE_FG!C:C, DATABASE_FG!F:F), " ") -> Ventilkoerper | P20: =IFERROR(INDEX(DATABASE_FG!$G$5:$G$367, MATCH(E20, DATABASE_FG!$C$5:$C$367, 0)), "Not Found") -> 550 | Q20: 60 | R20: approved | S20: =IFERROR(INDEX(DATABASE_FG!$L$5:$L$367, MATCH(E20, DATABASE_FG!$C$5:$C$367, 0)), " ") -> 56 | T20: yes | Z20: 241307 | AA20: Yes | AB20: 45394 | AC20: 2024338 | AD20: =IF(NOT(ISBLANK(AC20)), C20, "") -> 5500495155 | AE20: =IF(NOT(ISBLANK(AC20)), E20, "") -> 1535100044 | AF20: 5 | AG20: =AF20*H20 -> 41.25 | AK20: =IF(AB20="", IF(K20 < TODAY(), "Late", ""), IF(AB20 <= K20 + 2, "On Time", "Late")) -> On Time | AL20: =TEXT(K20,"mmmm") -> April | AM20: =YEAR(Table1[[#This Row],[ETA As requested dd.mm.yyyy]]) -> 2024
A21: BOSCH Homburg | B21: firm | C21: 5500495155 | D21: 45491 | E21: 1535100044 | F21: =IFERROR(VLOOKUP(Table1[[#This Row],[Part Number]],DATABASE_FG!$C$6:D10010,2,FALSE)," ") -> VALVE BODY . | G21: =IFERROR(_xlfn.XLOOKUP(Table1[[#This Row],[Part Number]],Table3[Part number],Table3[Drawing Revision]),"") -> AB | H21: {=IFERROR(INDEX(PDB!$C:$AT,MATCH(E21,PDB!$B:$B,0),MATCH(YEAR(K21),0+PDB!$C$1:$AT$1,0)),"")} -> 8.25 | I21: 4 | J21: =H21*I21 -> 33 | K21: 45741 | L21: =WEEKNUM(Table1[[#This Row],[ETA As requested dd.mm.yyyy]]) -> 13 | M21: =YEAR(Table1[[#This Row],[ETA As requested dd.mm.yyyy]]) -> 2025 | N21: =IFERROR(INDEX(DATABASE_FG!$H$5:$H$367, MATCH(E21, DATABASE_FG!$C$5:$C$367, 0)), " ") -> 0 | O21: =IF(E21<>"", _xlfn.XLOOKUP(E21, DATABASE_FG!C:C, DATABASE_FG!F:F), " ") -> Ventilkoerper | P21: =IFERROR(INDEX(DATABASE_FG!$G$5:$G$367, MATCH(E21, DATABASE_FG!$C$5:$C$367, 0)), "Not Found") -> 550 | Q21: 60 | R21: approved | S21: =IFERROR(INDEX(DATABASE_FG!$L$5:$L$367, MATCH(E21, DATABASE_FG!$C$5:$C$367, 0)), " ") -> 56 | T21: yes | AA21: Yes | AB21: 45394 | AC21: 2024338 | AD21: =IF(NOT(ISBLANK(AC21)), C21, "") -> 5500495155 | AE21: =IF(NOT(ISBLANK(AC21)), E21, "") -> 1535100044 | AF21: 4 | AG21: =AF21*H21 -> 33 | AK21: =IF(AB21="", IF(K21 < TODAY(), "Late", ""), IF(AB21 <= K21 + 2, "On Time", "Late")) -> On Time | AL21: =TEXT(K21,"mmmm") -> March | AM21: =YEAR(Table1[[#This Row],[ETA As requested dd.mm.yyyy]]) -> 2025
A22: BOSCH Homburg | B22: firm | C22: 5500495155 | D22: 45749 | E22: 1535100044 | F22: =IFERROR(VLOOKUP(Table1[[#This Row],[Part Number]],DATABASE_FG!$C$6:D10011,2,FALSE)," ") -> VALVE BODY . | G22: =IFERROR(_xlfn.XLOOKUP(Table1[[#This Row],[Part Number]],Table3[Part number],Table3[Drawing Revision]),"") -> AB | H22: {=IFERROR(INDEX(PDB!$C:$AT,MATCH(E22,PDB!$B:$B,0),MATCH(YEAR(K22),0+PDB!$C$1:$AT$1,0)),"")} -> 8.25 | I22: 85 | J22: =IFERROR(Table1[[#This Row],[Quantity]]*Table1[[#This Row],[Price/Unit EUR]]," ") -> 701.25 | K22: 45789 | L22: =WEEKNUM(Table1[[#This Row],[ETA As requested dd.mm.yyyy]]) -> 20 | M22: =YEAR(Table1[[#This Row],[ETA As requested dd.mm.yyyy]]) -> 2025 | N22: =IFERROR(INDEX(DATABASE_FG!$H$5:$H$367, MATCH(E22, DATABASE_FG!$C$5:$C$367, 0)), " ") -> 0 | O22: =IF(E22<>"", _xlfn.XLOOKUP(E22, DATABASE_FG!C:C, DATABASE_FG!F:F), " ") -> Ventilkoerper | P22: =IFERROR(INDEX(DATABASE_FG!$G$5:$G$367, MATCH(E22, DATABASE_FG!$C$5:$C$367, 0)), "Not Found") -> 550 | Q22: 56 | R22: approved | S22: =IFERROR(INDEX(DATABASE_FG!$L$5:$L$367, MATCH(E22, DATABASE_FG!$C$5:$C$367, 0)), " ") -> 56 | T22: yes | W22: yes | Y22: produse | AA22: Yes | AB22: 45811 | AC22: 25868 | AD22: =IF(NOT(ISBLANK(AC22)), C22, "") -> 5500495155 | AE22: =IF(NOT(ISBLANK(AC22)), E22, "") -> 1535100044 | AF22: 85 | AG22: =AF22*H22 -> 701.25 | AJ22: 20250699-03.06.2025 | AK22: =IF(AB22="", IF(K22 < TODAY(), "Late", ""), IF(AB22 <= K22 + 2, "On Time", "Late")) -> Late | AL22: =TEXT(K22,"mmmm") -> May | AM22: =YEAR(Table1[[#This Row],[ETA As requested dd.mm.yyyy]]) -> 2025
A23: BOSCH Homburg | B23: firm | C23: 5500495155 | D23: 45749 | E23: 1535100044 | F23: =IFERROR(VLOOKUP(Table1[[#This Row],[Part Number]],DATABASE_FG!$C$6:D10012,2,FALSE)," ") -> VALVE BODY . | G23: =IFERROR(_xlfn.XLOOKUP(Table1[[#This Row],[Part Number]],Table3[Part number],Table3[Drawing Revision]),"") -> AB | H23: {=IFERROR(INDEX(PDB!$C:$AT,MATCH(E23,PDB!$B:$B,0),MATCH(YEAR(K23),0+PDB!$C$1:$AT$1,0)),"")} -> 8.25 | I23: =165+9 -> 174 | J23: =IFERROR(Table1[[#This Row],[Quantity]]*Table1[[#This Row],[Price/Unit EUR]]," ") -> 1435.5 | K23: 46006 | L23: =WEEKNUM(Table1[[#This Row],[ETA As requested dd.mm.yyyy]]) -> 51 | M23: =YEAR(Table1[[#This Row],[ETA As requested dd.mm.yyyy]]) -> 2025 | N23: =IFERROR(INDEX(DATABASE_FG!$H$5:$H$367, MATCH(E23, DATABASE_FG!$C$5:$C$367, 0)), " ") -> 0 | O23: =IF(E23<>"", _xlfn.XLOOKUP(E23, DATABASE_FG!C:C, DATABASE_FG!F:F), " ") -> Ventilkoerper | P23: =IFERROR(INDEX(DATABASE_FG!$G$5:$G$367, MATCH(E23, DATABASE_FG!$C$5:$C$367, 0)), "Not Found") -> 550 | Q23: 56 | R23: approved | S23: =IFERROR(INDEX(DATABASE_FG!$L$5:$L$367, MATCH(E23, DATABASE_FG!$C$5:$C$367, 0)), " ") -> 56 | T23: yes | AA23: Yes | AB23: 45859 | AC23: 251082 | AD23: =IF(NOT(ISBLANK(AC23)), C23, "") -> 5500495155 | AE23: =IF(NOT(ISBLANK(AC23)), E23, "") -> 1535100044 | AF23: 174 | AG23: =AF23*H23 -> 1435.5 | AJ23: 20250960-24.07.2025 | AK23: =IF(AB23="", IF(K23 < TODAY(), "Late", ""), IF(AB23 <= K23 + 2, "On Time", "Late")) -> On Time | AL23: =TEXT(K23,"mmmm") -> December | AM23: =YEAR(Table1[[#This Row],[ETA As requested dd.mm.yyyy]]) -> 2025
A24: BOSCH Homburg | B24: forecast | C24: 5500495155 | D24: 45749 | E24: 1535100044 | F24: =IFERROR(VLOOKUP(Table1[[#This Row],[Part Number]],DATABASE_FG!$C$6:D10013,2,FALSE)," ") -> VALVE BODY . | G24: =IFERROR(_xlfn.XLOOKUP(Table1[[#This Row],[Part Number]],Table3[Part number],Table3[Drawing Revision]),"") -> AB | H24: {=IFERROR(INDEX(PDB!$C:$AT,MATCH(E24,PDB!$B:$B,0),MATCH(YEAR(K24),0+PDB!$C$1:$AT$1,0)),"")} -> 0 | I24: =25-9 -> 16 | J24: =IFERROR(Table1[[#This Row],[Quantity]]*Table1[[#This Row],[Price/Unit EUR]]," ") -> 0 | K24: 46048 | L24: =WEEKNUM(Table1[[#This Row],[ETA As requested dd.mm.yyyy]]) -> 5 | M24: =YEAR(Table1[[#This Row],[ETA As requested dd.mm.yyyy]]) -> 2026 | N24: =IFERROR(INDEX(DATABASE_FG!$H$5:$H$367, MATCH(E24, DATABASE_FG!$C$5:$C$367, 0)), " ") -> 0 | O24: =IF(E24<>"", _xlfn.XLOOKUP(E24, DATABASE_FG!C:C, DATABASE_FG!F:F), " ") -> Ventilkoerper | P24: =IFERROR(INDEX(DATABASE_FG!$G$5:$G$367, MATCH(E24, DATABASE_FG!$C$5:$C$367, 0)), "Not Found") -> 550 | Q24: 56 | R24: approved | S24: =IFERROR(INDEX(DATABASE_FG!$L$5:$L$367, MATCH(E24, DATABASE_FG!$C$5:$C$367, 0)), " ") -> 56 | T24: yes | AA24: No | AD24: =IF(NOT(ISBLANK(AC24)), C24, "") | AE24: =IF(NOT(ISBLANK(AC24)), E24, "") | AG24: =AF24*H24 -> 0 | AK24: =IF(AB24="", IF(K24 < TODAY(), "Late", ""), IF(AB24 <= K24 + 2, "On Time", "Late")) | AL24: =TEXT(K24,"mmmm") -> January | AM24: =YEAR(Table1[[#This Row],[ETA As requested dd.mm.yyyy]]) -> 2026
A25: BOSCH Homburg | B25: forecast | C25: 5500495155 | D25: 45749 | E25: 1535100044 | F25: =IFERROR(VLOOKUP(Table1[[#This Row],[Part Number]],DATABASE_FG!$C$6:D10014,2,FALSE)," ") -> VALVE BODY . | G25: =IFERROR(_xlfn.XLOOKUP(Table1[[#This Row],[Part Number]],Table3[Part number],Table3[Drawing Revision]),"") -> AB | H25: {=IFERROR(INDEX(PDB!$C:$AT,MATCH(E25,PDB!$B:$B,0),MATCH(YEAR(K25),0+PDB!$C$1:$AT$1,0)),"")} -> 0 | I25: 15 | J25: =IFERROR(Table1[[#This Row],[Quantity]]*Table1[[#This Row],[Price/Unit EUR]]," ") -> 0 | K25: 46076 | L25: =WEEKNUM(Table1[[#This Row],[ETA As requested dd.mm.yyyy]]) -> 9 | M25: =YEAR(Table1[[#This Row],[ETA As requested dd.mm.yyyy]]) -> 2026 | N25: =IFERROR(INDEX(DATABASE_FG!$H$5:$H$367, MATCH(E25, DATABASE_FG!$C$5:$C$367, 0)), " ") -> 0 | O25: =IF(E25<>"", _xlfn.XLOOKUP(E25, DATABASE_FG!C:C, DATABASE_FG!F:F), " ") -> Ventilkoerper | P25: =IFERROR(INDEX(DATABASE_FG!$G$5:$G$367, MATCH(E25, DATABASE_FG!$C$5:$C$367, 0)), "Not Found") -> 550 | Q25: 56 | R25: approved | S25: =IFERROR(INDEX(DATABASE_FG!$L$5:$L$367, MATCH(E25, DATABASE_FG!$C$5:$C$367, 0)), " ") -> 56 | T25: yes | AA25: No | AD25: =IF(NOT(ISBLANK(AC25)), C25, "") | AE25: =IF(NOT(ISBLANK(AC25)), E25, "") | AG25: =AF25*H25 -> 0 | AK25: =IF(AB25="", IF(K25 < TODAY(), "Late", ""), IF(AB25 <= K25 + 2, "On Time", "Late")) | AL25: =TEXT(K25,"mmmm") -> February | AM25: =YEAR(Table1[[#This Row],[ETA As requested dd.mm.yyyy]]) -> 2026
A26: BOSCH Homburg | B26: forecast | C26: 5500495155 | D26: 45749 | E26: 1535100044 | F26: =IFERROR(VLOOKUP(Table1[[#This Row],[Part Number]],DATABASE_FG!$C$6:D10015,2,FALSE)," ") -> VALVE BODY . | G26: =IFERROR(_xlfn.XLOOKUP(Table1[[#This Row],[Part Number]],Table3[Part number],Table3[Drawing Revision]),"") -> AB | H26: {=IFERROR(INDEX(PDB!$C:$AT,MATCH(E26,PDB!$B:$B,0),MATCH(YEAR(K26),0+PDB!$C$1:$AT$1,0)),"")} -> 0 | I26: 45 | J26: =IFERROR(Table1[[#This Row],[Quantity]]*Table1[[#This Row],[Price/Unit EUR]]," ") -> 0 | K26: 46106 | L26: =WEEKNUM(Table1[[#This Row],[ETA As requested dd.mm.yyyy]]) -> 13 | M26: =YEAR(Table1[[#This Row],[ETA As requested dd.mm.yyyy]]) -> 2026 | N26: =IFERROR(INDEX(DATABASE_FG!$H$5:$H$367, MATCH(E26, DATABASE_FG!$C$5:$C$367, 0)), " ") -> 0 | O26: =IF(E26<>"", _xlfn.XLOOKUP(E26, DATABASE_FG!C:C, DATABASE_FG!F:F), " ") -> Ventilkoerper | P26: =IFERROR(INDEX(DATABASE_FG!$G$5:$G$367, MATCH(E26, DATABASE_FG!$C$5:$C$367, 0)), "Not Found") -> 550 | Q26: 56 | R26: approved | S26: =IFERROR(INDEX(DATABASE_FG!$L$5:$L$367, MATCH(E26, DATABASE_FG!$C$5:$C$367, 0)), " ") -> 56 | T26: yes | AA26: No | AD26: =IF(NOT(ISBLANK(AC26)), C26, "") | AE26: =IF(NOT(ISBLANK(AC26)), E26, "") | AG26: =AF26*H26 -> 0 | AK26: =IF(AB26="", IF(K26 < TODAY(), "Late", ""), IF(AB26 <= K26 + 2, "On Time", "Late")) | AL26: =TEXT(K26,"mmmm") -> March | AM26: =YEAR(Table1[[#This Row],[ETA As requested dd.mm.yyyy]]) -> 2026
A27: BOSCH Homburg | B27: forecast | C27: 5500495155 | D27: 45749 | E27: 1535100044 | F27: =IFERROR(VLOOKUP(Table1[[#This Row],[Part Number]],DATABASE_FG!$C$6:D10016,2,FALSE)," ") -> VALVE BODY . | G27: =IFERROR(_xlfn.XLOOKUP(Table1[[#This Row],[Part Number]],Table3[Part number],Table3[Drawing Revision]),"") -> AB | H27: {=IFERROR(INDEX(PDB!$C:$AT,MATCH(E27,PDB!$B:$B,0),MATCH(YEAR(K27),0+PDB!$C$1:$AT$1,0)),"")} -> 0 | I27: 30 | J27: =IFERROR(Table1[[#This Row],[Quantity]]*Table1[[#This Row],[Price/Unit EUR]]," ") -> 0 | K27: 46136 | L27: =WEEKNUM(Table1[[#This Row],[ETA As requested dd.mm.yyyy]]) -> 17 | M27: =YEAR(Table1[[#This Row],[ETA As requested dd.mm.yyyy]]) -> 2026 | N27: =IFERROR(INDEX(DATABASE_FG!$H$5:$H$367, MATCH(E27, DATABASE_FG!$C$5:$C$367, 0)), " ") -> 0 | O27: =IF(E27<>"", _xlfn.XLOOKUP(E27, DATABASE_FG!C:C, DATABASE_FG!F:F), " ") -> Ventilkoerper | P27: =IFERROR(INDEX(DATABASE_FG!$G$5:$G$367, MATCH(E27, DATABASE_FG!$C$5:$C$367, 0)), "Not Found") -> 550 | Q27: 56 | R27: approved | S27: =IFERROR(INDEX(DATABASE_FG!$L$5:$L$367, MATCH(E27, DATABASE_FG!$C$5:$C$367, 0)), " ") -> 56 | T27: yes | AA27: No | AD27: =IF(NOT(ISBLANK(AC27)), C27, "") | AE27: =IF(NOT(ISBLANK(AC27)), E27, "") | AG27: =AF27*H27 -> 0 | AK27: =IF(AB27="", IF(K27 < TODAY(), "Late", ""), IF(AB27 <= K27 + 2, "On Time", "Late")) | AL27: =TEXT(K27,"mmmm") -> April | AM27: =YEAR(Table1[[#This Row],[ETA As requested dd.mm.yyyy]]) -> 2026
A28: BOSCH Homburg | B28: forecast | C28: 5500495155 | D28: 45749 | E28: 1535100044 | F28: =IFERROR(VLOOKUP(Table1[[#This Row],[Part Number]],DATABASE_FG!$C$6:D10017,2,FALSE)," ") -> VALVE BODY . | G28: =IFERROR(_xlfn.XLOOKUP(Table1[[#This Row],[Part Number]],Table3[Part number],Table3[Drawing Revision]),"") -> AB | H28: {=IFERROR(INDEX(PDB!$C:$AT,MATCH(E28,PDB!$B:$B,0),MATCH(YEAR(K28),0+PDB!$C$1:$AT$1,0)),"")} -> 0 | I28: 35 | J28: =IFERROR(Table1[[#This Row],[Quantity]]*Table1[[#This Row],[Price/Unit EUR]]," ") -> 0 | K28: 46164 | L28: =WEEKNUM(Table1[[#This Row],[ETA As requested dd.mm.yyyy]]) -> 21 | M28: =YEAR(Table1[[#This Row],[ETA As requested dd.mm.yyyy]]) -> 2026 | N28: =IFERROR(INDEX(DATABASE_FG!$H$5:$H$367, MATCH(E28, DATABASE_FG!$C$5:$C$367, 0)), " ") -> 0 | O28: =IF(E28<>"", _xlfn.XLOOKUP(E28, DATABASE_FG!C:C, DATABASE_FG!F:F), " ") -> Ventilkoerper | P28: =IFERROR(INDEX(DATABASE_FG!$G$5:$G$367, MATCH(E28, DATABASE_FG!$C$5:$C$367, 0)), "Not Found") -> 550 | Q28: 56 | R28: approved | S28: =IFERROR(INDEX(DATABASE_FG!$L$5:$L$367, MATCH(E28, DATABASE_FG!$C$5:$C$367, 0)), " ") -> 56 | T28: yes | AA28: No | AD28: =IF(NOT(ISBLANK(AC28)), C28, "") | AE28: =IF(NOT(ISBLANK(AC28)), E28, "") | AG28: =AF28*H28 -> 0 | AK28: =IF(AB28="", IF(K28 < TODAY(), "Late", ""), IF(AB28 <= K28 + 2, "On Time", "Late")) | AL28: =TEXT(K28,"mmmm") -> May | AM28: =YEAR(Table1[[#This Row],[ETA As requested dd.mm.yyyy]]) -> 2026
A29: BOSCH Homburg | B29: forecast | C29: 5500495155 | D29: 45749 | E29: 1535100044 | F29: =IFERROR(VLOOKUP(Table1[[#This Row],[Part Number]],DATABASE_FG!$C$6:D10018,2,FALSE)," ") -> VALVE BODY . | G29: =IFERROR(_xlfn.XLOOKUP(Table1[[#This Row],[Part Number]],Table3[Part number],Table3[Drawing Revision]),"") -> AB | H29: {=IFERROR(INDEX(PDB!$C:$AT,MATCH(E29,PDB!$B:$B,0),MATCH(YEAR(K29),0+PDB!$C$1:$AT$1,0)),"")} -> 0 | I29: 15 | J29: =IFERROR(Table1[[#This Row],[Quantity]]*Table1[[#This Row],[Price/Unit EUR]]," ") -> 0 | K29: 46197 | L29: =WEEKNUM(Table1[[#This Row],[ETA As requested dd.mm.yyyy]]) -> 26 | M29: =YEAR(Table1[[#This Row],[ETA As requested dd.mm.yyyy]]) -> 2026 | N29: =IFERROR(INDEX(DATABASE_FG!$H$5:$H$367, MATCH(E29, DATABASE_FG!$C$5:$C$367, 0)), " ") -> 0 | O29: =IF(E29<>"", _xlfn.XLOOKUP(E29, DATABASE_FG!C:C, DATABASE_FG!F:F), " ") -> Ventilkoerper | P29: =IFERROR(INDEX(DATABASE_FG!$G$5:$G$367, MATCH(E29, DATABASE_FG!$C$5:$C$367, 0)), "Not Found") -> 550 | Q29: 56 | R29: approved | S29: =IFERROR(INDEX(DATABASE_FG!$L$5:$L$367, MATCH(E29, DATABASE_FG!$C$5:$C$367, 0)), " ") -> 56 | T29: yes | AA29: No | AD29: =IF(NOT(ISBLANK(AC29)), C29, "") | AE29: =IF(NOT(ISBLANK(AC29)), E29, "") | AG29: =AF29*H29 -> 0 | AK29: =IF(AB29="", IF(K29 < TODAY(), "Late", ""), IF(AB29 <= K29 + 2, "On Time", "Late")) | AL29: =TEXT(K29,"mmmm") -> June | AM29: =YEAR(Table1[[#This Row],[ETA As requested dd.mm.yyyy]]) -> 2026
A30: BOSCH Homburg | B30: forecast | C30: 5500495155 | D30: 45749 | E30: 1535100044 | F30: =IFERROR(VLOOKUP(Table1[[#This Row],[Part Number]],DATABASE_FG!$C$6:D10019,2,FALSE)," ") -> VALVE BODY . | G30: =IFERROR(_xlfn.XLOOKUP(Table1[[#This Row],[Part Number]],Table3[Part number],Table3[Drawing Revision]),"") -> AB | H30: {=IFERROR(INDEX(PDB!$C:$AT,MATCH(E30,PDB!$B:$B,0),MATCH(YEAR(K30),0+PDB!$C$1:$AT$1,0)),"")} -> 0 | I30: 30 | J30: =IFERROR(Table1[[#This Row],[Quantity]]*Table1[[#This Row],[Price/Unit EUR]]," ") -> 0 | K30: 46230 | L30: =WEEKNUM(Table1[[#This Row],[ETA As requested dd.mm.yyyy]]) -> 31 | M30: =YEAR(Table1[[#This Row],[ETA As requested dd.mm.yyyy]]) -> 2026 | N30: =IFERROR(INDEX(DATABASE_FG!$H$5:$H$367, MATCH(E30, DATABASE_FG!$C$5:$C$367, 0)), " ") -> 0 | O30: =IF(E30<>"", _xlfn.XLOOKUP(E30, DATABASE_FG!C:C, DATABASE_FG!F:F), " ") -> Ventilkoerper | P30: =IFERROR(INDEX(DATABASE_FG!$G$5:$G$367, MATCH(E30, DATABASE_FG!$C$5:$C$367, 0)), "Not Found") -> 550 | Q30: 56 | R30: approved | S30: =IFERROR(INDEX(DATABASE_FG!$L$5:$L$367, MATCH(E30, DATABASE_FG!$C$5:$C$367, 0)), " ") -> 56 | T30: yes | AA30: No | AD30: =IF(NOT(ISBLANK(AC30)), C30, "") | AE30: =IF(NOT(ISBLANK(AC30)), E30, "") | AG30: =AF30*H30 -> 0 | AK30: =IF(AB30="", IF(K30 < TODAY(), "Late", ""), IF(AB30 <= K30 + 2, "On Time", "Late")) | AL30: =TEXT(K30,"mmmm") -> July | AM30: =YEAR(Table1[[#This Row],[ETA As requested dd.mm.yyyy]]) -> 2026
A31: BOSCH Homburg | B31: forecast | C31: 5500495155 | D31: 45749 | E31: 1535100044 | F31: =IFERROR(VLOOKUP(Table1[[#This Row],[Part Number]],DATABASE_FG!$C$6:D10020,2,FALSE)," ") -> VALVE BODY . | G31: =IFERROR(_xlfn.XLOOKUP(Table1[[#This Row],[Part Number]],Table3[Part number],Table3[Drawing Revision]),"") -> AB | H31: {=IFERROR(INDEX(PDB!$C:$AT,MATCH(E31,PDB!$B:$B,0),MATCH(YEAR(K31),0+PDB!$C$1:$AT$1,0)),"")} -> 0 | I31: 30 | J31: =IFERROR(Table1[[#This Row],[Quantity]]*Table1[[#This Row],[Price/Unit EUR]]," ") -> 0 | K31: 46259 | L31: =WEEKNUM(Table1[[#This Row],[ETA As requested dd.mm.yyyy]]) -> 35 | M31: =YEAR(Table1[[#This Row],[ETA As requested dd.mm.yyyy]]) -> 2026 | N31: =IFERROR(INDEX(DATABASE_FG!$H$5:$H$367, MATCH(E31, DATABASE_FG!$C$5:$C$367, 0)), " ") -> 0 | O31: =IF(E31<>"", _xlfn.XLOOKUP(E31, DATABASE_FG!C:C, DATABASE_FG!F:F), " ") -> Ventilkoerper | P31: =IFERROR(INDEX(DATABASE_FG!$G$5:$G$367, MATCH(E31, DATABASE_FG!$C$5:$C$367, 0)), "Not Found") -> 550 | Q31: 56 | R31: approved | S31: =IFERROR(INDEX(DATABASE_FG!$L$5:$L$367, MATCH(E31, DATABASE_FG!$C$5:$C$367, 0)), " ") -> 56 | T31: yes | AA31: No | AD31: =IF(NOT(ISBLANK(AC31)), C31, "") | AE31: =IF(NOT(ISBLANK(AC31)), E31, "") | AG31: =AF31*H31 -> 0 | AK31: =IF(AB31="", IF(K31 < TODAY(), "Late", ""), IF(AB31 <= K31 + 2, "On Time", "Late")) | AL31: =TEXT(K31,"mmmm") -> August | AM31: =YEAR(Table1[[#This Row],[ETA As requested dd.mm.yyyy]]) -> 2026
A32: BOSCH Homburg | B32: forecast | C32: 5500495155 | D32: 45749 | E32: 1535100044 | F32: =IFERROR(VLOOKUP(Table1[[#This Row],[Part Number]],DATABASE_FG!$C$6:D10021,2,FALSE)," ") -> VALVE BODY . | G32: =IFERROR(_xlfn.XLOOKUP(Table1[[#This Row],[Part Number]],Table3[Part number],Table3[Drawing Revision]),"") -> AB | H32: {=IFERROR(INDEX(PDB!$C:$AT,MATCH(E32,PDB!$B:$B,0),MATCH(YEAR(K32),0+PDB!$C$1:$AT$1,0)),"")} -> 0 | I32: 25 | J32: =IFERROR(Table1[[#This Row],[Quantity]]*Table1[[#This Row],[Price/Unit EUR]]," ") -> 0 | K32: 46289 | L32: =WEEKNUM(Table1[[#This Row],[ETA As requested dd.mm.yyyy]]) -> 39 | M32: =YEAR(Table1[[#This Row],[ETA As requested dd.mm.yyyy]]) -> 2026 | N32: =IFERROR(INDEX(DATABASE_FG!$H$5:$H$367, MATCH(E32, DATABASE_FG!$C$5:$C$367, 0)), " ") -> 0 | O32: =IF(E32<>"", _xlfn.XLOOKUP(E32, DATABASE_FG!C:C, DATABASE_FG!F:F), " ") -> Ventilkoerper | P32: =IFERROR(INDEX(DATABASE_FG!$G$5:$G$367, MATCH(E32, DATABASE_FG!$C$5:$C$367, 0)), "Not Found") -> 550 | Q32: 56 | R32: approved | S32: =IFERROR(INDEX(DATABASE_FG!$L$5:$L$367, MATCH(E32, DATABASE_FG!$C$5:$C$367, 0)), " ") -> 56 | T32: yes | AA32: No | AD32: =IF(NOT(ISBLANK(AC32)), C32, "") | AE32: =IF(NOT(ISBLANK(AC32)), E32, "") | AG32: =AF32*H32 -> 0 | AK32: =IF(AB32="", IF(K32 < TODAY(), "Late", ""), IF(AB32 <= K32 + 2, "On Time", "Late")) | AL32: =TEXT(K32,"mmmm") -> September | AM32: =YEAR(Table1[[#This Row],[ETA As requested dd.mm.yyyy]]) -> 2026
A33: BOSCH Homburg | B33: forecast | C33: 5500495155 | D33: 45749 | E33: 1535100044 | F33: =IFERROR(VLOOKUP(Table1[[#This Row],[Part Number]],DATABASE_FG!$C$6:D10022,2,FALSE)," ") -> VALVE BODY . | G33: =IFERROR(_xlfn.XLOOKUP(Table1[[#This Row],[Part Number]],Table3[Part number],Table3[Drawing Revision]),"") -> AB | H33: {=IFERROR(INDEX(PDB!$C:$AT,MATCH(E33,PDB!$B:$B,0),MATCH(YEAR(K33),0+PDB!$C$1:$AT$1,0)),"")} -> 0 | I33: 30 | J33: =IFERROR(Table1[[#This Row],[Quantity]]*Table1[[#This Row],[Price/Unit EUR]]," ") -> 0 | K33: 46321 | L33: =WEEKNUM(Table1[[#This Row],[ETA As requested dd.mm.yyyy]]) -> 44 | M33: =YEAR(Table1[[#This Row],[ETA As requested dd.mm.yyyy]]) -> 2026 | N33: =IFERROR(INDEX(DATABASE_FG!$H$5:$H$367, MATCH(E33, DATABASE_FG!$C$5:$C$367, 0)), " ") -> 0 | O33: =IF(E33<>"", _xlfn.XLOOKUP(E33, DATABASE_FG!C:C, DATABASE_FG!F:F), " ") -> Ventilkoerper | P33: =IFERROR(INDEX(DATABASE_FG!$G$5:$G$367, MATCH(E33, DATABASE_FG!$C$5:$C$367, 0)), "Not Found") -> 550 | Q33: 56 | R33: approved | S33: =IFERROR(INDEX(DATABASE_FG!$L$5:$L$367, MATCH(E33, DATABASE_FG!$C$5:$C$367, 0)), " ") -> 56 | T33: yes | AA33: No | AD33: =IF(NOT(ISBLANK(AC33)), C33, "") | AE33: =IF(NOT(ISBLANK(AC33)), E33, "") | AG33: =AF33*H33 -> 0 | AK33: =IF(AB33="", IF(K33 < TODAY(), "Late", ""), IF(AB33 <= K33 + 2, "On Time", "Late")) | AL33: =TEXT(K33,"mmmm") -> October | AM33: =YEAR(Table1[[#This Row],[ETA As requested dd.mm.yyyy]]) -> 2026
A34: BOSCH Homburg | B34: firm | C34: 5500495154 | D34: 45491 | E34: 1535100045 | F34: =IFERROR(VLOOKUP(Table1[[#This Row],[Part Number]],DATABASE_FG!$C$6:D10023,2,FALSE)," ") -> VALVE BODY | G34: =IFERROR(_xlfn.XLOOKUP(Table1[[#This Row],[Part Number]],Table3[Part number],Table3[Drawing Revision]),"") -> 1 | H34: {=IFERROR(INDEX(PDB!$C:$AT,MATCH(E34,PDB!$B:$B,0),MATCH(YEAR(K34),0+PDB!$C$1:$AT$1,0)),"")} -> 0.97 | I34: 16 | J34: =IFERROR(Table1[[#This Row],[Quantity]]*Table1[[#This Row],[Price/Unit EUR]]," ") -> 15.52 | K34: 45534 | L34: =WEEKNUM(Table1[[#This Row],[ETA As requested dd.mm.yyyy]]) -> 35 | M34: =YEAR(Table1[[#This Row],[ETA As requested dd.mm.yyyy]]) -> 2024 | N34: =IFERROR(INDEX(DATABASE_FG!$H$5:$H$367, MATCH(E34, DATABASE_FG!$C$5:$C$367, 0)), " ") -> 0 | O34: =IF(E34<>"", _xlfn.XLOOKUP(E34, DATABASE_FG!C:C, DATABASE_FG!F:F), " ") -> Ventilkoerper | P34: =IFERROR(INDEX(DATABASE_FG!$G$5:$G$367, MATCH(E34, DATABASE_FG!$C$5:$C$367, 0)), "Not Found") -> 16 | R34: approved | S34: =IFERROR(INDEX(DATABASE_FG!$L$5:$L$367, MATCH(E34, DATABASE_FG!$C$5:$C$367, 0)), " ") -> 42 | T34: no | AA34: Yes | AB34: 45581 | AC34: 202401244 | AD34: =IF(NOT(ISBLANK(AC34)), C34, "") -> 5500495154 | AE34: =IF(NOT(ISBLANK(AC34)), E34, "") -> 1535100045 | AF34: =16-16 -> 0 | AG34: =AF34*H34 -> 0 | AI34: stornate 116 | AJ34: 20241307-16.10.2024/20241525-09.12.2024 | AK34: =IF(AB34="", IF(K34 < TODAY(), "Late", ""), IF(AB34 <= K34 + 2, "On Time", "Late")) -> Late | AL34: =TEXT(K34,"mmmm") -> August | AM34: =YEAR(Table1[[#This Row],[ETA As requested dd.mm.yyyy]]) -> 2024
A35: BOSCH Homburg | B35: firm | C35: 5500495154 | D35: 45491 | E35: 1535100045 | F35: =IFERROR(VLOOKUP(Table1[[#This Row],[Part Number]],DATABASE_FG!$C$6:D10024,2,FALSE)," ") -> VALVE BODY | G35: =IFERROR(_xlfn.XLOOKUP(Table1[[#This Row],[Part Number]],Table3[Part number],Table3[Drawing Revision]),"") -> 1 | H35: {=IFERROR(INDEX(PDB!$C:$AT,MATCH(E35,PDB!$B:$B,0),MATCH(YEAR(K35),0+PDB!$C$1:$AT$1,0)),"")} -> 0.97 | I35: 100 | J35: =IFERROR(Table1[[#This Row],[Quantity]]*Table1[[#This Row],[Price/Unit EUR]]," ") -> 97 | K35: 45594 | L35: =WEEKNUM(Table1[[#This Row],[ETA As requested dd.mm.yyyy]]) -> 44 | M35: =YEAR(Table1[[#This Row],[ETA As requested dd.mm.yyyy]]) -> 2024 | N35: =IFERROR(INDEX(DATABASE_FG!$H$5:$H$367, MATCH(E35, DATABASE_FG!$C$5:$C$367, 0)), " ") -> 0 | O35: =IF(E35<>"", _xlfn.XLOOKUP(E35, DATABASE_FG!C:C, DATABASE_FG!F:F), " ") -> Ventilkoerper | P35: =IFERROR(INDEX(DATABASE_FG!$G$5:$G$367, MATCH(E35, DATABASE_FG!$C$5:$C$367, 0)), "Not Found") -> 16 | S35: =IFERROR(INDEX(DATABASE_FG!$L$5:$L$367, MATCH(E35, DATABASE_FG!$C$5:$C$367, 0)), " ") -> 42 | AA35: Yes | AB35: 45581 | AC35: 202401244 | AD35: =IF(NOT(ISBLANK(AC35)), C35, "") -> 5500495154 | AE35: =IF(NOT(ISBLANK(AC35)), E35, "") -> 1535100045 | AF35: =100-100 -> 0 | AG35: =AF35*H35 -> 0 | AI35: stornate 116 | AJ35: 20241307-16.10.2024/20241525-09.12.2024 | AK35: =IF(AB35="", IF(K35 < TODAY(), "Late", ""), IF(AB35 <= K35 + 2, "On Time", "Late")) -> On Time | AL35: =TEXT(K35,"mmmm") -> October | AM35: =YEAR(Table1[[#This Row],[ETA As requested dd.mm.yyyy]]) -> 2024
A36: BOSCH Homburg | B36: firm | C36: 5500495154 | D36: 45491 | E36: 1535100045 | F36: =IFERROR(VLOOKUP(Table1[[#This Row],[Part Number]],DATABASE_FG!$C$6:D10025,2,FALSE)," ") -> VALVE BODY | G36: =IFERROR(_xlfn.XLOOKUP(Table1[[#This Row],[Part Number]],Table3[Part number],Table3[Drawing Revision]),"") -> 1 | H36: {=IFERROR(INDEX(PDB!$C:$AT,MATCH(E36,PDB!$B:$B,0),MATCH(YEAR(K36),0+PDB!$C$1:$AT$1,0)),"")} -> 0.97 | I36: =86+114+100+65 -> 365 | J36: =IFERROR(Table1[[#This Row],[Quantity]]*Table1[[#This Row],[Price/Unit EUR]]," ") -> 354.05 | K36: 45904 | L36: =WEEKNUM(Table1[[#This Row],[ETA As requested dd.mm.yyyy]]) -> 36 | M36: =YEAR(Table1[[#This Row],[ETA As requested dd.mm.yyyy]]) -> 2025 | N36: =IFERROR(INDEX(DATABASE_FG!$H$5:$H$367, MATCH(E36, DATABASE_FG!$C$5:$C$367, 0)), " ") -> 0 | O36: =IF(E36<>"", _xlfn.XLOOKUP(E36, DATABASE_FG!C:C, DATABASE_FG!F:F), " ") -> Ventilkoerper | P36: =IFERROR(INDEX(DATABASE_FG!$G$5:$G$367, MATCH(E36, DATABASE_FG!$C$5:$C$367, 0)), "Not Found") -> 16 | S36: =Table1[[#This Row],[Quantity]]/48 -> 7.6041667 | U36: DA - RETUR DE LA CLIENT | W36: yes | Y36: produse | AA36: Yes | AB36: 45859 | AC36: 251083 | AD36: =IF(NOT(ISBLANK(AC36)), C36, "") -> 5500495154 | AE36: =IF(NOT(ISBLANK(AC36)), E36, "") -> 1535100045 | AF36: 365 | AG36: =AF36*H36 -> 354.05 | AJ36: 20250965-24.07.2025 | AK36: =IF(AB36="", IF(K36 < TODAY(), "Late", ""), IF(AB36 <= K36 + 2, "On Time", "Late")) -> On Time | AL36: =TEXT(K36,"mmmm") -> September | AM36: =YEAR(Table1[[#This Row],[ETA As requested dd.mm.yyyy]]) -> 2025
A37: BOSCH Homburg | B37: forecast | C37: 5500495154 | D37: 45491 | E37: 1535100045 | F37: =IFERROR(VLOOKUP(Table1[[#This Row],[Part Number]],DATABASE_FG!$C$6:D10026,2,FALSE)," ") -> VALVE BODY | G37: =IFERROR(_xlfn.XLOOKUP(Table1[[#This Row],[Part Number]],Table3[Part number],Table3[Drawing Revision]),"") -> 1 | H37: {=IFERROR(INDEX(PDB!$C:$AT,MATCH(E37,PDB!$B:$B,0),MATCH(YEAR(K37),0+PDB!$C$1:$AT$1,0)),"")} -> 0.97 | I37: =100-65 -> 35 | J37: =IFERROR(Table1[[#This Row],[Quantity]]*Table1[[#This Row],[Price/Unit EUR]]," ") -> 33.95 | K37: 45965 | L37: =WEEKNUM(Table1[[#This Row],[ETA As requested dd.mm.yyyy]]) -> 45 | M37: =YEAR(Table1[[#This Row],[ETA As requested dd.mm.yyyy]]) -> 2025 | N37: =IFERROR(INDEX(DATABASE_FG!$H$5:$H$367, MATCH(E37, DATABASE_FG!$C$5:$C$367, 0)), " ") -> 0 | O37: =IF(E37<>"", _xlfn.XLOOKUP(E37, DATABASE_FG!C:C, DATABASE_FG!F:F), " ") -> Ventilkoerper | P37: =IFERROR(INDEX(DATABASE_FG!$G$5:$G$367, MATCH(E37, DATABASE_FG!$C$5:$C$367, 0)), "Not Found") -> 16 | R37: approved | S37: =IFERROR(INDEX(DATABASE_FG!$L$5:$L$367, MATCH(E37, DATABASE_FG!$C$5:$C$367, 0)), " ") -> 42 | T37: no | W37: yes | Y37: produse | AA37: No | AD37: =IF(NOT(ISBLANK(AC37)), C37, "") | AE37: =IF(NOT(ISBLANK(AC37)), E37, "") | AG37: =AF37*H37 -> 0 | AK37: =IF(AB37="", IF(K37 < TODAY(), "Late", ""), IF(AB37 <= K37 + 2, "On Time", "Late")) -> Late | AL37: =TEXT(K37,"mmmm") -> November | AM37: =YEAR(Table1[[#This Row],[ETA As requested dd.mm.yyyy]]) -> 2025
A38: BOSCH Homburg | B38: firm | C38: 5500495154 | D38: 45491 | E38: 1535100045 | F38: =IFERROR(VLOOKUP(Table1[[#This Row],[Part Number]],DATABASE_FG!$C$6:D10027,2,FALSE)," ") -> VALVE BODY | G38: =IFERROR(_xlfn.XLOOKUP(Table1[[#This Row],[Part Number]],Table3[Part number],Table3[Drawing Revision]),"") -> 1 | H38: {=IFERROR(INDEX(PDB!$C:$AT,MATCH(E38,PDB!$B:$B,0),MATCH(YEAR(K38),0+PDB!$C$1:$AT$1,0)),"")} -> 0.97 | I38: 100 | J38: =IFERROR(Table1[[#This Row],[Quantity]]*Table1[[#This Row],[Price/Unit EUR]]," ") -> 97 | K38: 45999 | L38: =WEEKNUM(Table1[[#This Row],[ETA As requested dd.mm.yyyy]]) -> 50 | M38: =YEAR(Table1[[#This Row],[ETA As requested dd.mm.yyyy]]) -> 2025 | N38: =IFERROR(INDEX(DATABASE_FG!$H$5:$H$367, MATCH(E38, DATABASE_FG!$C$5:$C$367, 0)), " ") -> 0 | O38: =IF(E38<>"", _xlfn.XLOOKUP(E38, DATABASE_FG!C:C, DATABASE_FG!F:F), " ") -> Ventilkoerper | P38: =IFERROR(INDEX(DATABASE_FG!$G$5:$G$367, MATCH(E38, DATABASE_FG!$C$5:$C$367, 0)), "Not Found") -> 16 | S38: =Table1[[#This Row],[Quantity]]/48 -> 2.0833333 | AA38: No | AD38: =IF(NOT(ISBLANK(AC38)), C38, "") | AE38: =IF(NOT(ISBLANK(AC38)), E38, "") | AG38: =AF38*H38 -> 0 | AK38: =IF(AB38="", IF(K38 < TODAY(), "Late", ""), IF(AB38 <= K38 + 2, "On Time", "Late")) | AL38: =TEXT(K38,"mmmm") -> December | AM38: =YEAR(Table1[[#This Row],[ETA As requested dd.mm.yyyy]]) -> 2025
A39: BOSCH Homburg | B39: forecast | C39: 5500495154 | D39: 45428 | E39: 1535100045 | F39: =IFERROR(VLOOKUP(Table1[[#This Row],[Part Number]],DATABASE_FG!$C$6:D10028,2,FALSE)," ") -> VALVE BODY | G39: =IFERROR(_xlfn.XLOOKUP(Table1[[#This Row],[Part Number]],Table3[Part number],Table3[Drawing Revision]),"") -> 1 | H39: {=IFERROR(INDEX(PDB!$C:$AT,MATCH(E39,PDB!$B:$B,0),MATCH(YEAR(K39),0+PDB!$C$1:$AT$1,0)),"")} -> 0 | I39: 100 | J39: =IFERROR(Table1[[#This Row],[Quantity]]*Table1[[#This Row],[Price/Unit EUR]]," ") -> 0 | K39: 46048 | L39: =WEEKNUM(Table1[[#This Row],[ETA As requested dd.mm.yyyy]]) -> 5 | M39: =YEAR(Table1[[#This Row],[ETA As requested dd.mm.yyyy]]) -> 2026 | N39: =IFERROR(INDEX(DATABASE_FG!$H$5:$H$367, MATCH(E39, DATABASE_FG!$C$5:$C$367, 0)), " ") -> 0 | O39: =IF(E39<>"", _xlfn.XLOOKUP(E39, DATABASE_FG!C:C, DATABASE_FG!F:F), " ") -> Ventilkoerper | P39: =IFERROR(INDEX(DATABASE_FG!$G$5:$G$367, MATCH(E39, DATABASE_FG!$C$5:$C$367, 0)), "Not Found") -> 16 | Q39: 60 | R39: approved | S39: =IFERROR(INDEX(DATABASE_FG!$L$5:$L$367, MATCH(E39, DATABASE_FG!$C$5:$C$367, 0)), " ") -> 42 | T39: yes | Y39: Yes | AA39: No | AD39: =IF(NOT(ISBLANK(AC39)), C39, "") | AE39: =IF(NOT(ISBLANK(AC39)), E39, "") | AG39: =AF39*H39 -> 0 | AK39: =IF(AB39="", IF(K39 < TODAY(), "Late", ""), IF(AB39 <= K39 + 2, "On Time", "Late")) | AL39: =TEXT(K39,"mmmm") -> January | AM39: =YEAR(Table1[[#This Row],[ETA As requested dd.mm.yyyy]]) -> 2026
A40: BOSCH Homburg | B40: forecast | C40: 5500495154 | D40: 45428 | E40: 1535100045 | F40: =IFERROR(VLOOKUP(Table1[[#This Row],[Part Number]],DATABASE_FG!$C$6:D10029,2,FALSE)," ") -> VALVE BODY | G40: =IFERROR(_xlfn.XLOOKUP(Table1[[#This Row],[Part Number]],Table3[Part number],Table3[Drawing Revision]),"") -> 1 | H40: {=IFERROR(INDEX(PDB!$C:$AT,MATCH(E40,PDB!$B:$B,0),MATCH(YEAR(K40),0+PDB!$C$1:$AT$1,0)),"")} -> 0 | I40: 100 | J40: =IFERROR(Table1[[#This Row],[Quantity]]*Table1[[#This Row],[Price/Unit EUR]]," ") -> 0 | K40: 46083 | L40: =WEEKNUM(Table1[[#This Row],[ETA As requested dd.mm.yyyy]]) -> 10 | M40: =YEAR(Table1[[#This Row],[ETA As requested dd.mm.yyyy]]) -> 2026 | N40: =IFERROR(INDEX(DATABASE_FG!$H$5:$H$367, MATCH(E40, DATABASE_FG!$C$5:$C$367, 0)), " ") -> 0 | O40: =IF(E40<>"", _xlfn.XLOOKUP(E40, DATABASE_FG!C:C, DATABASE_FG!F:F), " ") -> Ventilkoerper | P40: =IFERROR(INDEX(DATABASE_FG!$G$5:$G$367, MATCH(E40, DATABASE_FG!$C$5:$C$367, 0)), "Not Found") -> 16 | Q40: 60 | R40: approved | S40: =IFERROR(INDEX(DATABASE_FG!$L$5:$L$367, MATCH(E40, DATABASE_FG!$C$5:$C$367, 0)), " ") -> 42 | T40: yes | Y40: Yes | AA40: No | AD40: =IF(NOT(ISBLANK(AC40)), C40, "") | AE40: =IF(NOT(ISBLANK(AC40)), E40, "") | AG40: =AF40*H40 -> 0 | AK40: =IF(AB40="", IF(K40 < TODAY(), "Late", ""), IF(AB40 <= K40 + 2, "On Time", "Late")) | AL40: =TEXT(K40,"mmmm") -> March | AM40: =YEAR(Table1[[#This Row],[ETA As requested dd.mm.yyyy]]) -> 2026
A41: BOSCH Homburg | B41: forecast | C41: 5500495154 | D41: 45428 | E41: 1535100045 | F41: =IFERROR(VLOOKUP(Table1[[#This Row],[Part Number]],DATABASE_FG!$C$6:D10030,2,FALSE)," ") -> VALVE BODY | G41: =IFERROR(_xlfn.XLOOKUP(Table1[[#This Row],[Part Number]],Table3[Part number],Table3[Drawing Revision]),"") -> 1 | H41: {=IFERROR(INDEX(PDB!$C:$AT,MATCH(E41,PDB!$B:$B,0),MATCH(YEAR(K41),0+PDB!$C$1:$AT$1,0)),"")} -> 0 | I41: 100 | J41: =IFERROR(Table1[[#This Row],[Quantity]]*Table1[[#This Row],[Price/Unit EUR]]," ") -> 0 | K41: 46091 | L41: =WEEKNUM(Table1[[#This Row],[ETA As requested dd.mm.yyyy]]) -> 11 | M41: =YEAR(Table1[[#This Row],[ETA As requested dd.mm.yyyy]]) -> 2026 | N41: =IFERROR(INDEX(DATABASE_FG!$H$5:$H$367, MATCH(E41, DATABASE_FG!$C$5:$C$367, 0)), " ") -> 0 | O41: =IF(E41<>"", _xlfn.XLOOKUP(E41, DATABASE_FG!C:C, DATABASE_FG!F:F), " ") -> Ventilkoerper | P41: =IFERROR(INDEX(DATABASE_FG!$G$5:$G$367, MATCH(E41, DATABASE_FG!$C$5:$C$367, 0)), "Not Found") -> 16 | Q41: 60 | R41: approved | S41: =IFERROR(INDEX(DATABASE_FG!$L$5:$L$367, MATCH(E41, DATABASE_FG!$C$5:$C$367, 0)), " ") -> 42 | T41: yes | Y41: Yes | AA41: No | AD41: =IF(NOT(ISBLANK(AC41)), C41, "") | AE41: =IF(NOT(ISBLANK(AC41)), E41, "") | AG41: =AF41*H41 -> 0 | AK41: =IF(AB41="", IF(K41 < TODAY(), "Late", ""), IF(AB41 <= K41 + 2, "On Time", "Late")) | AL41: =TEXT(K41,"mmmm") -> March | AM41: =YEAR(Table1[[#This Row],[ETA As requested dd.mm.yyyy]]) -> 2026
A42: BOSCH Homburg | B42: forecast | C42: 5500495154 | D42: 45428 | E42: 1535100045 | F42: =IFERROR(VLOOKUP(Table1[[#This Row],[Part Number]],DATABASE_FG!$C$6:D10031,2,FALSE)," ") -> VALVE BODY | G42: =IFERROR(_xlfn.XLOOKUP(Table1[[#This Row],[Part Number]],Table3[Part number],Table3[Drawing Revision]),"") -> 1 | H42: {=IFERROR(INDEX(PDB!$C:$AT,MATCH(E42,PDB!$B:$B,0),MATCH(YEAR(K42),0+PDB!$C$1:$AT$1,0)),"")} -> 0 | I42: 100 | J42: =IFERROR(Table1[[#This Row],[Quantity]]*Table1[[#This Row],[Price/Unit EUR]]," ") -> 0 | K42: 46135 | L42: =WEEKNUM(Table1[[#This Row],[ETA As requested dd.mm.yyyy]]) -> 17 | M42: =YEAR(Table1[[#This Row],[ETA As requested dd.mm.yyyy]]) -> 2026 | N42: =IFERROR(INDEX(DATABASE_FG!$H$5:$H$367, MATCH(E42, DATABASE_FG!$C$5:$C$367, 0)), " ") -> 0 | O42: =IF(E42<>"", _xlfn.XLOOKUP(E42, DATABASE_FG!C:C, DATABASE_FG!F:F), " ") -> Ventilkoerper | P42: =IFERROR(INDEX(DATABASE_FG!$G$5:$G$367, MATCH(E42, DATABASE_FG!$C$5:$C$367, 0)), "Not Found") -> 16 | Q42: 60 | R42: approved | S42: =IFERROR(INDEX(DATABASE_FG!$L$5:$L$367, MATCH(E42, DATABASE_FG!$C$5:$C$367, 0)), " ") -> 42 | T42: yes | Y42: Yes | AA42: No | AD42: =IF(NOT(ISBLANK(AC42)), C42, "") | AE42: =IF(NOT(ISBLANK(AC42)), E42, "") | AG42: =AF42*H42 -> 0 | AK42: =IF(AB42="", IF(K42 < TODAY(), "Late", ""), IF(AB42 <= K42 + 2, "On Time", "Late")) | AL42: =TEXT(K42,"mmmm") -> April | AM42: =YEAR(Table1[[#This Row],[ETA As requested dd.mm.yyyy]]) -> 2026
A43: BOSCH Homburg | B43: forecast | C43: 5500495154 | D43: 45428 | E43: 1535100045 | F43: =IFERROR(VLOOKUP(Table1[[#This Row],[Part Number]],DATABASE_FG!$C$6:D10032,2,FALSE)," ") -> VALVE BODY | G43: =IFERROR(_xlfn.XLOOKUP(Table1[[#This Row],[Part Number]],Table3[Part number],Table3[Drawing Revision]),"") -> 1 | H43: {=IFERROR(INDEX(PDB!$C:$AT,MATCH(E43,PDB!$B:$B,0),MATCH(YEAR(K43),0+PDB!$C$1:$AT$1,0)),"")} -> 0 | I43: 100 | J43: =IFERROR(Table1[[#This Row],[Quantity]]*Table1[[#This Row],[Price/Unit EUR]]," ") -> 0 | K43: 46184 | L43: =WEEKNUM(Table1[[#This Row],[ETA As requested dd.mm.yyyy]]) -> 24 | M43: =YEAR(Table1[[#This Row],[ETA As requested dd.mm.yyyy]]) -> 2026 | N43: =IFERROR(INDEX(DATABASE_FG!$H$5:$H$367, MATCH(E43, DATABASE_FG!$C$5:$C$367, 0)), " ") -> 0 | O43: =IF(E43<>"", _xlfn.XLOOKUP(E43, DATABASE_FG!C:C, DATABASE_FG!F:F), " ") -> Ventilkoerper | P43: =IFERROR(INDEX(DATABASE_FG!$G$5:$G$367, MATCH(E43, DATABASE_FG!$C$5:$C$367, 0)), "Not Found") -> 16 | Q43: 60 | R43: approved | S43: =IFERROR(INDEX(DATABASE_FG!$L$5:$L$367, MATCH(E43, DATABASE_FG!$C$5:$C$367, 0)), " ") -> 42 | T43: yes | Y43: Yes | AA43: No | AD43: =IF(NOT(ISBLANK(AC43)), C43, "") | AE43: =IF(NOT(ISBLANK(AC43)), E43, "") | AG43: =AF43*H43 -> 0 | AK43: =IF(AB43="", IF(K43 < TODAY(), "Late", ""), IF(AB43 <= K43 + 2, "On Time", "Late")) | AL43: =TEXT(K43,"mmmm") -> June | AM43: =YEAR(Table1[[#This Row],[ETA As requested dd.mm.yyyy]]) -> 2026
A44: BOSCH Homburg | B44: forecast | C44: 5500495154 | D44: 45428 | E44: 1535100045 | F44: =IFERROR(VLOOKUP(Table1[[#This Row],[Part Number]],DATABASE_FG!$C$6:D10033,2,FALSE)," ") -> VALVE BODY | G44: =IFERROR(_xlfn.XLOOKUP(Table1[[#This Row],[Part Number]],Table3[Part number],Table3[Drawing Revision]),"") -> 1 | H44: {=IFERROR(INDEX(PDB!$C:$AT,MATCH(E44,PDB!$B:$B,0),MATCH(YEAR(K44),0+PDB!$C$1:$AT$1,0)),"")} -> 0 | I44: 100 | J44: =IFERROR(Table1[[#This Row],[Quantity]]*Table1[[#This Row],[Price/Unit EUR]]," ") -> 0 | K44: 46239 | L44: =WEEKNUM(Table1[[#This Row],[ETA As requested dd.mm.yyyy]]) -> 32 | M44: =YEAR(Table1[[#This Row],[ETA As requested dd.mm.yyyy]]) -> 2026 | N44: =IFERROR(INDEX(DATABASE_FG!$H$5:$H$367, MATCH(E44, DATABASE_FG!$C$5:$C$367, 0)), " ") -> 0 | O44: =IF(E44<>"", _xlfn.XLOOKUP(E44, DATABASE_FG!C:C, DATABASE_FG!F:F), " ") -> Ventilkoerper | P44: =IFERROR(INDEX(DATABASE_FG!$G$5:$G$367, MATCH(E44, DATABASE_FG!$C$5:$C$367, 0)), "Not Found") -> 16 | Q44: 60 | R44: approved | S44: =IFERROR(INDEX(DATABASE_FG!$L$5:$L$367, MATCH(E44, DATABASE_FG!$C$5:$C$367, 0)), " ") -> 42 | T44: yes | Y44: Yes | AA44: No | AD44: =IF(NOT(ISBLANK(AC44)), C44, "") | AE44: =IF(NOT(ISBLANK(AC44)), E44, "") | AG44: =AF44*H44 -> 0 | AK44: =IF(AB44="", IF(K44 < TODAY(), "Late", ""), IF(AB44 <= K44 + 2, "On Time", "Late")) | AL44: =TEXT(K44,"mmmm") -> August | AM44: =YEAR(Table1[[#This Row],[ETA As requested dd.mm.yyyy]]) -> 2026
A45: BOSCH Homburg | B45: forecast | C45: 5500495154 | D45: 45428 | E45: 1535100045 | F45: =IFERROR(VLOOKUP(Table1[[#This Row],[Part Number]],DATABASE_FG!$C$6:D10034,2,FALSE)," ") -> VALVE BODY | G45: =IFERROR(_xlfn.XLOOKUP(Table1[[#This Row],[Part Number]],Table3[Part number],Table3[Drawing Revision]),"") -> 1 | H45: {=IFERROR(INDEX(PDB!$C:$AT,MATCH(E45,PDB!$B:$B,0),MATCH(YEAR(K45),0+PDB!$C$1:$AT$1,0)),"")} -> 0 | I45: 100 | J45: =IFERROR(Table1[[#This Row],[Quantity]]*Table1[[#This Row],[Price/Unit EUR]]," ") -> 0 | K45: 46274 | L45: =WEEKNUM(Table1[[#This Row],[ETA As requested dd.mm.yyyy]]) -> 37 | M45: =YEAR(Table1[[#This Row],[ETA As requested dd.mm.yyyy]]) -> 2026 | N45: =IFERROR(INDEX(DATABASE_FG!$H$5:$H$367, MATCH(E45, DATABASE_FG!$C$5:$C$367, 0)), " ") -> 0 | O45: =IF(E45<>"", _xlfn.XLOOKUP(E45, DATABASE_FG!C:C, DATABASE_FG!F:F), " ") -> Ventilkoerper | P45: =IFERROR(INDEX(DATABASE_FG!$G$5:$G$367, MATCH(E45, DATABASE_FG!$C$5:$C$367, 0)), "Not Found") -> 16 | Q45: 60 | R45: approved | S45: =IFERROR(INDEX(DATABASE_FG!$L$5:$L$367, MATCH(E45, DATABASE_FG!$C$5:$C$367, 0)), " ") -> 42 | T45: yes | Y45: Yes | AA45: No | AD45: =IF(NOT(ISBLANK(AC45)), C45, "") | AE45: =IF(NOT(ISBLANK(AC45)), E45, "") | AG45: =AF45*H45 -> 0 | AK45: =IF(AB45="", IF(K45 < TODAY(), "Late", ""), IF(AB45 <= K45 + 2, "On Time", "Late")) | AL45: =TEXT(K45,"mmmm") -> September | AM45: =YEAR(Table1[[#This Row],[ETA As requested dd.mm.yyyy]]) -> 2026
A46: BOSCH Homburg | B46: forecast | C46: 5500495154 | D46: 45428 | E46: 1535100045 | F46: =IFERROR(VLOOKUP(Table1[[#This Row],[Part Number]],DATABASE_FG!$C$6:D10035,2,FALSE)," ") -> VALVE BODY | G46: =IFERROR(_xlfn.XLOOKUP(Table1[[#This Row],[Part Number]],Table3[Part number],Table3[Drawing Revision]),"") -> 1 | H46: {=IFERROR(INDEX(PDB!$C:$AT,MATCH(E46,PDB!$B:$B,0),MATCH(YEAR(K46),0+PDB!$C$1:$AT$1,0)),"")} -> 0 | I46: 100 | J46: =IFERROR(Table1[[#This Row],[Quantity]]*Table1[[#This Row],[Price/Unit EUR]]," ") -> 0 | K46: 46309 | L46: =WEEKNUM(Table1[[#This Row],[ETA As requested dd.mm.yyyy]]) -> 42 | M46: =YEAR(Table1[[#This Row],[ETA As requested dd.mm.yyyy]]) -> 2026 | N46: =IFERROR(INDEX(DATABASE_FG!$H$5:$H$367, MATCH(E46, DATABASE_FG!$C$5:$C$367, 0)), " ") -> 0 | O46: =IF(E46<>"", _xlfn.XLOOKUP(E46, DATABASE_FG!C:C, DATABASE_FG!F:F), " ") -> Ventilkoerper | P46: =IFERROR(INDEX(DATABASE_FG!$G$5:$G$367, MATCH(E46, DATABASE_FG!$C$5:$C$367, 0)), "Not Found") -> 16 | Q46: 60 | R46: approved | S46: =IFERROR(INDEX(DATABASE_FG!$L$5:$L$367, MATCH(E46, DATABASE_FG!$C$5:$C$367, 0)), " ") -> 42 | T46: yes | Y46: Yes | AA46: No | AD46: =IF(NOT(ISBLANK(AC46)), C46, "") | AE46: =IF(NOT(ISBLANK(AC46)), E46, "") | AG46: =AF46*H46 -> 0 | AK46: =IF(AB46="", IF(K46 < TODAY(), "Late", ""), IF(AB46 <= K46 + 2, "On Time", "Late")) | AL46: =TEXT(K46,"mmmm") -> October | AM46: =YEAR(Table1[[#This Row],[ETA As requested dd.mm.yyyy]]) -> 2026
A47: BOSCH Homburg | B47: firm | C47: 5500495153 | D47: 45428 | E47: 1535100046 | F47: =IFERROR(VLOOKUP(Table1[[#This Row],[Part Number]],DATABASE_FG!$C$6:D10036,2,FALSE)," ") -> VALVE BODY | G47: =IFERROR(_xlfn.XLOOKUP(Table1[[#This Row],[Part Number]],Table3[Part number],Table3[Drawing Revision]),"") -> AB | H47: {=IFERROR(INDEX(PDB!$C:$AT,MATCH(E47,PDB!$B:$B,0),MATCH(YEAR(K47),0+PDB!$C$1:$AT$1,0)),"")} -> 5.31 | I47: 200 | J47: =IFERROR(Table1[[#This Row],[Quantity]]*Table1[[#This Row],[Price/Unit EUR]]," ") -> 1062 | K47: 45376 | L47: =WEEKNUM(Table1[[#This Row],[ETA As requested dd.mm.yyyy]]) -> 13 | M47: =YEAR(Table1[[#This Row],[ETA As requested dd.mm.yyyy]]) -> 2024 | N47: =IFERROR(INDEX(DATABASE_FG!$H$5:$H$367, MATCH(E47, DATABASE_FG!$C$5:$C$367, 0)), " ") -> 0 | O47: =IF(E47<>"", _xlfn.XLOOKUP(E47, DATABASE_FG!C:C, DATABASE_FG!F:F), " ") -> Ventilkoerper | P47: =IFERROR(INDEX(DATABASE_FG!$G$5:$G$367, MATCH(E47, DATABASE_FG!$C$5:$C$367, 0)), "Not Found") -> 100 | Q47: 60 | R47: approved | S47: =IFERROR(INDEX(DATABASE_FG!$L$5:$L$367, MATCH(E47, DATABASE_FG!$C$5:$C$367, 0)), " ") -> 56 | T47: yes | Z47: 241514/242711 | AA47: Yes | AB47: 45477 | AC47: 2024777 | AD47: =IF(NOT(ISBLANK(AC47)), C47, "") -> 5500495153 | AE47: =IF(NOT(ISBLANK(AC47)), E47, "") -> 1535100046 | AF47: 104 | AG47: =AF47*H47 -> 552.24 | AI47: 56 returnate | AJ47: 20240831-04.07.2024 | AK47: =IF(AB47="", IF(K47 < TODAY(), "Late", ""), IF(AB47 <= K47 + 2, "On Time", "Late")) -> Late | AL47: =TEXT(K47,"mmmm") -> March | AM47: =YEAR(Table1[[#This Row],[ETA As requested dd.mm.yyyy]]) -> 2024
A48: BOSCH Homburg | B48: firm | C48: 5500495153 | D48: 45428 | E48: 1535100046 | F48: =IFERROR(VLOOKUP(Table1[[#This Row],[Part Number]],DATABASE_FG!$C$6:D10037,2,FALSE)," ") -> VALVE BODY | G48: =IFERROR(_xlfn.XLOOKUP(Table1[[#This Row],[Part Number]],Table3[Part number],Table3[Drawing Revision]),"") -> AB | H48: {=IFERROR(INDEX(PDB!$C:$AT,MATCH(E48,PDB!$B:$B,0),MATCH(YEAR(K48),0+PDB!$C$1:$AT$1,0)),"")} -> 5.31 | I48: 0 | J48: =IFERROR(Table1[[#This Row],[Quantity]]*Table1[[#This Row],[Price/Unit EUR]]," ") -> 0 | K48: 45377 | L48: =WEEKNUM(Table1[[#This Row],[ETA As requested dd.mm.yyyy]]) -> 13 | M48: =YEAR(Table1[[#This Row],[ETA As requested dd.mm.yyyy]]) -> 2024 | N48: =IFERROR(INDEX(DATABASE_FG!$H$5:$H$367, MATCH(E48, DATABASE_FG!$C$5:$C$367, 0)), " ") -> 0 | O48: =IF(E48<>"", _xlfn.XLOOKUP(E48, DATABASE_FG!C:C, DATABASE_FG!F:F), " ") -> Ventilkoerper | P48: =IFERROR(INDEX(DATABASE_FG!$G$5:$G$367, MATCH(E48, DATABASE_FG!$C$5:$C$367, 0)), "Not Found") -> 100 | Q48: 60 | R48: approved | S48: =Table1[[#This Row],[Quantity]]/48 -> 0 | AA48: Yes | AB48: 45504 | AC48: 2024946 | AD48: =IF(NOT(ISBLANK(AC48)), C48, "") -> 5500495153 | AE48: =IF(NOT(ISBLANK(AC48)), E48, "") -> 1535100046 | AF48: 96 | AG48: =AF48*H48 -> 509.76 | AJ48: 20240995-05.08.2024 | AK48: =IF(AB48="", IF(K48 < TODAY(), "Late", ""), IF(AB48 <= K48 + 2, "On Time", "Late")) -> Late | AL48: =TEXT(K48,"mmmm") -> March | AM48: =YEAR(Table1[[#This Row],[ETA As requested dd.mm.yyyy]]) -> 2024
A49: BOSCH Homburg | B49: firm | C49: 5500495153 | D49: 45428 | E49: 1535100046 | F49: =IFERROR(VLOOKUP(Table1[[#This Row],[Part Number]],DATABASE_FG!$C$6:D10038,2,FALSE)," ") -> VALVE BODY | G49: =IFERROR(_xlfn.XLOOKUP(Table1[[#This Row],[Part Number]],Table3[Part number],Table3[Drawing Revision]),"") -> AB | H49: {=IFERROR(INDEX(PDB!$C:$AT,MATCH(E49,PDB!$B:$B,0),MATCH(YEAR(K49),0+PDB!$C$1:$AT$1,0)),"")} -> 5.31 | I49: 0 | J49: =IFERROR(Table1[[#This Row],[Quantity]]*Table1[[#This Row],[Price/Unit EUR]]," ") -> 0 | K49: 45378 | L49: =WEEKNUM(Table1[[#This Row],[ETA As requested dd.mm.yyyy]]) -> 13 | M49: =YEAR(Table1[[#This Row],[ETA As requested dd.mm.yyyy]]) -> 2024 | N49: =IFERROR(INDEX(DATABASE_FG!$H$5:$H$367, MATCH(E49, DATABASE_FG!$C$5:$C$367, 0)), " ") -> 0 | O49: =IF(E49<>"", _xlfn.XLOOKUP(E49, DATABASE_FG!C:C, DATABASE_FG!F:F), " ") -> Ventilkoerper | P49: =IFERROR(INDEX(DATABASE_FG!$G$5:$G$367, MATCH(E49, DATABASE_FG!$C$5:$C$367, 0)), "Not Found") -> 100 | Q49: 60 | R49: approved | S49: =Table1[[#This Row],[Quantity]]/48 -> 0 | AA49: Yes | AB49: 45504 | AC49: 2024947 | AD49: =IF(NOT(ISBLANK(AC49)), C49, "") -> 5500495153 | AE49: =IF(NOT(ISBLANK(AC49)), E49, "") -> 1535100046 | AF49: 56 | AG49: =AF49*H49 -> 297.36 | AI49: piese de inlocuire | AJ49: 20241058-14.08.2024/20241031-09.08.2024 | AK49: =IF(AB49="", IF(K49 < TODAY(), "Late", ""), IF(AB49 <= K49 + 2, "On Time", "Late")) -> Late | AL49: =TEXT(K49,"mmmm") -> March | AM49: =YEAR(Table1[[#This Row],[ETA As requested dd.mm.yyyy]]) -> 2024
A50: BOSCH Homburg | B50: firm | C50: 5500495153 | D50: 45428 | E50: 1535100046 | F50: =IFERROR(VLOOKUP(Table1[[#This Row],[Part Number]],DATABASE_FG!$C$6:D10039,2,FALSE)," ") -> VALVE BODY | G50: =IFERROR(_xlfn.XLOOKUP(Table1[[#This Row],[Part Number]],Table3[Part number],Table3[Drawing Revision]),"") -> AB | H50: {=IFERROR(INDEX(PDB!$C:$AT,MATCH(E50,PDB!$B:$B,0),MATCH(YEAR(K50),0+PDB!$C$1:$AT$1,0)),"")} -> 5.31 | I50: 100 | J50: =IFERROR(Table1[[#This Row],[Quantity]]*Table1[[#This Row],[Price/Unit EUR]]," ") -> 531 | K50: 45583 | L50: =WEEKNUM(Table1[[#This Row],[ETA As requested dd.mm.yyyy]]) -> 42 | M50: =YEAR(Table1[[#This Row],[ETA As requested dd.mm.yyyy]]) -> 2024 | N50: =IFERROR(INDEX(DATABASE_FG!$H$5:$H$367, MATCH(E50, DATABASE_FG!$C$5:$C$367, 0)), " ") -> 0 | O50: =IF(E50<>"", _xlfn.XLOOKUP(E50, DATABASE_FG!C:C, DATABASE_FG!F:F), " ") -> Ventilkoerper | P50: =IFERROR(INDEX(DATABASE_FG!$G$5:$G$367, MATCH(E50, DATABASE_FG!$C$5:$C$367, 0)), "Not Found") -> 100 | Q50: 60 | R50: approved | S50: =IFERROR(INDEX(DATABASE_FG!$L$5:$L$367, MATCH(E50, DATABASE_FG!$C$5:$C$367, 0)), " ") -> 56 | T50: yes | Y50: Yes | AA50: Yes | AB50: 45709 | AC50: 25247 | AD50: =IF(NOT(ISBLANK(AC50)), C50, "") -> 5500495153 | AE50: =IF(NOT(ISBLANK(AC50)), E50, "") -> 1535100046 | AF50: 100 | AG50: =AF50*H50 -> 531 | AJ50: 20250218-21.02.2025/20250428-31.02.2025/20250429-31.03.2025 | AK50: =IF(AB50="", IF(K50 < TODAY(), "Late", ""), IF(AB50 <= K50 + 2, "On Time", "Late")) -> Late | AL50: =TEXT(K50,"mmmm") -> October | AM50: =YEAR(Table1[[#This Row],[ETA As requested dd.mm.yyyy]]) -> 2024
A51: BOSCH Homburg | B51: firm | C51: 5500495153 | D51: 45428 | E51: 1535100046 | F51: =IFERROR(VLOOKUP(Table1[[#This Row],[Part Number]],DATABASE_FG!$C$6:D10040,2,FALSE)," ") -> VALVE BODY | G51: =IFERROR(_xlfn.XLOOKUP(Table1[[#This Row],[Part Number]],Table3[Part number],Table3[Drawing Revision]),"") -> AB | H51: {=IFERROR(INDEX(PDB!$C:$AT,MATCH(E51,PDB!$B:$B,0),MATCH(YEAR(K51),0+PDB!$C$1:$AT$1,0)),"")} -> 5.31 | I51: 84 | J51: =IFERROR(Table1[[#This Row],[Quantity]]*Table1[[#This Row],[Price/Unit EUR]]," ") -> 446.04 | K51: 45635 | L51: =WEEKNUM(Table1[[#This Row],[ETA As requested dd.mm.yyyy]]) -> 50 | M51: =YEAR(Table1[[#This Row],[ETA As requested dd.mm.yyyy]]) -> 2024 | N51: =IFERROR(INDEX(DATABASE_FG!$H$5:$H$367, MATCH(E51, DATABASE_FG!$C$5:$C$367, 0)), " ") -> 0 | O51: =IF(E51<>"", _xlfn.XLOOKUP(E51, DATABASE_FG!C:C, DATABASE_FG!F:F), " ") -> Ventilkoerper | P51: =IFERROR(INDEX(DATABASE_FG!$G$5:$G$367, MATCH(E51, DATABASE_FG!$C$5:$C$367, 0)), "Not Found") -> 100 | Q51: 60 | R51: approved | S51: =IFERROR(INDEX(DATABASE_FG!$L$5:$L$367, MATCH(E51, DATABASE_FG!$C$5:$C$367, 0)), " ") -> 56 | T51: yes | Y51: Yes | AA51: Yes | AB51: 45709 | AC51: 25247 | AD51: =IF(NOT(ISBLANK(AC51)), C51, "") -> 5500495153 | AE51: =IF(NOT(ISBLANK(AC51)), E51, "") -> 1535100046 | AF51: 84 | AG51: =AF51*H51 -> 446.04 | AK51: =IF(AB51="", IF(K51 < TODAY(), "Late", ""), IF(AB51 <= K51 + 2, "On Time", "Late")) -> Late | AL51: =TEXT(K51,"mmmm") -> December | AM51: =YEAR(Table1[[#This Row],[ETA As requested dd.mm.yyyy]]) -> 2024
A52: BOSCH Homburg | B52: firm | C52: 5500495153 | D52: 45428 | E52: 1535100046 | F52: =IFERROR(VLOOKUP(Table1[[#This Row],[Part Number]],DATABASE_FG!$C$6:D10041,2,FALSE)," ") -> VALVE BODY | G52: =IFERROR(_xlfn.XLOOKUP(Table1[[#This Row],[Part Number]],Table3[Part number],Table3[Drawing Revision]),"") -> AB | H52: {=IFERROR(INDEX(PDB!$C:$AT,MATCH(E52,PDB!$B:$B,0),MATCH(YEAR(K52),0+PDB!$C$1:$AT$1,0)),"")} -> 5.31 | I52: =100-84+43 -> 59 | J52: =IFERROR(Table1[[#This Row],[Quantity]]*Table1[[#This Row],[Price/Unit EUR]]," ") -> 313.29 | K52: 45635 | L52: =WEEKNUM(Table1[[#This Row],[ETA As requested dd.mm.yyyy]]) -> 50 | M52: =YEAR(Table1[[#This Row],[ETA As requested dd.mm.yyyy]]) -> 2024 | N52: =IFERROR(INDEX(DATABASE_FG!$H$5:$H$367, MATCH(E52, DATABASE_FG!$C$5:$C$367, 0)), " ") -> 0 | O52: =IF(E52<>"", _xlfn.XLOOKUP(E52, DATABASE_FG!C:C, DATABASE_FG!F:F), " ") -> Ventilkoerper | P52: =IFERROR(INDEX(DATABASE_FG!$G$5:$G$367, MATCH(E52, DATABASE_FG!$C$5:$C$367, 0)), "Not Found") -> 100 | Q52: 60 | R52: approved | S52: =IFERROR(INDEX(DATABASE_FG!$L$5:$L$367, MATCH(E52, DATABASE_FG!$C$5:$C$367, 0)), " ") -> 56 | T52: yes | Y52: Yes | AA52: Yes | AB52: 45838 | AC52: 260017 | AD52: =IF(NOT(ISBLANK(AC52)), C52, "") -> 5500495153 | AE52: =IF(NOT(ISBLANK(AC52)), E52, "") -> 1535100046 | AF52: 59 | AG52: =AF52*H52 -> 313.29 | AK52: =IF(AB52="", IF(K52 < TODAY(), "Late", ""), IF(AB52 <= K52 + 2, "On Time", "Late")) -> Late | AL52: =TEXT(K52,"mmmm") -> December | AM52: =YEAR(Table1[[#This Row],[ETA As requested dd.mm.yyyy]]) -> 2024
A53: BOSCH Homburg | B53: firm | C53: 5500495153 | D53: 45428 | E53: 1535100046 | F53: =IFERROR(VLOOKUP(Table1[[#This Row],[Part Number]],DATABASE_FG!$C$6:D10042,2,FALSE)," ") -> VALVE BODY | G53: =IFERROR(_xlfn.XLOOKUP(Table1[[#This Row],[Part Number]],Table3[Part number],Table3[Drawing Revision]),"") -> AB | H53: {=IFERROR(INDEX(PDB!$C:$AT,MATCH(E53,PDB!$B:$B,0),MATCH(YEAR(K53),0+PDB!$C$1:$AT$1,0)),"")} -> 5.31 | I53: =100-43+2 -> 59 | J53: =IFERROR(Table1[[#This Row],[Quantity]]*Table1[[#This Row],[Price/Unit EUR]]," ") -> 313.29 | K53: 45726 | L53: =WEEKNUM(Table1[[#This Row],[ETA As requested dd.mm.yyyy]]) -> 11 | M53: =YEAR(Table1[[#This Row],[ETA As requested dd.mm.yyyy]]) -> 2025 | N53: =IFERROR(INDEX(DATABASE_FG!$H$5:$H$367, MATCH(E53, DATABASE_FG!$C$5:$C$367, 0)), " ") -> 0 | O53: =IF(E53<>"", _xlfn.XLOOKUP(E53, DATABASE_FG!C:C, DATABASE_FG!F:F), " ") -> Ventilkoerper | P53: =IFERROR(INDEX(DATABASE_FG!$G$5:$G$367, MATCH(E53, DATABASE_FG!$C$5:$C$367, 0)), "Not Found") -> 100 | Q53: 60 | R53: approved | S53: =IFERROR(INDEX(DATABASE_FG!$L$5:$L$367, MATCH(E53, DATABASE_FG!$C$5:$C$367, 0)), " ") -> 56 | T53: yes | W53: yes | Y53: Yes | AA53: Yes | AB53: 45838 | AC53: 260017 | AD53: =IF(NOT(ISBLANK(AC53)), C53, "") -> 5500495153 | AE53: =IF(NOT(ISBLANK(AC53)), E53, "") -> 1535100046 | AF53: 59 | AG53: =AF53*H53 -> 313.29 | AJ53: 20250813-30.06.2025/20251371/20251372-30.10.2025 | AK53: =IF(AB53="", IF(K53 < TODAY(), "Late", ""), IF(AB53 <= K53 + 2, "On Time", "Late")) -> Late | AL53: =TEXT(K53,"mmmm") -> March | AM53: =YEAR(Table1[[#This Row],[ETA As requested dd.mm.yyyy]]) -> 2025
A54: BOSCH Homburg | B54: firm | C54: 5500495153 | D54: 45428 | E54: 1535100046 | F54: =IFERROR(VLOOKUP(Table1[[#This Row],[Part Number]],DATABASE_FG!$C$6:D10043,2,FALSE)," ") -> VALVE BODY | G54: =IFERROR(_xlfn.XLOOKUP(Table1[[#This Row],[Part Number]],Table3[Part number],Table3[Drawing Revision]),"") -> AB | H54: {=IFERROR(INDEX(PDB!$C:$AT,MATCH(E54,PDB!$B:$B,0),MATCH(YEAR(K54),0+PDB!$C$1:$AT$1,0)),"")} -> 5.31 | I54: =3*100+77 -> 377 | J54: =IFERROR(Table1[[#This Row],[Quantity]]*Table1[[#This Row],[Price/Unit EUR]]," ") -> 2001.87 | K54: 45899 | L54: =WEEKNUM(Table1[[#This Row],[ETA As requested dd.mm.yyyy]]) -> 35 | M54: =YEAR(Table1[[#This Row],[ETA As requested dd.mm.yyyy]]) -> 2025 | N54: =IFERROR(INDEX(DATABASE_FG!$H$5:$H$367, MATCH(E54, DATABASE_FG!$C$5:$C$367, 0)), " ") -> 0 | O54: =IF(E54<>"", _xlfn.XLOOKUP(E54, DATABASE_FG!C:C, DATABASE_FG!F:F), " ") -> Ventilkoerper | P54: =IFERROR(INDEX(DATABASE_FG!$G$5:$G$367, MATCH(E54, DATABASE_FG!$C$5:$C$367, 0)), "Not Found") -> 100 | Q54: 60 | R54: approved | S54: =IFERROR(INDEX(DATABASE_FG!$L$5:$L$367, MATCH(E54, DATABASE_FG!$C$5:$C$367, 0)), " ") -> 56 | T54: yes | AA54: Yes | AB54: 45859 | AC54: 251084 | AD54: =IF(NOT(ISBLANK(AC54)), C54, "") -> 5500495153 | AE54: =IF(NOT(ISBLANK(AC54)), E54, "") -> 1535100046 | AF54: 377 | AG54: =AF54*H54 -> 2001.87 | AJ54: 20250961-24.07.2025 | AK54: =IF(AB54="", IF(K54 < TODAY(), "Late", ""), IF(AB54 <= K54 + 2, "On Time", "Late")) -> On Time | AL54: =TEXT(K54,"mmmm") -> August | AM54: =YEAR(Table1[[#This Row],[ETA As requested dd.mm.yyyy]]) -> 2025
A55: BOSCH Homburg | B55: forecast | C55: 5500495153 | D55: 45939 | E55: 1535100046 | F55: =IFERROR(VLOOKUP(Table1[[#This Row],[Part Number]],DATABASE_FG!$C$6:D10044,2,FALSE)," ") -> VALVE BODY | G55: =IFERROR(_xlfn.XLOOKUP(Table1[[#This Row],[Part Number]],Table3[Part number],Table3[Drawing Revision]),"") -> AB | H55: {=IFERROR(INDEX(PDB!$C:$AT,MATCH(E55,PDB!$B:$B,0),MATCH(YEAR(K55),0+PDB!$C$1:$AT$1,0)),"")} -> 5.31 | I55: =100-77 -> 23 | J55: =IFERROR(Table1[[#This Row],[Quantity]]*Table1[[#This Row],[Price/Unit EUR]]," ") -> 122.13 | K55: 45953 | L55: =WEEKNUM(Table1[[#This Row],[ETA As requested dd.mm.yyyy]]) -> 43 | M55: =YEAR(Table1[[#This Row],[ETA As requested dd.mm.yyyy]]) -> 2025 | N55: =IFERROR(INDEX(DATABASE_FG!$H$5:$H$367, MATCH(E55, DATABASE_FG!$C$5:$C$367, 0)), " ") -> 0 | O55: =IF(E55<>"", _xlfn.XLOOKUP(E55, DATABASE_FG!C:C, DATABASE_FG!F:F), " ") -> Ventilkoerper | P55: =IFERROR(INDEX(DATABASE_FG!$G$5:$G$367, MATCH(E55, DATABASE_FG!$C$5:$C$367, 0)), "Not Found") -> 100 | Q55: 60 | R55: approved | S55: =IFERROR(INDEX(DATABASE_FG!$L$5:$L$367, MATCH(E55, DATABASE_FG!$C$5:$C$367, 0)), " ") -> 56 | T55: yes | W55: yes | Y55: Yes | AA55: No | AD55: =IF(NOT(ISBLANK(AC55)), C55, "") | AE55: =IF(NOT(ISBLANK(AC55)), E55, "") | AG55: =AF55*H55 -> 0 | AK55: =IF(AB55="", IF(K55 < TODAY(), "Late", ""), IF(AB55 <= K55 + 2, "On Time", "Late")) -> Late | AL55: =TEXT(K55,"mmmm") -> October | AM55: =YEAR(Table1[[#This Row],[ETA As requested dd.mm.yyyy]]) -> 2025
A56: BOSCH Homburg | B56: forecast | C56: 5500495153 | D56: 45939 | E56: 1535100046 | F56: =IFERROR(VLOOKUP(Table1[[#This Row],[Part Number]],DATABASE_FG!$C$6:D10045,2,FALSE)," ") -> VALVE BODY | G56: =IFERROR(_xlfn.XLOOKUP(Table1[[#This Row],[Part Number]],Table3[Part number],Table3[Drawing Revision]),"") -> AB | H56: {=IFERROR(INDEX(PDB!$C:$AT,MATCH(E56,PDB!$B:$B,0),MATCH(YEAR(K56),0+PDB!$C$1:$AT$1,0)),"")} -> 5.31 | I56: 100 | J56: =IFERROR(Table1[[#This Row],[Quantity]]*Table1[[#This Row],[Price/Unit EUR]]," ") -> 531 | K56: 45988 | L56: =WEEKNUM(Table1[[#This Row],[ETA As requested dd.mm.yyyy]]) -> 48 | M56: =YEAR(Table1[[#This Row],[ETA As requested dd.mm.yyyy]]) -> 2025 | N56: =IFERROR(INDEX(DATABASE_FG!$H$5:$H$367, MATCH(E56, DATABASE_FG!$C$5:$C$367, 0)), " ") -> 0 | O56: =IF(E56<>"", _xlfn.XLOOKUP(E56, DATABASE_FG!C:C, DATABASE_FG!F:F), " ") -> Ventilkoerper | P56: =IFERROR(INDEX(DATABASE_FG!$G$5:$G$367, MATCH(E56, DATABASE_FG!$C$5:$C$367, 0)), "Not Found") -> 100 | Q56: 60 | R56: approved | S56: =Table1[[#This Row],[Quantity]]/48 -> 2.0833333 | AA56: No | AD56: =IF(NOT(ISBLANK(AC56)), C56, "") | AE56: =IF(NOT(ISBLANK(AC56)), E56, "") | AG56: =AF56*H56 -> 0 | AK56: =IF(AB56="", IF(K56 < TODAY(), "Late", ""), IF(AB56 <= K56 + 2, "On Time", "Late")) | AL56: =TEXT(K56,"mmmm") -> November | AM56: =YEAR(Table1[[#This Row],[ETA As requested dd.mm.yyyy]]) -> 2025
A57: BOSCH Homburg | B57: forecast | C57: 5500495153 | D57: 45939 | E57: 1535100046 | F57: =IFERROR(VLOOKUP(Table1[[#This Row],[Part Number]],DATABASE_FG!$C$6:D10046,2,FALSE)," ") -> VALVE BODY | G57: =IFERROR(_xlfn.XLOOKUP(Table1[[#This Row],[Part Number]],Table3[Part number],Table3[Drawing Revision]),"") -> AB | H57: {=IFERROR(INDEX(PDB!$C:$AT,MATCH(E57,PDB!$B:$B,0),MATCH(YEAR(K57),0+PDB!$C$1:$AT$1,0)),"")} -> 0 | I57: 100 | J57: =IFERROR(Table1[[#This Row],[Quantity]]*Table1[[#This Row],[Price/Unit EUR]]," ") -> 0 | K57: 46044 | L57: =WEEKNUM(Table1[[#This Row],[ETA As requested dd.mm.yyyy]]) -> 4 | M57: =YEAR(Table1[[#This Row],[ETA As requested dd.mm.yyyy]]) -> 2026 | N57: =IFERROR(INDEX(DATABASE_FG!$H$5:$H$367, MATCH(E57, DATABASE_FG!$C$5:$C$367, 0)), " ") -> 0 | O57: =IF(E57<>"", _xlfn.XLOOKUP(E57, DATABASE_FG!C:C, DATABASE_FG!F:F), " ") -> Ventilkoerper | P57: =IFERROR(INDEX(DATABASE_FG!$G$5:$G$367, MATCH(E57, DATABASE_FG!$C$5:$C$367, 0)), "Not Found") -> 100 | Q57: 60 | R57: approved | S57: =Table1[[#This Row],[Quantity]]/48 -> 2.0833333 | AA57: No | AD57: =IF(NOT(ISBLANK(AC57)), C57, "") | AE57: =IF(NOT(ISBLANK(AC57)), E57, "") | AG57: =AF57*H57 -> 0 | AK57: =IF(AB57="", IF(K57 < TODAY(), "Late", ""), IF(AB57 <= K57 + 2, "On Time", "Late")) | AL57: =TEXT(K57,"mmmm") -> January | AM57: =YEAR(Table1[[#This Row],[ETA As requested dd.mm.yyyy]]) -> 2026
A58: BOSCH Homburg | B58: forecast | C58: 5500495153 | D58: 45939 | E58: 1535100046 | F58: =IFERROR(VLOOKUP(Table1[[#This Row],[Part Number]],DATABASE_FG!$C$6:D10047,2,FALSE)," ") -> VALVE BODY | G58: =IFERROR(_xlfn.XLOOKUP(Table1[[#This Row],[Part Number]],Table3[Part number],Table3[Drawing Revision]),"") -> AB | H58: {=IFERROR(INDEX(PDB!$C:$AT,MATCH(E58,PDB!$B:$B,0),MATCH(YEAR(K58),0+PDB!$C$1:$AT$1,0)),"")} -> 0 | I58: 100 | J58: =IFERROR(Table1[[#This Row],[Quantity]]*Table1[[#This Row],[Price/Unit EUR]]," ") -> 0 | K58: 46108 | L58: =WEEKNUM(Table1[[#This Row],[ETA As requested dd.mm.yyyy]]) -> 13 | M58: =YEAR(Table1[[#This Row],[ETA As requested dd.mm.yyyy]]) -> 2026 | N58: =IFERROR(INDEX(DATABASE_FG!$H$5:$H$367, MATCH(E58, DATABASE_FG!$C$5:$C$367, 0)), " ") -> 0 | O58: =IF(E58<>"", _xlfn.XLOOKUP(E58, DATABASE_FG!C:C, DATABASE_FG!F:F), " ") -> Ventilkoerper | P58: =IFERROR(INDEX(DATABASE_FG!$G$5:$G$367, MATCH(E58, DATABASE_FG!$C$5:$C$367, 0)), "Not Found") -> 100 | Q58: 60 | R58: approved | S58: =Table1[[#This Row],[Quantity]]/48 -> 2.0833333 | AA58: No | AD58: =IF(NOT(ISBLANK(AC58)), C58, "") | AE58: =IF(NOT(ISBLANK(AC58)), E58, "") | AG58: =AF58*H58 -> 0 | AK58: =IF(AB58="", IF(K58 < TODAY(), "Late", ""), IF(AB58 <= K58 + 2, "On Time", "Late")) | AL58: =TEXT(K58,"mmmm") -> March | AM58: =YEAR(Table1[[#This Row],[ETA As requested dd.mm.yyyy]]) -> 2026
A59: BOSCH Homburg | B59: forecast | C59: 5500495153 | D59: 45939 | E59: 1535100046 | F59: =IFERROR(VLOOKUP(Table1[[#This Row],[Part Number]],DATABASE_FG!$C$6:D10048,2,FALSE)," ") -> VALVE BODY | G59: =IFERROR(_xlfn.XLOOKUP(Table1[[#This Row],[Part Number]],Table3[Part number],Table3[Drawing Revision]),"") -> AB | H59: {=IFERROR(INDEX(PDB!$C:$AT,MATCH(E59,PDB!$B:$B,0),MATCH(YEAR(K59),0+PDB!$C$1:$AT$1,0)),"")} -> 0 | I59: 100 | J59: =IFERROR(Table1[[#This Row],[Quantity]]*Table1[[#This Row],[Price/Unit EUR]]," ") -> 0 | K59: 46163 | L59: =WEEKNUM(Table1[[#This Row],[ETA As requested dd.mm.yyyy]]) -> 21 | M59: =YEAR(Table1[[#This Row],[ETA As requested dd.mm.yyyy]]) -> 2026 | N59: =IFERROR(INDEX(DATABASE_FG!$H$5:$H$367, MATCH(E59, DATABASE_FG!$C$5:$C$367, 0)), " ") -> 0 | O59: =IF(E59<>"", _xlfn.XLOOKUP(E59, DATABASE_FG!C:C, DATABASE_FG!F:F), " ") -> Ventilkoerper | P59: =IFERROR(INDEX(DATABASE_FG!$G$5:$G$367, MATCH(E59, DATABASE_FG!$C$5:$C$367, 0)), "Not Found") -> 100 | Q59: 60 | R59: approved | S59: =Table1[[#This Row],[Quantity]]/48 -> 2.0833333 | AA59: No | AD59: =IF(NOT(ISBLANK(AC59)), C59, "") | AE59: =IF(NOT(ISBLANK(AC59)), E59, "") | AG59: =AF59*H59 -> 0 | AK59: =IF(AB59="", IF(K59 < TODAY(), "Late", ""), IF(AB59 <= K59 + 2, "On Time", "Late")) | AL59: =TEXT(K59,"mmmm") -> May | AM59: =YEAR(Table1[[#This Row],[ETA As requested dd.mm.yyyy]]) -> 2026
A60: BOSCH Homburg | B60: forecast | C60: 5500495153 | D60: 45939 | E60: 1535100046 | F60: =IFERROR(VLOOKUP(Table1[[#This Row],[Part Number]],DATABASE_FG!$C$6:D10049,2,FALSE)," ") -> VALVE BODY | G60: =IFERROR(_xlfn.XLOOKUP(Table1[[#This Row],[Part Number]],Table3[Part number],Table3[Drawing Revision]),"") -> AB | H60: {=IFERROR(INDEX(PDB!$C:$AT,MATCH(E60,PDB!$B:$B,0),MATCH(YEAR(K60),0+PDB!$C$1:$AT$1,0)),"")} -> 0 | I60: 100 | J60: =IFERROR(Table1[[#This Row],[Quantity]]*Table1[[#This Row],[Price/Unit EUR]]," ") -> 0 | K60: 46245 | L60: =WEEKNUM(Table1[[#This Row],[ETA As requested dd.mm.yyyy]]) -> 33 | M60: =YEAR(Table1[[#This Row],[ETA As requested dd.mm.yyyy]]) -> 2026 | N60: =IFERROR(INDEX(DATABASE_FG!$H$5:$H$367, MATCH(E60, DATABASE_FG!$C$5:$C$367, 0)), " ") -> 0 | O60: =IF(E60<>"", _xlfn.XLOOKUP(E60, DATABASE_FG!C:C, DATABASE_FG!F:F), " ") -> Ventilkoerper | P60: =IFERROR(INDEX(DATABASE_FG!$G$5:$G$367, MATCH(E60, DATABASE_FG!$C$5:$C$367, 0)), "Not Found") -> 100 | Q60: 60 | R60: approved | S60: =Table1[[#This Row],[Quantity]]/48 -> 2.0833333 | AA60: No | AD60: =IF(NOT(ISBLANK(AC60)), C60, "") | AE60: =IF(NOT(ISBLANK(AC60)), E60, "") | AG60: =AF60*H60 -> 0 | AK60: =IF(AB60="", IF(K60 < TODAY(), "Late", ""), IF(AB60 <= K60 + 2, "On Time", "Late")) | AL60: =TEXT(K60,"mmmm") -> August | AM60: =YEAR(Table1[[#This Row],[ETA As requested dd.mm.yyyy]]) -> 2026
A61: BOSCH Homburg | B61: forecast | C61: 5500495153 | D61: 45939 | E61: 1535100046 | F61: =IFERROR(VLOOKUP(Table1[[#This Row],[Part Number]],DATABASE_FG!$C$6:D10050,2,FALSE)," ") -> VALVE BODY | G61: =IFERROR(_xlfn.XLOOKUP(Table1[[#This Row],[Part Number]],Table3[Part number],Table3[Drawing Revision]),"") -> AB | H61: {=IFERROR(INDEX(PDB!$C:$AT,MATCH(E61,PDB!$B:$B,0),MATCH(YEAR(K61),0+PDB!$C$1:$AT$1,0)),"")} -> 0 | I61: 69 | J61: =IFERROR(Table1[[#This Row],[Quantity]]*Table1[[#This Row],[Price/Unit EUR]]," ") -> 0 | K61: 46328 | L61: =WEEKNUM(Table1[[#This Row],[ETA As requested dd.mm.yyyy]]) -> 45 | M61: =YEAR(Table1[[#This Row],[ETA As requested dd.mm.yyyy]]) -> 2026 | N61: =IFERROR(INDEX(DATABASE_FG!$H$5:$H$367, MATCH(E61, DATABASE_FG!$C$5:$C$367, 0)), " ") -> 0 | O61: =IF(E61<>"", _xlfn.XLOOKUP(E61, DATABASE_FG!C:C, DATABASE_FG!F:F), " ") -> Ventilkoerper | P61: =IFERROR(INDEX(DATABASE_FG!$G$5:$G$367, MATCH(E61, DATABASE_FG!$C$5:$C$367, 0)), "Not Found") -> 100 | Q61: 60 | R61: approved | S61: =IFERROR(INDEX(DATABASE_FG!$L$5:$L$367, MATCH(E61, DATABASE_FG!$C$5:$C$367, 0)), " ") -> 56 | T61: yes | W61: yes | Y61: Yes | AA61: No | AD61: =IF(NOT(ISBLANK(AC61)), C61, "") | AE61: =IF(NOT(ISBLANK(AC61)), E61, "") | AG61: =AF61*H61 -> 0 | AK61: =IF(AB61="", IF(K61 < TODAY(), "Late", ""), IF(AB61 <= K61 + 2, "On Time", "Late")) | AL61: =TEXT(K61,"mmmm") -> November | AM61: =YEAR(Table1[[#This Row],[ETA As requested dd.mm.yyyy]]) -> 2026
A62: BOSCH Homburg | B62: firm | C62: 4508756412 | E62: 1813218040 | F62: =IFERROR(VLOOKUP(Table1[[#This Row],[Part Number]],DATABASE_FG!$C$6:D10051,2,FALSE)," ") -> valve body | G62: =IFERROR(_xlfn.XLOOKUP(Table1[[#This Row],[Part Number]],Table3[Part number],Table3[Drawing Revision]),"") -> AB | H62: {=IFERROR(INDEX(PDB!$C:$AT,MATCH(E62,PDB!$B:$B,0),MATCH(YEAR(K62),0+PDB!$C$1:$AT$1,0)),"")} -> 9.37 | I62: 5 | J62: =IFERROR(Table1[[#This Row],[Quantity]]*Table1[[#This Row],[Price/Unit EUR]]," ") -> 46.85 | K62: 44665 | L62: =WEEKNUM(Table1[[#This Row],[ETA As requested dd.mm.yyyy]]) -> 16 | M62: =YEAR(Table1[[#This Row],[ETA As requested dd.mm.yyyy]]) -> 2022 | N62: =IFERROR(INDEX(DATABASE_FG!$H$5:$H$367, MATCH(E62, DATABASE_FG!$C$5:$C$367, 0)), " ") -> 0 | O62: =IF(E62<>"", _xlfn.XLOOKUP(E62, DATABASE_FG!C:C, DATABASE_FG!F:F), " ") -> Ventilkoerper | P62: =IFERROR(INDEX(DATABASE_FG!$G$5:$G$367, MATCH(E62, DATABASE_FG!$C$5:$C$367, 0)), "Not Found") -> 1 | R62: project | S62: =IFERROR(INDEX(DATABASE_FG!$L$5:$L$367, MATCH(E62, DATABASE_FG!$C$5:$C$367, 0)), " ") -> 56 | T62: yes | AA62: Yes | AD62: =IF(NOT(ISBLANK(AC62)), C62, "") | AE62: =IF(NOT(ISBLANK(AC62)), E62, "") | AF62: 0 | AG62: =AF62*H62 -> 0 | AI62: Proiect Anulat | AK62: =IF(AB62="", IF(K62 < TODAY(), "Late", ""), IF(AB62 <= K62 + 2, "On Time", "Late")) -> Late | AL62: =TEXT(K62,"mmmm") -> April | AM62: =YEAR(Table1[[#This Row],[ETA As requested dd.mm.yyyy]]) -> 2022
A63: BOSCH Homburg | B63: firm | C63: 4508756412 | E63: 1813218042 | F63: =IFERROR(VLOOKUP(Table1[[#This Row],[Part Number]],DATABASE_FG!$C$6:D10052,2,FALSE)," ") -> VALVE BODY | G63: =IFERROR(_xlfn.XLOOKUP(Table1[[#This Row],[Part Number]],Table3[Part number],Table3[Drawing Revision]),"") -> AB | H63: {=IFERROR(INDEX(PDB!$C:$AT,MATCH(E63,PDB!$B:$B,0),MATCH(YEAR(K63),0+PDB!$C$1:$AT$1,0)),"")} -> 8.45 | I63: 5 | J63: =IFERROR(Table1[[#This Row],[Quantity]]*Table1[[#This Row],[Price/Unit EUR]]," ") -> 42.25 | K63: 45541 | L63: =WEEKNUM(Table1[[#This Row],[ETA As requested dd.mm.yyyy]]) -> 36 | M63: =YEAR(Table1[[#This Row],[ETA As requested dd.mm.yyyy]]) -> 2024 | N63: =IFERROR(INDEX(DATABASE_FG!$H$5:$H$367, MATCH(E63, DATABASE_FG!$C$5:$C$367, 0)), " ") -> 0 | O63: =IF(E63<>"", _xlfn.XLOOKUP(E63, DATABASE_FG!C:C, DATABASE_FG!F:F), " ") -> Ventilkoerper | P63: =IFERROR(INDEX(DATABASE_FG!$G$5:$G$367, MATCH(E63, DATABASE_FG!$C$5:$C$367, 0)), "Not Found") -> 50 | Q63: 60 | R63: project | S63: =IFERROR(INDEX(DATABASE_FG!$L$5:$L$367, MATCH(E63, DATABASE_FG!$C$5:$C$367, 0)), " ") -> 56 | T63: yes | Y63: project | Z63: 240412 | AA63: Yes | AB63: 45583 | AC63: 202401258 | AD63: =IF(NOT(ISBLANK(AC63)), C63, "") -> 4508756412 | AE63: =IF(NOT(ISBLANK(AC63)), E63, "") -> 1813218042 | AF63: 5 | AG63: =AF63*H63 -> 42.25 | AJ63: 20241325-18.10.2024 | AK63: =IF(AB63="", IF(K63 < TODAY(), "Late", ""), IF(AB63 <= K63 + 2, "On Time", "Late")) -> Late | AL63: =TEXT(K63,"mmmm") -> September | AM63: =YEAR(Table1[[#This Row],[ETA As requested dd.mm.yyyy]]) -> 2024
A64: BOSCH Homburg | B64: firm | C64: 4509910041 | D64: 45335 | E64: 1813218050 | F64: =IFERROR(VLOOKUP(Table1[[#This Row],[Part Number]],DATABASE_FG!$C$6:D10053,2,FALSE)," ") -> VALVE BODY . | G64: =IFERROR(_xlfn.XLOOKUP(Table1[[#This Row],[Part Number]],Table3[Part number],Table3[Drawing Revision]),"") -> AB | H64: {=IFERROR(INDEX(PDB!$C:$AT,MATCH(E64,PDB!$B:$B,0),MATCH(YEAR(K64),0+PDB!$C$1:$AT$1,0)),"")} -> 7.46 | I64: 5 | J64: =IFERROR(Table1[[#This Row],[Quantity]]*Table1[[#This Row],[Price/Unit EUR]]," ") -> 37.3 | K64: 45349 | L64: =WEEKNUM(Table1[[#This Row],[ETA As requested dd.mm.yyyy]]) -> 9 | M64: =YEAR(Table1[[#This Row],[ETA As requested dd.mm.yyyy]]) -> 2024 | N64: =IFERROR(INDEX(DATABASE_FG!$H$5:$H$367, MATCH(E64, DATABASE_FG!$C$5:$C$367, 0)), " ") -> 0 | O64: =IF(E64<>"", _xlfn.XLOOKUP(E64, DATABASE_FG!C:C, DATABASE_FG!F:F), " ") -> Ventilkoerper | P64: =IFERROR(INDEX(DATABASE_FG!$G$5:$G$367, MATCH(E64, DATABASE_FG!$C$5:$C$367, 0)), "Not Found") -> 250 | Q64: 60 | R64: project | S64: =IFERROR(INDEX(DATABASE_FG!$L$5:$L$367, MATCH(E64, DATABASE_FG!$C$5:$C$367, 0)), " ") -> 56 | T64: yes | Z64: 240717 | AA64: Yes | AB64: 45408 | AC64: 2024413 | AD64: =IF(NOT(ISBLANK(AC64)), C64, "") -> 4509910041 | AE64: =IF(NOT(ISBLANK(AC64)), E64, "") -> 1813218050 | AF64: 5 | AG64: =AF64*H64 -> 37.3 | AI64: VALIDARE | AJ64: 20240467-26.04.2024 | AK64: =IF(AB64="", IF(K64 < TODAY(), "Late", ""), IF(AB64 <= K64 + 2, "On Time", "Late")) -> Late | AL64: =TEXT(K64,"mmmm") -> February | AM64: =YEAR(Table1[[#This Row],[ETA As requested dd.mm.yyyy]]) -> 2024
A65: BOSCH Homburg | B65: firm | C65: 5500500924 | D65: 45369 | E65: 1813218050 | F65: =IFERROR(VLOOKUP(Table1[[#This Row],[Part Number]],DATABASE_FG!$C$6:D10054,2,FALSE)," ") -> VALVE BODY . | G65: =IFERROR(_xlfn.XLOOKUP(Table1[[#This Row],[Part Number]],Table3[Part number],Table3[Drawing Revision]),"") -> AB | H65: {=IFERROR(INDEX(PDB!$C:$AT,MATCH(E65,PDB!$B:$B,0),MATCH(YEAR(K65),0+PDB!$C$1:$AT$1,0)),"")} -> 7.46 | I65: 600 | J65: =IFERROR(Table1[[#This Row],[Quantity]]*Table1[[#This Row],[Price/Unit EUR]]," ") -> 4476 | K65: 45366 | L65: =WEEKNUM(Table1[[#This Row],[ETA As requested dd.mm.yyyy]]) -> 11 | M65: =YEAR(Table1[[#This Row],[ETA As requested dd.mm.yyyy]]) -> 2024 | N65: =IFERROR(INDEX(DATABASE_FG!$H$5:$H$367, MATCH(E65, DATABASE_FG!$C$5:$C$367, 0)), " ") -> 0 | O65: =IF(E65<>"", _xlfn.XLOOKUP(E65, DATABASE_FG!C:C, DATABASE_FG!F:F), " ") -> Ventilkoerper | P65: =IFERROR(INDEX(DATABASE_FG!$G$5:$G$367, MATCH(E65, DATABASE_FG!$C$5:$C$367, 0)), "Not Found") -> 250 | Q65: 60 | R65: project | S65: =IFERROR(INDEX(DATABASE_FG!$L$5:$L$367, MATCH(E65, DATABASE_FG!$C$5:$C$367, 0)), " ") -> 56 | T65: yes | Z65: 240718/242012 | AA65: Yes | AB65: 45401 | AC65: 2024382 | AD65: =IF(NOT(ISBLANK(AC65)), C65, "") -> 5500500924 | AE65: =IF(NOT(ISBLANK(AC65)), E65, "") -> 1813218050 | AF65: =200-170 -> 30 | AG65: =AF65*H65 -> 223.8 | AJ65: 20240416-19.04.2024/20250155-17.02.2025 | AK65: =IF(AB65="", IF(K65 < TODAY(), "Late", ""), IF(AB65 <= K65 + 2, "On Time", "Late")) -> Late | AL65: =TEXT(K65,"mmmm") -> March | AM65: =YEAR(Table1[[#This Row],[ETA As requested dd.mm.yyyy]]) -> 2024
A66: BOSCH Homburg | B66: firm | C66: 5500500924 | D66: 45369 | E66: 1813218050 | F66: =IFERROR(VLOOKUP(Table1[[#This Row],[Part Number]],DATABASE_FG!$C$6:D10055,2,FALSE)," ") -> VALVE BODY . | G66: =IFERROR(_xlfn.XLOOKUP(Table1[[#This Row],[Part Number]],Table3[Part number],Table3[Drawing Revision]),"") -> AB | H66: {=IFERROR(INDEX(PDB!$C:$AT,MATCH(E66,PDB!$B:$B,0),MATCH(YEAR(K66),0+PDB!$C$1:$AT$1,0)),"")} -> 7.46 | I66: 0 | J66: =IFERROR(Table1[[#This Row],[Quantity]]*Table1[[#This Row],[Price/Unit EUR]]," ") -> 0 | K66: 45367 | L66: =WEEKNUM(Table1[[#This Row],[ETA As requested dd.mm.yyyy]]) -> 11 | M66: =YEAR(Table1[[#This Row],[ETA As requested dd.mm.yyyy]]) -> 2024 | N66: =IFERROR(INDEX(DATABASE_FG!$H$5:$H$367, MATCH(E66, DATABASE_FG!$C$5:$C$367, 0)), " ") -> 0 | O66: =IF(E66<>"", _xlfn.XLOOKUP(E66, DATABASE_FG!C:C, DATABASE_FG!F:F), " ") -> Ventilkoerper | P66: =IFERROR(INDEX(DATABASE_FG!$G$5:$G$367, MATCH(E66, DATABASE_FG!$C$5:$C$367, 0)), "Not Found") -> 250 | S66: =IFERROR(INDEX(DATABASE_FG!$L$5:$L$367, MATCH(E66, DATABASE_FG!$C$5:$C$367, 0)), " ") -> 56 | AA66: Yes | AB66: 45411 | AC66: 2024421 | AD66: =IF(NOT(ISBLANK(AC66)), C66, "") -> 5500500924 | AE66: =IF(NOT(ISBLANK(AC66)), E66, "") -> 1813218050 | AF66: 150 | AG66: =AF66*H66 -> 1119 | AJ66: 20240478-29.04.2024 | AK66: =IF(AB66="", IF(K66 < TODAY(), "Late", ""), IF(AB66 <= K66 + 2, "On Time", "Late")) -> Late | AL66: =TEXT(K66,"mmmm") -> March | AM66: =YEAR(Table1[[#This Row],[ETA As requested dd.mm.yyyy]]) -> 2024
A67: BOSCH Homburg | B67: firm | C67: 5500500924 | D67: 45369 | E67: 1813218050 | F67: =IFERROR(VLOOKUP(Table1[[#This Row],[Part Number]],DATABASE_FG!$C$6:D10056,2,FALSE)," ") -> VALVE BODY . | G67: =IFERROR(_xlfn.XLOOKUP(Table1[[#This Row],[Part Number]],Table3[Part number],Table3[Drawing Revision]),"") -> AB | H67: {=IFERROR(INDEX(PDB!$C:$AT,MATCH(E67,PDB!$B:$B,0),MATCH(YEAR(K67),0+PDB!$C$1:$AT$1,0)),"")} -> 7.46 | I67: 0 | J67: =IFERROR(Table1[[#This Row],[Quantity]]*Table1[[#This Row],[Price/Unit EUR]]," ") -> 0 | K67: 45368 | L67: =WEEKNUM(Table1[[#This Row],[ETA As requested dd.mm.yyyy]]) -> 12 | M67: =YEAR(Table1[[#This Row],[ETA As requested dd.mm.yyyy]]) -> 2024 | N67: =IFERROR(INDEX(DATABASE_FG!$H$5:$H$367, MATCH(E67, DATABASE_FG!$C$5:$C$367, 0)), " ") -> 0 | O67: =IF(E67<>"", _xlfn.XLOOKUP(E67, DATABASE_FG!C:C, DATABASE_FG!F:F), " ") -> Ventilkoerper | P67: =IFERROR(INDEX(DATABASE_FG!$G$5:$G$367, MATCH(E67, DATABASE_FG!$C$5:$C$367, 0)), "Not Found") -> 250 | S67: =IFERROR(INDEX(DATABASE_FG!$L$5:$L$367, MATCH(E67, DATABASE_FG!$C$5:$C$367, 0)), " ") -> 56 | AA67: Yes | AB67: 45440 | AC67: 2024548 | AD67: =IF(NOT(ISBLANK(AC67)), C67, "") -> 5500500924 | AE67: =IF(NOT(ISBLANK(AC67)), E67, "") -> 1813218050 | AF67: =250-250 -> 0 | AG67: =AF67*H67 -> 0 | AJ67: 20240615-28.05.2024/20250154-17.02.2025 | AK67: =IF(AB67="", IF(K67 < TODAY(), "Late", ""), IF(AB67 <= K67 + 2, "On Time", "Late")) -> Late | AL67: =TEXT(K67,"mmmm") -> March | AM67: =YEAR(Table1[[#This Row],[ETA As requested dd.mm.yyyy]]) -> 2024
A68: BOSCH Homburg | B68: firm | C68: 4508771389 | E68: 1818509133 | F68: =IFERROR(VLOOKUP(Table1[[#This Row],[Part Number]],DATABASE_FG!$C$6:D10057,2,FALSE)," ") -> VALVE BODY | G68: =IFERROR(_xlfn.XLOOKUP(Table1[[#This Row],[Part Number]],Table3[Part number],Table3[Drawing Revision]),"") -> 1 | H68: {=IFERROR(INDEX(PDB!$C:$AT,MATCH(E68,PDB!$B:$B,0),MATCH(YEAR(K68),0+PDB!$C$1:$AT$1,0)),"")} -> 4.55 | I68: 5 | J68: =IFERROR(Table1[[#This Row],[Quantity]]*Table1[[#This Row],[Price/Unit EUR]]," ") -> 22.75 | K68: 45541 | L68: =WEEKNUM(Table1[[#This Row],[ETA As requested dd.mm.yyyy]]) -> 36 | M68: =YEAR(Table1[[#This Row],[ETA As requested dd.mm.yyyy]]) -> 2024 | N68: =IFERROR(INDEX(DATABASE_FG!$H$5:$H$367, MATCH(E68, DATABASE_FG!$C$5:$C$367, 0)), " ") -> 0 | O68: =IF(E68<>"", _xlfn.XLOOKUP(E68, DATABASE_FG!C:C, DATABASE_FG!F:F), " ") -> Ventilkoerper | P68: =IFERROR(INDEX(DATABASE_FG!$G$5:$G$367, MATCH(E68, DATABASE_FG!$C$5:$C$367, 0)), "Not Found") -> 216 | Q68: 60 | R68: project | S68: =IFERROR(INDEX(DATABASE_FG!$L$5:$L$367, MATCH(E68, DATABASE_FG!$C$5:$C$367, 0)), " ") -> 56 | T68: yes | AA68: Yes | AB68: 45496 | AC68: 2024895 | AD68: =IF(NOT(ISBLANK(AC68)), C68, "") -> 4508771389 | AE68: =IF(NOT(ISBLANK(AC68)), E68, "") -> 1818509133 | AF68: 5 | AG68: =AF68*H68 -> 22.75 | AJ68: 20240937-23.07.2024 | AK68: =IF(AB68="", IF(K68 < TODAY(), "Late", ""), IF(AB68 <= K68 + 2, "On Time", "Late")) -> On Time | AL68: =TEXT(K68,"mmmm") -> September | AM68: =YEAR(Table1[[#This Row],[ETA As requested dd.mm.yyyy]]) -> 2024
A69: BOSCH Homburg | B69: firm | C69: 4508771389 | E69: 1818509138 | F69: =IFERROR(VLOOKUP(Table1[[#This Row],[Part Number]],DATABASE_FG!$C$6:D10058,2,FALSE)," ") -> VALVE BODY | G69: =IFERROR(_xlfn.XLOOKUP(Table1[[#This Row],[Part Number]],Table3[Part number],Table3[Drawing Revision]),"") -> AB | H69: {=IFERROR(INDEX(PDB!$C:$AT,MATCH(E69,PDB!$B:$B,0),MATCH(YEAR(K69),0+PDB!$C$1:$AT$1,0)),"")} -> 4.53 | I69: 5 | J69: =IFERROR(Table1[[#This Row],[Quantity]]*Table1[[#This Row],[Price/Unit EUR]]," ") -> 22.65 | K69: 45541 | L69: =WEEKNUM(Table1[[#This Row],[ETA As requested dd.mm.yyyy]]) -> 36 | M69: =YEAR(Table1[[#This Row],[ETA As requested dd.mm.yyyy]]) -> 2024 | N69: =IFERROR(INDEX(DATABASE_FG!$H$5:$H$367, MATCH(E69, DATABASE_FG!$C$5:$C$367, 0)), " ") -> 0 | O69: =IF(E69<>"", _xlfn.XLOOKUP(E69, DATABASE_FG!C:C, DATABASE_FG!F:F), " ") -> Ventilkoerper | P69: =IFERROR(INDEX(DATABASE_FG!$G$5:$G$367, MATCH(E69, DATABASE_FG!$C$5:$C$367, 0)), "Not Found") -> 216 | R69: project | S69: =IFERROR(INDEX(DATABASE_FG!$L$5:$L$367, MATCH(E69, DATABASE_FG!$C$5:$C$367, 0)), " ") -> 56 | T69: yes | Z69: 240708/241207 | AA69: Yes | AB69: 45527 | AC69: 202401056 | AD69: =IF(NOT(ISBLANK(AC69)), C69, "") -> 4508771389 | AE69: =IF(NOT(ISBLANK(AC69)), E69, "") -> 1818509138 | AF69: 5 | AG69: =AF69*H69 -> 22.65 | AI69: PPAP | AJ69: 20241099-26.08.2024 | AK69: =IF(AB69="", IF(K69 < TODAY(), "Late", ""), IF(AB69 <= K69 + 2, "On Time", "Late")) -> On Time | AL69: =TEXT(K69,"mmmm") -> September | AM69: =YEAR(Table1[[#This Row],[ETA As requested dd.mm.yyyy]]) -> 2024
A70: BOSCH Homburg | B70: firm | C70: 4508771389 | E70: 1818509164 | F70: =IFERROR(VLOOKUP(Table1[[#This Row],[Part Number]],DATABASE_FG!$C$6:D10059,2,FALSE)," ") -> VALVE BODY | G70: =IFERROR(_xlfn.XLOOKUP(Table1[[#This Row],[Part Number]],Table3[Part number],Table3[Drawing Revision]),"") -> 1 | H70: {=IFERROR(INDEX(PDB!$C:$AT,MATCH(E70,PDB!$B:$B,0),MATCH(YEAR(K70),0+PDB!$C$1:$AT$1,0)),"")} -> 6.4 | I70: 5 | J70: =IFERROR(Table1[[#This Row],[Quantity]]*Table1[[#This Row],[Price/Unit EUR]]," ") -> 32 | K70: 45541 | L70: =WEEKNUM(Table1[[#This Row],[ETA As requested dd.mm.yyyy]]) -> 36 | M70: =YEAR(Table1[[#This Row],[ETA As requested dd.mm.yyyy]]) -> 2024 | N70: =IFERROR(INDEX(DATABASE_FG!$H$5:$H$367, MATCH(E70, DATABASE_FG!$C$5:$C$367, 0)), " ") -> 0 | O70: =IF(E70<>"", _xlfn.XLOOKUP(E70, DATABASE_FG!C:C, DATABASE_FG!F:F), " ") -> Ventilkoerper | P70: =IFERROR(INDEX(DATABASE_FG!$G$5:$G$367, MATCH(E70, DATABASE_FG!$C$5:$C$367, 0)), "Not Found") -> 50 | Q70: 60 | R70: project | S70: =IFERROR(INDEX(DATABASE_FG!$L$5:$L$367, MATCH(E70, DATABASE_FG!$C$5:$C$367, 0)), " ") -> 56 | T70: yes | X70: project | Y70: yes | AA70: Yes | AB70: 45930 | AC70: 251174 | AD70: =IF(NOT(ISBLANK(AC70)), C70, "") -> 4508771389 | AE70: =IF(NOT(ISBLANK(AC70)), E70, "") -> 1818509164 | AF70: 5 | AG70: =AF70*H70 -> 32 | AJ70: 20251273-30.09.2025/20251277-01.10.2025/20251278-01.10.2025 | AK70: =IF(AB70="", IF(K70 < TODAY(), "Late", ""), IF(AB70 <= K70 + 2, "On Time", "Late")) -> Late | AL70: =TEXT(K70,"mmmm") -> September | AM70: =YEAR(Table1[[#This Row],[ETA As requested dd.mm.yyyy]]) -> 2024
A71: BOSCH Homburg | B71: firm | C71: 4508771389 | E71: 1818509172 | F71: =IFERROR(VLOOKUP(Table1[[#This Row],[Part Number]],DATABASE_FG!$C$6:D10060,2,FALSE)," ") -> VALVE BODY | G71: =IFERROR(_xlfn.XLOOKUP(Table1[[#This Row],[Part Number]],Table3[Part number],Table3[Drawing Revision]),"") -> 1 | H71: {=IFERROR(INDEX(PDB!$C:$AT,MATCH(E71,PDB!$B:$B,0),MATCH(YEAR(K71),0+PDB!$C$1:$AT$1,0)),"")} -> 4.05 | I71: 5 | J71: =IFERROR(Table1[[#This Row],[Quantity]]*Table1[[#This Row],[Price/Unit EUR]]," ") -> 20.25 | K71: 45541 | L71: =WEEKNUM(Table1[[#This Row],[ETA As requested dd.mm.yyyy]]) -> 36 | M71: =YEAR(Table1[[#This Row],[ETA As requested dd.mm.yyyy]]) -> 2024 | N71: =IFERROR(INDEX(DATABASE_FG!$H$5:$H$367, MATCH(E71, DATABASE_FG!$C$5:$C$367, 0)), " ") -> 0 | O71: =IF(E71<>"", _xlfn.XLOOKUP(E71, DATABASE_FG!C:C, DATABASE_FG!F:F), " ") -> Ventilkoerper | P71: =IFERROR(INDEX(DATABASE_FG!$G$5:$G$367, MATCH(E71, DATABASE_FG!$C$5:$C$367, 0)), "Not Found") -> 1 | Q71: 60 | R71: project | S71: =IFERROR(INDEX(DATABASE_FG!$L$5:$L$367, MATCH(E71, DATABASE_FG!$C$5:$C$367, 0)), " ") -> 56 | T71: yes | X71: project | Y71: yes | AA71: Yes | AB71: 45930 | AC71: 251173 | AD71: =IF(NOT(ISBLANK(AC71)), C71, "") -> 4508771389 | AE71: =IF(NOT(ISBLANK(AC71)), E71, "") -> 1818509172 | AF71: 5 | AG71: =AF71*H71 -> 20.25 | AI71: PPAP | AJ71: 20221265-20.12.2022/20251275-01.10.2025/20251279-01.10.2025 | AK71: =IF(AB71="", IF(K71 < TODAY(), "Late", ""), IF(AB71 <= K71 + 2, "On Time", "Late")) -> Late | AL71: =TEXT(K71,"mmmm") -> September | AM71: =YEAR(Table1[[#This Row],[ETA As requested dd.mm.yyyy]]) -> 2024
A72: BOSCH Homburg | B72: firm | C72: 4508769328 | E72: 1818509193 | F72: =IFERROR(VLOOKUP(Table1[[#This Row],[Part Number]],DATABASE_FG!$C$6:D10061,2,FALSE)," ") -> VALVE BODY | G72: =IFERROR(_xlfn.XLOOKUP(Table1[[#This Row],[Part Number]],Table3[Part number],Table3[Drawing Revision]),"") -> 1 | H72: {=IFERROR(INDEX(PDB!$C:$AT,MATCH(E72,PDB!$B:$B,0),MATCH(YEAR(K72),0+PDB!$C$1:$AT$1,0)),"")} -> 3.27 | I72: 5 | J72: =IFERROR(Table1[[#This Row],[Quantity]]*Table1[[#This Row],[Price/Unit EUR]]," ") -> 16.35 | K72: 45541 | L72: =WEEKNUM(Table1[[#This Row],[ETA As requested dd.mm.yyyy]]) -> 36 | M72: =YEAR(Table1[[#This Row],[ETA As requested dd.mm.yyyy]]) -> 2024 | N72: =IFERROR(INDEX(DATABASE_FG!$H$5:$H$367, MATCH(E72, DATABASE_FG!$C$5:$C$367, 0)), " ") -> 0 | O72: =IF(E72<>"", _xlfn.XLOOKUP(E72, DATABASE_FG!C:C, DATABASE_FG!F:F), " ") -> Ventilkoerper | P72: =IFERROR(INDEX(DATABASE_FG!$G$5:$G$367, MATCH(E72, DATABASE_FG!$C$5:$C$367, 0)), "Not Found") -> 300 | R72: project | S72: =IFERROR(INDEX(DATABASE_FG!$L$5:$L$367, MATCH(E72, DATABASE_FG!$C$5:$C$367, 0)), " ") -> 56 | T72: yes | Z72: 240813 | AA72: Yes | AB72: 45541 | AC72: 202401114 | AD72: =IF(NOT(ISBLANK(AC72)), C72, "") -> 4508769328 | AE72: =IF(NOT(ISBLANK(AC72)), E72, "") -> 1818509193 | AF72: 5 | AG72: =AF72*H72 -> 16.35 | AI72: PPAP | AJ72: 20241155-06.09.2024 | AK72: =IF(AB72="", IF(K72 < TODAY(), "Late", ""), IF(AB72 <= K72 + 2, "On Time", "Late")) -> On Time | AL72: =TEXT(K72,"mmmm") -> September | AM72: =YEAR(Table1[[#This Row],[ETA As requested dd.mm.yyyy]]) -> 2024
A73: BOSCH Homburg | B73: firm | C73: 4508756412 | E73: 1818509251 | F73: =IFERROR(VLOOKUP(Table1[[#This Row],[Part Number]],DATABASE_FG!$C$6:D10062,2,FALSE)," ") -> VALVE BODY | G73: =IFERROR(_xlfn.XLOOKUP(Table1[[#This Row],[Part Number]],Table3[Part number],Table3[Drawing Revision]),"") -> 1 | H73: {=IFERROR(INDEX(PDB!$C:$AT,MATCH(E73,PDB!$B:$B,0),MATCH(YEAR(K73),0+PDB!$C$1:$AT$1,0)),"")} -> 13.79 | I73: 5 | J73: =IFERROR(Table1[[#This Row],[Quantity]]*Table1[[#This Row],[Price/Unit EUR]]," ") -> 68.95 | K73: 45541 | L73: =WEEKNUM(Table1[[#This Row],[ETA As requested dd.mm.yyyy]]) -> 36 | M73: =YEAR(Table1[[#This Row],[ETA As requested dd.mm.yyyy]]) -> 2024 | N73: =IFERROR(INDEX(DATABASE_FG!$H$5:$H$367, MATCH(E73, DATABASE_FG!$C$5:$C$367, 0)), " ") -> 0 | O73: =IF(E73<>"", _xlfn.XLOOKUP(E73, DATABASE_FG!C:C, DATABASE_FG!F:F), " ") -> Ventilkoerper | P73: =IFERROR(INDEX(DATABASE_FG!$G$5:$G$367, MATCH(E73, DATABASE_FG!$C$5:$C$367, 0)), "Not Found") -> 360 | R73: project | S73: =IFERROR(INDEX(DATABASE_FG!$L$5:$L$367, MATCH(E73, DATABASE_FG!$C$5:$C$367, 0)), " ") -> 56 | T73: yes | Z73: 241006 | AA73: Yes | AB73: 45426 | AC73: 2024470 | AD73: =IF(NOT(ISBLANK(AC73)), C73, "") -> 4508756412 | AE73: =IF(NOT(ISBLANK(AC73)), E73, "") -> 1818509251 | AF73: 5 | AG73: =AF73*H73 -> 68.95 | AI73: validare | AJ73: 20240540-14.05.2024 | AK73: =IF(AB73="", IF(K73 < TODAY(), "Late", ""), IF(AB73 <= K73 + 2, "On Time", "Late")) -> On Time | AL73: =TEXT(K73,"mmmm") -> September | AM73: =YEAR(Table1[[#This Row],[ETA As requested dd.mm.yyyy]]) -> 2024
A74: BOSCH Homburg | B74: firm | C74: 4508427493 | E74: 1818509259 | F74: =IFERROR(VLOOKUP(Table1[[#This Row],[Part Number]],DATABASE_FG!$C$6:D10063,2,FALSE)," ") -> VALVE BODY | G74: =IFERROR(_xlfn.XLOOKUP(Table1[[#This Row],[Part Number]],Table3[Part number],Table3[Drawing Revision]),"") -> 1 | H74: {=IFERROR(INDEX(PDB!$C:$AT,MATCH(E74,PDB!$B:$B,0),MATCH(YEAR(K74),0+PDB!$C$1:$AT$1,0)),"")} -> 13.47 | I74: 5 | J74: =IFERROR(Table1[[#This Row],[Quantity]]*Table1[[#This Row],[Price/Unit EUR]]," ") -> 67.35 | K74: 45541 | L74: =WEEKNUM(Table1[[#This Row],[ETA As requested dd.mm.yyyy]]) -> 36 | M74: =YEAR(Table1[[#This Row],[ETA As requested dd.mm.yyyy]]) -> 2024 | N74: =IFERROR(INDEX(DATABASE_FG!$H$5:$H$367, MATCH(E74, DATABASE_FG!$C$5:$C$367, 0)), " ") -> 0 | O74: =IF(E74<>"", _xlfn.XLOOKUP(E74, DATABASE_FG!C:C, DATABASE_FG!F:F), " ") -> Ventilkoerper | P74: =IFERROR(INDEX(DATABASE_FG!$G$5:$G$367, MATCH(E74, DATABASE_FG!$C$5:$C$367, 0)), "Not Found") -> 30 | Q74: 60 | R74: project | S74: =IFERROR(INDEX(DATABASE_FG!$L$5:$L$367, MATCH(E74, DATABASE_FG!$C$5:$C$367, 0)), " ") -> 56 | T74: yes | Z74: 241109 | AA74: Yes | AB74: 45496 | AC74: 2024896 | AD74: =IF(NOT(ISBLANK(AC74)), C74, "") -> 4508427493 | AE74: =IF(NOT(ISBLANK(AC74)), E74, "") -> 1818509259 | AF74: 5 | AG74: =AF74*H74 -> 67.35 | AJ74: 20240939-23.07.2024 | AK74: =IF(AB74="", IF(K74 < TODAY(), "Late", ""), IF(AB74 <= K74 + 2, "On Time", "Late")) -> On Time | AL74: =TEXT(K74,"mmmm") -> September | AM74: =YEAR(Table1[[#This Row],[ETA As requested dd.mm.yyyy]]) -> 2024
A75: BOSCH Homburg | B75: firm | C75: 4509031934 | E75: 1818509259 | F75: =IFERROR(VLOOKUP(Table1[[#This Row],[Part Number]],DATABASE_FG!$C$6:D10064,2,FALSE)," ") -> VALVE BODY | G75: =IFERROR(_xlfn.XLOOKUP(Table1[[#This Row],[Part Number]],Table3[Part number],Table3[Drawing Revision]),"") -> 1 | H75: {=IFERROR(INDEX(PDB!$C:$AT,MATCH(E75,PDB!$B:$B,0),MATCH(YEAR(K75),0+PDB!$C$1:$AT$1,0)),"")} -> 13.47 | I75: 90 | J75: =IFERROR(Table1[[#This Row],[Quantity]]*Table1[[#This Row],[Price/Unit EUR]]," ") -> 1212.3 | K75: 45541 | L75: =WEEKNUM(Table1[[#This Row],[ETA As requested dd.mm.yyyy]]) -> 36 | M75: =YEAR(Table1[[#This Row],[ETA As requested dd.mm.yyyy]]) -> 2024 | N75: =IFERROR(INDEX(DATABASE_FG!$H$5:$H$367, MATCH(E75, DATABASE_FG!$C$5:$C$367, 0)), " ") -> 0 | O75: =IF(E75<>"", _xlfn.XLOOKUP(E75, DATABASE_FG!C:C, DATABASE_FG!F:F), " ") -> Ventilkoerper | P75: =IFERROR(INDEX(DATABASE_FG!$G$5:$G$367, MATCH(E75, DATABASE_FG!$C$5:$C$367, 0)), "Not Found") -> 30 | Q75: 60 | R75: project | S75: =IFERROR(INDEX(DATABASE_FG!$L$5:$L$367, MATCH(E75, DATABASE_FG!$C$5:$C$367, 0)), " ") -> 56 | T75: yes | X75: ETA TBC | AA75: Yes | AB75: 45876 | AD75: =IF(NOT(ISBLANK(AC75)), C75, "") | AE75: =IF(NOT(ISBLANK(AC75)), E75, "") | AF75: 0 | AG75: =AF75*H75 -> 0 | AK75: =IF(AB75="", IF(K75 < TODAY(), "Late", ""), IF(AB75 <= K75 + 2, "On Time", "Late")) -> Late | AL75: =TEXT(K75,"mmmm") -> September | AM75: =YEAR(Table1[[#This Row],[ETA As requested dd.mm.yyyy]]) -> 2024
A76: BOSCH Homburg | B76: firm | C76: 4508756412 | E76: 1818509265 | F76: =IFERROR(VLOOKUP(Table1[[#This Row],[Part Number]],DATABASE_FG!$C$6:D10065,2,FALSE)," ") -> VALVE BODY | G76: =IFERROR(_xlfn.XLOOKUP(Table1[[#This Row],[Part Number]],Table3[Part number],Table3[Drawing Revision]),"") -> 1 | H76: {=IFERROR(INDEX(PDB!$C:$AT,MATCH(E76,PDB!$B:$B,0),MATCH(YEAR(K76),0+PDB!$C$1:$AT$1,0)),"")} -> 14.01 | I76: 5 | J76: =IFERROR(Table1[[#This Row],[Quantity]]*Table1[[#This Row],[Price/Unit EUR]]," ") -> 70.05 | K76: 45541 | L76: =WEEKNUM(Table1[[#This Row],[ETA As requested dd.mm.yyyy]]) -> 36 | M76: =YEAR(Table1[[#This Row],[ETA As requested dd.mm.yyyy]]) -> 2024 | N76: =IFERROR(INDEX(DATABASE_FG!$H$5:$H$367, MATCH(E76, DATABASE_FG!$C$5:$C$367, 0)), " ") -> 0 | O76: =IF(E76<>"", _xlfn.XLOOKUP(E76, DATABASE_FG!C:C, DATABASE_FG!F:F), " ") -> Ventilkoerper | P76: =IFERROR(INDEX(DATABASE_FG!$G$5:$G$367, MATCH(E76, DATABASE_FG!$C$5:$C$367, 0)), "Not Found") -> 10 | R76: project | S76: =IFERROR(INDEX(DATABASE_FG!$L$5:$L$367, MATCH(E76, DATABASE_FG!$C$5:$C$367, 0)), " ") -> 56 | T76: yes | Z76: 241005 | AA76: Yes | AB76: 45558 | AC76: 202401159 | AD76: =IF(NOT(ISBLANK(AC76)), C76, "") -> 4508756412 | AE76: =IF(NOT(ISBLANK(AC76)), E76, "") -> 1818509265 | AF76: 5 | AG76: =AF76*H76 -> 70.05 | AJ76: 20241223 23.09.2024 | AK76: =IF(AB76="", IF(K76 < TODAY(), "Late", ""), IF(AB76 <= K76 + 2, "On Time", "Late")) -> Late | AL76: =TEXT(K76,"mmmm") -> September | AM76: =YEAR(Table1[[#This Row],[ETA As requested dd.mm.yyyy]]) -> 2024
A77: BOSCH Homburg | B77: firm | C77: 4508771613 | E77: 1818509284 | F77: =IFERROR(VLOOKUP(Table1[[#This Row],[Part Number]],DATABASE_FG!$C$6:D10066,2,FALSE)," ") -> VALVE BODY | G77: =IFERROR(_xlfn.XLOOKUP(Table1[[#This Row],[Part Number]],Table3[Part number],Table3[Drawing Revision]),"") -> 1 | H77: {=IFERROR(INDEX(PDB!$C:$AT,MATCH(E77,PDB!$B:$B,0),MATCH(YEAR(K77),0+PDB!$C$1:$AT$1,0)),"")} -> 8.45 | I77: 5 | J77: =IFERROR(Table1[[#This Row],[Quantity]]*Table1[[#This Row],[Price/Unit EUR]]," ") -> 42.25 | K77: 45541 | L77: =WEEKNUM(Table1[[#This Row],[ETA As requested dd.mm.yyyy]]) -> 36 | M77: =YEAR(Table1[[#This Row],[ETA As requested dd.mm.yyyy]]) -> 2024 | N77: =IFERROR(INDEX(DATABASE_FG!$H$5:$H$367, MATCH(E77, DATABASE_FG!$C$5:$C$367, 0)), " ") -> 0 | O77: =IF(E77<>"", _xlfn.XLOOKUP(E77, DATABASE_FG!C:C, DATABASE_FG!F:F), " ") -> Ventilkoerper | P77: =IFERROR(INDEX(DATABASE_FG!$G$5:$G$367, MATCH(E77, DATABASE_FG!$C$5:$C$367, 0)), "Not Found") -> 117 | Q77: 60 | R77: project | S77: =IFERROR(INDEX(DATABASE_FG!$L$5:$L$367, MATCH(E77, DATABASE_FG!$C$5:$C$367, 0)), " ") -> 56 | T77: yes | Z77: 240309 | AA77: Yes | AB77: 45463 | AC77: 2024692 | AD77: =IF(NOT(ISBLANK(AC77)), C77, "") -> 4508771613 | AE77: =IF(NOT(ISBLANK(AC77)), E77, "") -> 1818509284 | AF77: 5 | AG77: =AF77*H77 -> 42.25 | AI77: validare | AJ77: 20240733-20.06.2024 | AK77: =IF(AB77="", IF(K77 < TODAY(), "Late", ""), IF(AB77 <= K77 + 2, "On Time", "Late")) -> On Time | AL77: =TEXT(K77,"mmmm") -> September | AM77: =YEAR(Table1[[#This Row],[ETA As requested dd.mm.yyyy]]) -> 2024
A78: BOSCH Homburg | B78: firm | C78: 5500552636 | D78: 45728 | E78: 1818509284 | F78: =IFERROR(VLOOKUP(Table1[[#This Row],[Part Number]],DATABASE_FG!$C$6:D10067,2,FALSE)," ") -> VALVE BODY | G78: =IFERROR(_xlfn.XLOOKUP(Table1[[#This Row],[Part Number]],Table3[Part number],Table3[Drawing Revision]),"") -> 1 | H78: {=IFERROR(INDEX(PDB!$C:$AT,MATCH(E78,PDB!$B:$B,0),MATCH(YEAR(K78),0+PDB!$C$1:$AT$1,0)),"")} -> 8.28 | I78: 195 | J78: =IFERROR(Table1[[#This Row],[Quantity]]*Table1[[#This Row],[Price/Unit EUR]]," ") -> 1614.6 | K78: 45777 | L78: =WEEKNUM(Table1[[#This Row],[ETA As requested dd.mm.yyyy]]) -> 18 | M78: =YEAR(Table1[[#This Row],[ETA As requested dd.mm.yyyy]]) -> 2025 | N78: =IFERROR(INDEX(DATABASE_FG!$H$5:$H$367, MATCH(E78, DATABASE_FG!$C$5:$C$367, 0)), " ") -> 0 | O78: =IF(E78<>"", _xlfn.XLOOKUP(E78, DATABASE_FG!C:C, DATABASE_FG!F:F), " ") -> Ventilkoerper | P78: 0 | R78: approved | S78: =IFERROR(INDEX(DATABASE_FG!$L$5:$L$367, MATCH(E78, DATABASE_FG!$C$5:$C$367, 0)), " ") -> 56 | T78: yes | W78: yes | AA78: Yes | AB78: 45869 | AC78: 251105 | AD78: =IF(NOT(ISBLANK(AC78)), C78, "") -> 5500552636 | AE78: =IF(NOT(ISBLANK(AC78)), E78, "") -> 1818509284 | AF78: 195 | AG78: =AF78*H78 -> 1614.6 | AI78: Eva Roth | AJ78: 20251013/31.07.2025/20251373/20251374-30.10.2025 | AK78: =IF(AB78="", IF(K78 < TODAY(), "Late", ""), IF(AB78 <= K78 + 2, "On Time", "Late")) -> Late | AL78: =TEXT(K78,"mmmm") -> April | AM78: =YEAR(Table1[[#This Row],[ETA As requested dd.mm.yyyy]]) -> 2025
A79: BOSCH Homburg | B79: firm | C79: 5500552636 | D79: 45728 | E79: 1818509284 | F79: =IFERROR(VLOOKUP(Table1[[#This Row],[Part Number]],DATABASE_FG!$C$6:D10068,2,FALSE)," ") -> VALVE BODY | G79: =IFERROR(_xlfn.XLOOKUP(Table1[[#This Row],[Part Number]],Table3[Part number],Table3[Drawing Revision]),"") -> 1 | H79: {=IFERROR(INDEX(PDB!$C:$AT,MATCH(E79,PDB!$B:$B,0),MATCH(YEAR(K79),0+PDB!$C$1:$AT$1,0)),"")} -> 8.28 | I79: 234 | J79: =IFERROR(Table1[[#This Row],[Quantity]]*Table1[[#This Row],[Price/Unit EUR]]," ") -> 1937.52 | K79: 45791 | L79: =WEEKNUM(Table1[[#This Row],[ETA As requested dd.mm.yyyy]]) -> 20 | M79: =YEAR(Table1[[#This Row],[ETA As requested dd.mm.yyyy]]) -> 2025 | N79: =IFERROR(INDEX(DATABASE_FG!$H$5:$H$367, MATCH(E79, DATABASE_FG!$C$5:$C$367, 0)), " ") -> 0 | O79: =IF(E79<>"", _xlfn.XLOOKUP(E79, DATABASE_FG!C:C, DATABASE_FG!F:F), " ") -> Ventilkoerper | P79: 0 | R79: approved | S79: =IFERROR(INDEX(DATABASE_FG!$L$5:$L$367, MATCH(E79, DATABASE_FG!$C$5:$C$367, 0)), " ") -> 56 | T79: yes | AA79: Yes | AB79: 45869 | AC79: 251105 | AD79: =IF(NOT(ISBLANK(AC79)), C79, "") -> 5500552636 | AE79: =IF(NOT(ISBLANK(AC79)), E79, "") -> 1818509284 | AF79: 234 | AG79: =AF79*H79 -> 1937.52 | AI79: Eva Roth | AJ79: 20251013/31.07.2025 | AK79: =IF(AB79="", IF(K79 < TODAY(), "Late", ""), IF(AB79 <= K79 + 2, "On Time", "Late")) -> Late | AL79: =TEXT(K79,"mmmm") -> May | AM79: =YEAR(Table1[[#This Row],[ETA As requested dd.mm.yyyy]]) -> 2025
A80: BOSCH Homburg | B80: firm | C80: 4508771613 | E80: 1818509289 | F80: =IFERROR(VLOOKUP(Table1[[#This Row],[Part Number]],DATABASE_FG!$C$6:D10069,2,FALSE)," ") -> VALVE BODY | G80: =IFERROR(_xlfn.XLOOKUP(Table1[[#This Row],[Part Number]],Table3[Part number],Table3[Drawing Revision]),"") -> 1 | H80: {=IFERROR(INDEX(PDB!$C:$AT,MATCH(E80,PDB!$B:$B,0),MATCH(YEAR(K80),0+PDB!$C$1:$AT$1,0)),"")} -> 10.99 | I80: 5 | J80: =IFERROR(Table1[[#This Row],[Quantity]]*Table1[[#This Row],[Price/Unit EUR]]," ") -> 54.95 | K80: 45541 | L80: =WEEKNUM(Table1[[#This Row],[ETA As requested dd.mm.yyyy]]) -> 36 | M80: =YEAR(Table1[[#This Row],[ETA As requested dd.mm.yyyy]]) -> 2024 | N80: =IFERROR(INDEX(DATABASE_FG!$H$5:$H$367, MATCH(E80, DATABASE_FG!$C$5:$C$367, 0)), " ") -> 0 | O80: =IF(E80<>"", _xlfn.XLOOKUP(E80, DATABASE_FG!C:C, DATABASE_FG!F:F), " ") -> Ventilkoerper | P80: =IFERROR(INDEX(DATABASE_FG!$G$5:$G$367, MATCH(E80, DATABASE_FG!$C$5:$C$367, 0)), "Not Found") -> 70 | R80: project | S80: =IFERROR(INDEX(DATABASE_FG!$L$5:$L$367, MATCH(E80, DATABASE_FG!$C$5:$C$367, 0)), " ") -> 56 | T80: yes | Z80: 240605 | AA80: Yes | AB80: 45471 | AC80: 2024741 | AD80: =IF(NOT(ISBLANK(AC80)), C80, "") -> 4508771613 | AE80: =IF(NOT(ISBLANK(AC80)), E80, "") -> 1818509289 | AF80: 5 | AG80: =AF80*H80 -> 54.95 | AI80: validare | AJ80: 20240802-28.06.2024 | AK80: =IF(AB80="", IF(K80 < TODAY(), "Late", ""), IF(AB80 <= K80 + 2, "On Time", "Late")) -> On Time | AL80: =TEXT(K80,"mmmm") -> September | AM80: =YEAR(Table1[[#This Row],[ETA As requested dd.mm.yyyy]]) -> 2024
A81: BOSCH Homburg | B81: firm | C81: 5500494575 | D81: 45588 | E81: 1818509439 | F81: =IFERROR(VLOOKUP(Table1[[#This Row],[Part Number]],DATABASE_FG!$C$6:D10070,2,FALSE)," ") -> VALVE BODY . | G81: =IFERROR(_xlfn.XLOOKUP(Table1[[#This Row],[Part Number]],Table3[Part number],Table3[Drawing Revision]),"") -> AA | H81: {=IFERROR(INDEX(PDB!$C:$AT,MATCH(E81,PDB!$B:$B,0),MATCH(YEAR(K81),0+PDB!$C$1:$AT$1,0)),"")} -> 0.74 | I81: 300 | J81: =IFERROR(Table1[[#This Row],[Quantity]]*Table1[[#This Row],[Price/Unit EUR]]," ") -> 222 | K81: 45701 | L81: =WEEKNUM(Table1[[#This Row],[ETA As requested dd.mm.yyyy]]) -> 7 | M81: =YEAR(Table1[[#This Row],[ETA As requested dd.mm.yyyy]]) -> 2025 | N81: =IFERROR(INDEX(DATABASE_FG!$H$5:$H$367, MATCH(E81, DATABASE_FG!$C$5:$C$367, 0)), " ") -> 0 | O81: =IF(E81<>"", _xlfn.XLOOKUP(E81, DATABASE_FG!C:C, DATABASE_FG!F:F), " ") -> Ventilkoerper | P81: =IFERROR(INDEX(DATABASE_FG!$G$5:$G$367, MATCH(E81, DATABASE_FG!$C$5:$C$367, 0)), "Not Found") -> 10 | Q81: 60 | R81: approved | S81: =IFERROR(INDEX(DATABASE_FG!$L$5:$L$367, MATCH(E81, DATABASE_FG!$C$5:$C$367, 0)), " ") -> 42 | T81: no | Y81: ETA 25.02 | AA81: Yes | AB81: 45723 | AC81: 25341 | AD81: =IF(NOT(ISBLANK(AC81)), C81, "") -> 5500494575 | AE81: =IF(NOT(ISBLANK(AC81)), E81, "") -> 1818509439 | AF81: 300 | AG81: =AF81*H81 -> 222 | AJ81: 20250292-07.03.2025 | AK81: =IF(AB81="", IF(K81 < TODAY(), "Late", ""), IF(AB81 <= K81 + 2, "On Time", "Late")) -> Late | AL81: =TEXT(K81,"mmmm") -> February | AM81: =YEAR(Table1[[#This Row],[ETA As requested dd.mm.yyyy]]) -> 2025
A82: BOSCH Homburg | B82: firm | C82: 5500494575 | D82: 45588 | E82: 1818509439 | F82: =IFERROR(VLOOKUP(Table1[[#This Row],[Part Number]],DATABASE_FG!$C$6:D10071,2,FALSE)," ") -> VALVE BODY . | G82: =IFERROR(_xlfn.XLOOKUP(Table1[[#This Row],[Part Number]],Table3[Part number],Table3[Drawing Revision]),"") -> AA | H82: {=IFERROR(INDEX(PDB!$C:$AT,MATCH(E82,PDB!$B:$B,0),MATCH(YEAR(K82),0+PDB!$C$1:$AT$1,0)),"")} -> 0.74 | I82: 608 | J82: =IFERROR(Table1[[#This Row],[Quantity]]*Table1[[#This Row],[Price/Unit EUR]]," ") -> 449.92 | K82: 45701 | L82: =WEEKNUM(Table1[[#This Row],[ETA As requested dd.mm.yyyy]]) -> 7 | M82: =YEAR(Table1[[#This Row],[ETA As requested dd.mm.yyyy]]) -> 2025 | N82: =IFERROR(INDEX(DATABASE_FG!$H$5:$H$367, MATCH(E82, DATABASE_FG!$C$5:$C$367, 0)), " ") -> 0 | O82: =IF(E82<>"", _xlfn.XLOOKUP(E82, DATABASE_FG!C:C, DATABASE_FG!F:F), " ") -> Ventilkoerper | P82: =IFERROR(INDEX(DATABASE_FG!$G$5:$G$367, MATCH(E82, DATABASE_FG!$C$5:$C$367, 0)), "Not Found") -> 10 | Q82: 60 | R82: approved | S82: =IFERROR(INDEX(DATABASE_FG!$L$5:$L$367, MATCH(E82, DATABASE_FG!$C$5:$C$367, 0)), " ") -> 42 | T82: no | Y82: ETA 25.02 | AA82: Yes | AB82: 45727 | AC82: 25352 | AD82: =IF(NOT(ISBLANK(AC82)), C82, "") -> 5500494575 | AE82: =IF(NOT(ISBLANK(AC82)), E82, "") -> 1818509439 | AF82: 608 | AG82: =AF82*H82 -> 449.92 | AJ82: 20250313-13.03.2025 | AK82: =IF(AB82="", IF(K82 < TODAY(), "Late", ""), IF(AB82 <= K82 + 2, "On Time", "Late")) -> Late | AL82: =TEXT(K82,"mmmm") -> February | AM82: =YEAR(Table1[[#This Row],[ETA As requested dd.mm.yyyy]]) -> 2025
A83: BOSCH Homburg | B83: firm | C83: 5500494575 | D83: 45588 | E83: 1818509439 | F83: =IFERROR(VLOOKUP(Table1[[#This Row],[Part Number]],DATABASE_FG!$C$6:D10072,2,FALSE)," ") -> VALVE BODY . | G83: =IFERROR(_xlfn.XLOOKUP(Table1[[#This Row],[Part Number]],Table3[Part number],Table3[Drawing Revision]),"") -> AA | H83: {=IFERROR(INDEX(PDB!$C:$AT,MATCH(E83,PDB!$B:$B,0),MATCH(YEAR(K83),0+PDB!$C$1:$AT$1,0)),"")} -> 0.74 | I83: =1000-300-608 -> 92 | J83: =IFERROR(Table1[[#This Row],[Quantity]]*Table1[[#This Row],[Price/Unit EUR]]," ") -> 68.08 | K83: 45701 | L83: =WEEKNUM(Table1[[#This Row],[ETA As requested dd.mm.yyyy]]) -> 7 | M83: =YEAR(Table1[[#This Row],[ETA As requested dd.mm.yyyy]]) -> 2025 | N83: =IFERROR(INDEX(DATABASE_FG!$H$5:$H$367, MATCH(E83, DATABASE_FG!$C$5:$C$367, 0)), " ") -> 0 | O83: =IF(E83<>"", _xlfn.XLOOKUP(E83, DATABASE_FG!C:C, DATABASE_FG!F:F), " ") -> Ventilkoerper | P83: =IFERROR(INDEX(DATABASE_FG!$G$5:$G$367, MATCH(E83, DATABASE_FG!$C$5:$C$367, 0)), "Not Found") -> 10 | Q83: 60 | R83: approved | S83: =IFERROR(INDEX(DATABASE_FG!$L$5:$L$367, MATCH(E83, DATABASE_FG!$C$5:$C$367, 0)), " ") -> 42 | T83: no | Y83: ETA 25.02 | AA83: Yes | AB83: 45755 | AC83: 25560 | AD83: =IF(NOT(ISBLANK(AC83)), C83, "") -> 5500494575 | AE83: =IF(NOT(ISBLANK(AC83)), E83, "") -> 1818509439 | AF83: 92 | AG83: =AF83*H83 -> 68.08 | AJ83: 20250487-10.04.2025 | AK83: =IF(AB83="", IF(K83 < TODAY(), "Late", ""), IF(AB83 <= K83 + 2, "On Time", "Late")) -> Late | AL83: =TEXT(K83,"mmmm") -> February | AM83: =YEAR(Table1[[#This Row],[ETA As requested dd.mm.yyyy]]) -> 2025
A84: BOSCH Homburg | B84: forecast | C84: 5500494575 | D84: 45588 | E84: 1818509439 | F84: =IFERROR(VLOOKUP(Table1[[#This Row],[Part Number]],DATABASE_FG!$C$6:D10073,2,FALSE)," ") -> VALVE BODY . | G84: =IFERROR(_xlfn.XLOOKUP(Table1[[#This Row],[Part Number]],Table3[Part number],Table3[Drawing Revision]),"") -> AA | H84: {=IFERROR(INDEX(PDB!$C:$AT,MATCH(E84,PDB!$B:$B,0),MATCH(YEAR(K84),0+PDB!$C$1:$AT$1,0)),"")} -> 0.74 | I84: 45 | J84: =IFERROR(Table1[[#This Row],[Quantity]]*Table1[[#This Row],[Price/Unit EUR]]," ") -> 33.3 | K84: 45999 | L84: =WEEKNUM(Table1[[#This Row],[ETA As requested dd.mm.yyyy]]) -> 50 | M84: =YEAR(Table1[[#This Row],[ETA As requested dd.mm.yyyy]]) -> 2025 | N84: =IFERROR(INDEX(DATABASE_FG!$H$5:$H$367, MATCH(E84, DATABASE_FG!$C$5:$C$367, 0)), " ") -> 0 | O84: =IF(E84<>"", _xlfn.XLOOKUP(E84, DATABASE_FG!C:C, DATABASE_FG!F:F), " ") -> Ventilkoerper | P84: =IFERROR(INDEX(DATABASE_FG!$G$5:$G$367, MATCH(E84, DATABASE_FG!$C$5:$C$367, 0)), "Not Found") -> 10 | Q84: 60 | R84: approved | S84: =IFERROR(INDEX(DATABASE_FG!$L$5:$L$367, MATCH(E84, DATABASE_FG!$C$5:$C$367, 0)), " ") -> 42 | T84: no | AA84: Yes | AB84: 45755 | AC84: 25560 | AD84: =IF(NOT(ISBLANK(AC84)), C84, "") -> 5500494575 | AE84: =IF(NOT(ISBLANK(AC84)), E84, "") -> 1818509439 | AF84: 45 | AG84: =AF84*H84 -> 33.3 | AJ84: 20250487-10.04.2025 | AK84: =IF(AB84="", IF(K84 < TODAY(), "Late", ""), IF(AB84 <= K84 + 2, "On Time", "Late")) -> On Time | AL84: =TEXT(K84,"mmmm") -> December | AM84: =YEAR(Table1[[#This Row],[ETA As requested dd.mm.yyyy]]) -> 2025
A85: BOSCH Homburg | B85: forecast | C85: 5500494575 | D85: 45939 | E85: 1818509439 | F85: =IFERROR(VLOOKUP(Table1[[#This Row],[Part Number]],DATABASE_FG!$C$6:D10074,2,FALSE)," ") -> VALVE BODY . | G85: =IFERROR(_xlfn.XLOOKUP(Table1[[#This Row],[Part Number]],Table3[Part number],Table3[Drawing Revision]),"") -> AA | H85: {=IFERROR(INDEX(PDB!$C:$AT,MATCH(E85,PDB!$B:$B,0),MATCH(YEAR(K85),0+PDB!$C$1:$AT$1,0)),"")} -> 0 | I85: 180 | J85: =IFERROR(Table1[[#This Row],[Quantity]]*Table1[[#This Row],[Price/Unit EUR]]," ") -> 0 | K85: 46044 | L85: =WEEKNUM(Table1[[#This Row],[ETA As requested dd.mm.yyyy]]) -> 4 | M85: =YEAR(Table1[[#This Row],[ETA As requested dd.mm.yyyy]]) -> 2026 | N85: =IFERROR(INDEX(DATABASE_FG!$H$5:$H$367, MATCH(E85, DATABASE_FG!$C$5:$C$367, 0)), " ") -> 0 | O85: =IF(E85<>"", _xlfn.XLOOKUP(E85, DATABASE_FG!C:C, DATABASE_FG!F:F), " ") -> Ventilkoerper | P85: =IFERROR(INDEX(DATABASE_FG!$G$5:$G$367, MATCH(E85, DATABASE_FG!$C$5:$C$367, 0)), "Not Found") -> 10 | Q85: 60 | R85: approved | S85: =IFERROR(INDEX(DATABASE_FG!$L$5:$L$367, MATCH(E85, DATABASE_FG!$C$5:$C$367, 0)), " ") -> 42 | T85: no | AA85: No | AD85: =IF(NOT(ISBLANK(AC85)), C85, "") | AE85: =IF(NOT(ISBLANK(AC85)), E85, "") | AG85: =AF85*H85 -> 0 | AK85: =IF(AB85="", IF(K85 < TODAY(), "Late", ""), IF(AB85 <= K85 + 2, "On Time", "Late")) | AL85: =TEXT(K85,"mmmm") -> January | AM85: =YEAR(Table1[[#This Row],[ETA As requested dd.mm.yyyy]]) -> 2026
A86: BOSCH Homburg | B86: forecast | C86: 5500494575 | D86: 45939 | E86: 1818509439 | F86: =IFERROR(VLOOKUP(Table1[[#This Row],[Part Number]],DATABASE_FG!$C$6:D10075,2,FALSE)," ") -> VALVE BODY . | G86: =IFERROR(_xlfn.XLOOKUP(Table1[[#This Row],[Part Number]],Table3[Part number],Table3[Drawing Revision]),"") -> AA | H86: {=IFERROR(INDEX(PDB!$C:$AT,MATCH(E86,PDB!$B:$B,0),MATCH(YEAR(K86),0+PDB!$C$1:$AT$1,0)),"")} -> 0 | I86: 300 | J86: =IFERROR(Table1[[#This Row],[Quantity]]*Table1[[#This Row],[Price/Unit EUR]]," ") -> 0 | K86: 46121 | L86: =WEEKNUM(Table1[[#This Row],[ETA As requested dd.mm.yyyy]]) -> 15 | M86: =YEAR(Table1[[#This Row],[ETA As requested dd.mm.yyyy]]) -> 2026 | N86: =IFERROR(INDEX(DATABASE_FG!$H$5:$H$367, MATCH(E86, DATABASE_FG!$C$5:$C$367, 0)), " ") -> 0 | O86: =IF(E86<>"", _xlfn.XLOOKUP(E86, DATABASE_FG!C:C, DATABASE_FG!F:F), " ") -> Ventilkoerper | P86: =IFERROR(INDEX(DATABASE_FG!$G$5:$G$367, MATCH(E86, DATABASE_FG!$C$5:$C$367, 0)), "Not Found") -> 10 | Q86: 61 | R86: approved | S86: =IFERROR(INDEX(DATABASE_FG!$L$5:$L$367, MATCH(E86, DATABASE_FG!$C$5:$C$367, 0)), " ") -> 42 | T86: no | AA86: No | AD86: =IF(NOT(ISBLANK(AC86)), C86, "") | AE86: =IF(NOT(ISBLANK(AC86)), E86, "") | AG86: =AF86*H86 -> 0 | AK86: =IF(AB86="", IF(K86 < TODAY(), "Late", ""), IF(AB86 <= K86 + 2, "On Time", "Late")) | AL86: =TEXT(K86,"mmmm") -> April | AM86: =YEAR(Table1[[#This Row],[ETA As requested dd.mm.yyyy]]) -> 2026
A87: BOSCH Homburg | B87: forecast | C87: 5500494575 | D87: 45939 | E87: 1818509439 | F87: =IFERROR(VLOOKUP(Table1[[#This Row],[Part Number]],DATABASE_FG!$C$6:D10076,2,FALSE)," ") -> VALVE BODY . | G87: =IFERROR(_xlfn.XLOOKUP(Table1[[#This Row],[Part Number]],Table3[Part number],Table3[Drawing Revision]),"") -> AA | H87: {=IFERROR(INDEX(PDB!$C:$AT,MATCH(E87,PDB!$B:$B,0),MATCH(YEAR(K87),0+PDB!$C$1:$AT$1,0)),"")} -> 0 | I87: 300 | J87: =IFERROR(Table1[[#This Row],[Quantity]]*Table1[[#This Row],[Price/Unit EUR]]," ") -> 0 | K87: 46202 | L87: =WEEKNUM(Table1[[#This Row],[ETA As requested dd.mm.yyyy]]) -> 27 | M87: =YEAR(Table1[[#This Row],[ETA As requested dd.mm.yyyy]]) -> 2026 | N87: =IFERROR(INDEX(DATABASE_FG!$H$5:$H$367, MATCH(E87, DATABASE_FG!$C$5:$C$367, 0)), " ") -> 0 | O87: =IF(E87<>"", _xlfn.XLOOKUP(E87, DATABASE_FG!C:C, DATABASE_FG!F:F), " ") -> Ventilkoerper | P87: =IFERROR(INDEX(DATABASE_FG!$G$5:$G$367, MATCH(E87, DATABASE_FG!$C$5:$C$367, 0)), "Not Found") -> 10 | Q87: 61 | R87: approved | S87: =IFERROR(INDEX(DATABASE_FG!$L$5:$L$367, MATCH(E87, DATABASE_FG!$C$5:$C$367, 0)), " ") -> 42 | T87: no | AA87: No | AD87: =IF(NOT(ISBLANK(AC87)), C87, "") | AE87: =IF(NOT(ISBLANK(AC87)), E87, "") | AG87: =AF87*H87 -> 0 | AK87: =IF(AB87="", IF(K87 < TODAY(), "Late", ""), IF(AB87 <= K87 + 2, "On Time", "Late")) | AL87: =TEXT(K87,"mmmm") -> June | AM87: =YEAR(Table1[[#This Row],[ETA As requested dd.mm.yyyy]]) -> 2026
A88: BOSCH Homburg | B88: forecast | C88: 5500494575 | D88: 45939 | E88: 1818509439 | F88: =IFERROR(VLOOKUP(Table1[[#This Row],[Part Number]],DATABASE_FG!$C$6:D10077,2,FALSE)," ") -> VALVE BODY . | G88: =IFERROR(_xlfn.XLOOKUP(Table1[[#This Row],[Part Number]],Table3[Part number],Table3[Drawing Revision]),"") -> AA | H88: {=IFERROR(INDEX(PDB!$C:$AT,MATCH(E88,PDB!$B:$B,0),MATCH(YEAR(K88),0+PDB!$C$1:$AT$1,0)),"")} -> 0 | I88: 291 | J88: =IFERROR(Table1[[#This Row],[Quantity]]*Table1[[#This Row],[Price/Unit EUR]]," ") -> 0 | K88: 46364 | L88: =WEEKNUM(Table1[[#This Row],[ETA As requested dd.mm.yyyy]]) -> 50 | M88: =YEAR(Table1[[#This Row],[ETA As requested dd.mm.yyyy]]) -> 2026 | N88: =IFERROR(INDEX(DATABASE_FG!$H$5:$H$367, MATCH(E88, DATABASE_FG!$C$5:$C$367, 0)), " ") -> 0 | O88: =IF(E88<>"", _xlfn.XLOOKUP(E88, DATABASE_FG!C:C, DATABASE_FG!F:F), " ") -> Ventilkoerper | P88: =IFERROR(INDEX(DATABASE_FG!$G$5:$G$367, MATCH(E88, DATABASE_FG!$C$5:$C$367, 0)), "Not Found") -> 10 | Q88: 61 | R88: approved | S88: =IFERROR(INDEX(DATABASE_FG!$L$5:$L$367, MATCH(E88, DATABASE_FG!$C$5:$C$367, 0)), " ") -> 42 | T88: no | AA88: No | AD88: =IF(NOT(ISBLANK(AC88)), C88, "") | AE88: =IF(NOT(ISBLANK(AC88)), E88, "") | AG88: =AF88*H88 -> 0 | AK88: =IF(AB88="", IF(K88 < TODAY(), "Late", ""), IF(AB88 <= K88 + 2, "On Time", "Late")) | AL88: =TEXT(K88,"mmmm") -> December | AM88: =YEAR(Table1[[#This Row],[ETA As requested dd.mm.yyyy]]) -> 2026
A89: BOSCH Homburg | B89: firm | C89: 4508771389 | E89: 1818509497 | F89: =IFERROR(VLOOKUP(Table1[[#This Row],[Part Number]],DATABASE_FG!$C$6:D10078,2,FALSE)," ") -> VALVE BODY | G89: =IFERROR(_xlfn.XLOOKUP(Table1[[#This Row],[Part Number]],Table3[Part number],Table3[Drawing Revision]),"") -> 1 | H89: {=IFERROR(INDEX(PDB!$C:$AT,MATCH(E89,PDB!$B:$B,0),MATCH(YEAR(K89),0+PDB!$C$1:$AT$1,0)),"")} -> 5.19 | I89: 5 | J89: =IFERROR(Table1[[#This Row],[Quantity]]*Table1[[#This Row],[Price/Unit EUR]]," ") -> 25.95 | K89: 45541 | L89: =WEEKNUM(Table1[[#This Row],[ETA As requested dd.mm.yyyy]]) -> 36 | M89: =YEAR(Table1[[#This Row],[ETA As requested dd.mm.yyyy]]) -> 2024 | N89: =IFERROR(INDEX(DATABASE_FG!$H$5:$H$367, MATCH(E89, DATABASE_FG!$C$5:$C$367, 0)), " ") -> 0 | O89: =IF(E89<>"", _xlfn.XLOOKUP(E89, DATABASE_FG!C:C, DATABASE_FG!F:F), " ") -> Ventilkoerper | P89: =IFERROR(INDEX(DATABASE_FG!$G$5:$G$367, MATCH(E89, DATABASE_FG!$C$5:$C$367, 0)), "Not Found") -> 240 | R89: project | S89: =Table1[[#This Row],[Quantity]]/48 -> 0.10416667 | AA89: Yes | AB89: 45876 | AD89: =IF(NOT(ISBLANK(AC89)), C89, "") | AE89: =IF(NOT(ISBLANK(AC89)), E89, "") | AF89: 0 | AG89: =AF89*H89 -> 0 | AK89: =IF(AB89="", IF(K89 < TODAY(), "Late", ""), IF(AB89 <= K89 + 2, "On Time", "Late")) -> Late | AL89: =TEXT(K89,"mmmm") -> September | AM89: =YEAR(Table1[[#This Row],[ETA As requested dd.mm.yyyy]]) -> 2024
A90: BOSCH Homburg | B90: firm | C90: 4508771389 | E90: 1818509497 | F90: =IFERROR(VLOOKUP(Table1[[#This Row],[Part Number]],DATABASE_FG!$C$6:D10079,2,FALSE)," ") -> VALVE BODY | G90: =IFERROR(_xlfn.XLOOKUP(Table1[[#This Row],[Part Number]],Table3[Part number],Table3[Drawing Revision]),"") -> 1 | H90: 300 | I90: 5 | J90: =IFERROR(Table1[[#This Row],[Quantity]]*Table1[[#This Row],[Price/Unit EUR]]," ") -> 1500 | K90: 45541 | L90: =WEEKNUM(Table1[[#This Row],[ETA As requested dd.mm.yyyy]]) -> 36 | M90: =YEAR(Table1[[#This Row],[ETA As requested dd.mm.yyyy]]) -> 2024 | N90: =IFERROR(INDEX(DATABASE_FG!$H$5:$H$367, MATCH(E90, DATABASE_FG!$C$5:$C$367, 0)), " ") -> 0 | O90: =IF(E90<>"", _xlfn.XLOOKUP(E90, DATABASE_FG!C:C, DATABASE_FG!F:F), " ") -> Ventilkoerper | P90: =IFERROR(INDEX(DATABASE_FG!$G$5:$G$367, MATCH(E90, DATABASE_FG!$C$5:$C$367, 0)), "Not Found") -> 240 | R90: project | S90: =IFERROR(INDEX(DATABASE_FG!$L$5:$L$367, MATCH(E90, DATABASE_FG!$C$5:$C$367, 0)), " ") -> 56 | T90: yes | X90: project | AA90: Yes | AB90: 45946 | AC90: 251192 | AD90: =IF(NOT(ISBLANK(AC90)), C90, "") -> 4508771389 | AE90: =IF(NOT(ISBLANK(AC90)), E90, "") -> 1818509497 | AF90: 5 | AG90: =AF90*H90 -> 1500 | AJ90: 20251336-22.10.2025 | AK90: =IF(AB90="", IF(K90 < TODAY(), "Late", ""), IF(AB90 <= K90 + 2, "On Time", "Late")) -> Late | AL90: =TEXT(K90,"mmmm") -> September | AM90: =YEAR(Table1[[#This Row],[ETA As requested dd.mm.yyyy]]) -> 2024
A91: BOSCH Homburg | B91: firm | C91: 4508756412 | E91: 1818509503 | F91: =IFERROR(VLOOKUP(Table1[[#This Row],[Part Number]],DATABASE_FG!$C$6:D10080,2,FALSE)," ") -> VALVE BODY | G91: =IFERROR(_xlfn.XLOOKUP(Table1[[#This Row],[Part Number]],Table3[Part number],Table3[Drawing Revision]),"") -> 1 | H91: {=IFERROR(INDEX(PDB!$C:$AT,MATCH(E91,PDB!$B:$B,0),MATCH(YEAR(K91),0+PDB!$C$1:$AT$1,0)),"")} -> 12.65 | I91: 5 | J91: =IFERROR(Table1[[#This Row],[Quantity]]*Table1[[#This Row],[Price/Unit EUR]]," ") -> 63.25 | K91: 45541 | L91: =WEEKNUM(Table1[[#This Row],[ETA As requested dd.mm.yyyy]]) -> 36 | M91: =YEAR(Table1[[#This Row],[ETA As requested dd.mm.yyyy]]) -> 2024 | N91: =IFERROR(INDEX(DATABASE_FG!$H$5:$H$367, MATCH(E91, DATABASE_FG!$C$5:$C$367, 0)), " ") -> 0 | O91: =IF(E91<>"", _xlfn.XLOOKUP(E91, DATABASE_FG!C:C, DATABASE_FG!F:F), " ") -> Ventilkoerper | P91: =IFERROR(INDEX(DATABASE_FG!$G$5:$G$367, MATCH(E91, DATABASE_FG!$C$5:$C$367, 0)), "Not Found") -> 100 | R91: project | S91: =IFERROR(INDEX(DATABASE_FG!$L$5:$L$367, MATCH(E91, DATABASE_FG!$C$5:$C$367, 0)), " ") -> 56 | T91: yes | Z91: 240904 | AA91: Yes | AB91: 45558 | AC91: 202401159 | AD91: =IF(NOT(ISBLANK(AC91)), C91, "") -> 4508756412 | AE91: =IF(NOT(ISBLANK(AC91)), E91, "") -> 1818509503 | AF91: 5 | AG91: =AF91*H91 -> 63.25 | AJ91: 20241223 23.09.2024 | AK91: =IF(AB91="", IF(K91 < TODAY(), "Late", ""), IF(AB91 <= K91 + 2, "On Time", "Late")) -> Late | AL91: =TEXT(K91,"mmmm") -> September | AM91: =YEAR(Table1[[#This Row],[ETA As requested dd.mm.yyyy]]) -> 2024
A92: BOSCH Homburg | B92: firm | C92: 4508771613 | D92: 45553 | E92: 1818509508 | F92: =IFERROR(VLOOKUP(Table1[[#This Row],[Part Number]],DATABASE_FG!$C$6:D10081,2,FALSE)," ") -> VALVE BODY | G92: =IFERROR(_xlfn.XLOOKUP(Table1[[#This Row],[Part Number]],Table3[Part number],Table3[Drawing Revision]),"") -> 1 | H92: {=IFERROR(INDEX(PDB!$C:$AT,MATCH(E92,PDB!$B:$B,0),MATCH(YEAR(K92),0+PDB!$C$1:$AT$1,0)),"")} -> 9.32 | I92: 5 | J92: =IFERROR(Table1[[#This Row],[Quantity]]*Table1[[#This Row],[Price/Unit EUR]]," ") -> 46.6 | K92: 45541 | L92: =WEEKNUM(Table1[[#This Row],[ETA As requested dd.mm.yyyy]]) -> 36 | M92: =YEAR(Table1[[#This Row],[ETA As requested dd.mm.yyyy]]) -> 2024 | N92: =IFERROR(INDEX(DATABASE_FG!$H$5:$H$367, MATCH(E92, DATABASE_FG!$C$5:$C$367, 0)), " ") -> 0 | O92: =IF(E92<>"", _xlfn.XLOOKUP(E92, DATABASE_FG!C:C, DATABASE_FG!F:F), " ") -> Ventilkoerper | P92: =IFERROR(INDEX(DATABASE_FG!$G$5:$G$367, MATCH(E92, DATABASE_FG!$C$5:$C$367, 0)), "Not Found") -> 105 | Q92: 60 | R92: project | S92: =IFERROR(INDEX(DATABASE_FG!$L$5:$L$367, MATCH(E92, DATABASE_FG!$C$5:$C$367, 0)), " ") -> 56 | T92: yes | AA92: Yes | AB92: 45478 | AC92: 2024806 | AD92: =IF(NOT(ISBLANK(AC92)), C92, "") -> 4508771613 | AE92: =IF(NOT(ISBLANK(AC92)), E92, "") -> 1818509508 | AF92: 5 | AG92: =AF92*H92 -> 46.6 | AI92: VALIDARE | AJ92: 20240852-05.07.2024 | AK92: =IF(AB92="", IF(K92 < TODAY(), "Late", ""), IF(AB92 <= K92 + 2, "On Time", "Late")) -> On Time | AL92: =TEXT(K92,"mmmm") -> September | AM92: =YEAR(Table1[[#This Row],[ETA As requested dd.mm.yyyy]]) -> 2024
A93: BOSCH Homburg | B93: firm | C93: 4508771613 | D93: 45553 | E93: 1818509508 | F93: =IFERROR(VLOOKUP(Table1[[#This Row],[Part Number]],DATABASE_FG!$C$6:D10082,2,FALSE)," ") -> VALVE BODY | G93: =IFERROR(_xlfn.XLOOKUP(Table1[[#This Row],[Part Number]],Table3[Part number],Table3[Drawing Revision]),"") -> 1 | H93: {=IFERROR(INDEX(PDB!$C:$AT,MATCH(E93,PDB!$B:$B,0),MATCH(YEAR(K93),0+PDB!$C$1:$AT$1,0)),"")} -> 9.32 | I93: 5 | J93: =IFERROR(Table1[[#This Row],[Quantity]]*Table1[[#This Row],[Price/Unit EUR]]," ") -> 46.6 | K93: 45542 | L93: =WEEKNUM(Table1[[#This Row],[ETA As requested dd.mm.yyyy]]) -> 36 | M93: =YEAR(Table1[[#This Row],[ETA As requested dd.mm.yyyy]]) -> 2024 | N93: =IFERROR(INDEX(DATABASE_FG!$H$5:$H$367, MATCH(E93, DATABASE_FG!$C$5:$C$367, 0)), " ") -> 0 | O93: =IF(E93<>"", _xlfn.XLOOKUP(E93, DATABASE_FG!C:C, DATABASE_FG!F:F), " ") -> Ventilkoerper | P93: =IFERROR(INDEX(DATABASE_FG!$G$5:$G$367, MATCH(E93, DATABASE_FG!$C$5:$C$367, 0)), "Not Found") -> 105 | S93: =Table1[[#This Row],[Quantity]]/48 -> 0.10416667 | AA93: Yes | AB93: 45496 | AC93: 2024899 | AD93: =IF(NOT(ISBLANK(AC93)), C93, "") -> 4508771613 | AE93: =IF(NOT(ISBLANK(AC93)), E93, "") -> 1818509508 | AF93: 5 | AG93: =AF93*H93 -> 46.6 | AH93: COZAC LUCIAN | AI93: stornate*NU SE FACTUREAZA* | AJ93: 20240941-23.07.2024/20241042-13.08.2024 | AK93: =IF(AB93="", IF(K93 < TODAY(), "Late", ""), IF(AB93 <= K93 + 2, "On Time", "Late")) -> On Time | AL93: =TEXT(K93,"mmmm") -> September | AM93: =YEAR(Table1[[#This Row],[ETA As requested dd.mm.yyyy]]) -> 2024
A94: BOSCH Homburg | B94: forecast | C94: 5500549962 | D94: 45553 | E94: 1818509508 | F94: =IFERROR(VLOOKUP(Table1[[#This Row],[Part Number]],DATABASE_FG!$C$6:D10083,2,FALSE)," ") -> VALVE BODY | G94: =IFERROR(_xlfn.XLOOKUP(Table1[[#This Row],[Part Number]],Table3[Part number],Table3[Drawing Revision]),"") -> 1 | H94: {=IFERROR(INDEX(PDB!$C:$AT,MATCH(E94,PDB!$B:$B,0),MATCH(YEAR(K94),0+PDB!$C$1:$AT$1,0)),"")} -> 0 | I94: 105 | J94: =IFERROR(Table1[[#This Row],[Quantity]]*Table1[[#This Row],[Price/Unit EUR]]," ") -> 0 | K94: 46057 | L94: =WEEKNUM(Table1[[#This Row],[ETA As requested dd.mm.yyyy]]) -> 6 | M94: =YEAR(Table1[[#This Row],[ETA As requested dd.mm.yyyy]]) -> 2026 | N94: =IFERROR(INDEX(DATABASE_FG!$H$5:$H$367, MATCH(E94, DATABASE_FG!$C$5:$C$367, 0)), " ") -> 0 | O94: =IF(E94<>"", _xlfn.XLOOKUP(E94, DATABASE_FG!C:C, DATABASE_FG!F:F), " ") -> Ventilkoerper | P94: =IFERROR(INDEX(DATABASE_FG!$G$5:$G$367, MATCH(E94, DATABASE_FG!$C$5:$C$367, 0)), "Not Found") -> 105 | S94: =IFERROR(INDEX(DATABASE_FG!$L$5:$L$367, MATCH(E94, DATABASE_FG!$C$5:$C$367, 0)), " ") -> 56 | AA94: No | AD94: =IF(NOT(ISBLANK(AC94)), C94, "") | AE94: =IF(NOT(ISBLANK(AC94)), E94, "") | AG94: =AF94*H94 -> 0 | AK94: =IF(AB94="", IF(K94 < TODAY(), "Late", ""), IF(AB94 <= K94 + 2, "On Time", "Late")) | AL94: =TEXT(K94,"mmmm") -> February | AM94: =YEAR(Table1[[#This Row],[ETA As requested dd.mm.yyyy]]) -> 2026
A95: BOSCH Homburg | B95: forecast | C95: 5500549962 | D95: 45553 | E95: 1818509508 | F95: =IFERROR(VLOOKUP(Table1[[#This Row],[Part Number]],DATABASE_FG!$C$6:D10084,2,FALSE)," ") -> VALVE BODY | G95: =IFERROR(_xlfn.XLOOKUP(Table1[[#This Row],[Part Number]],Table3[Part number],Table3[Drawing Revision]),"") -> 1 | H95: {=IFERROR(INDEX(PDB!$C:$AT,MATCH(E95,PDB!$B:$B,0),MATCH(YEAR(K95),0+PDB!$C$1:$AT$1,0)),"")} -> 0 | I95: 105 | J95: =IFERROR(Table1[[#This Row],[Quantity]]*Table1[[#This Row],[Price/Unit EUR]]," ") -> 0 | K95: 46148 | L95: =WEEKNUM(Table1[[#This Row],[ETA As requested dd.mm.yyyy]]) -> 19 | M95: =YEAR(Table1[[#This Row],[ETA As requested dd.mm.yyyy]]) -> 2026 | N95: =IFERROR(INDEX(DATABASE_FG!$H$5:$H$367, MATCH(E95, DATABASE_FG!$C$5:$C$367, 0)), " ") -> 0 | O95: =IF(E95<>"", _xlfn.XLOOKUP(E95, DATABASE_FG!C:C, DATABASE_FG!F:F), " ") -> Ventilkoerper | P95: =IFERROR(INDEX(DATABASE_FG!$G$5:$G$367, MATCH(E95, DATABASE_FG!$C$5:$C$367, 0)), "Not Found") -> 105 | S95: =IFERROR(INDEX(DATABASE_FG!$L$5:$L$367, MATCH(E95, DATABASE_FG!$C$5:$C$367, 0)), " ") -> 56 | AA95: No | AD95: =IF(NOT(ISBLANK(AC95)), C95, "") | AE95: =IF(NOT(ISBLANK(AC95)), E95, "") | AG95: =AF95*H95 -> 0 | AK95: =IF(AB95="", IF(K95 < TODAY(), "Late", ""), IF(AB95 <= K95 + 2, "On Time", "Late")) | AL95: =TEXT(K95,"mmmm") -> May | AM95: =YEAR(Table1[[#This Row],[ETA As requested dd.mm.yyyy]]) -> 2026
A96: BOSCH Homburg | B96: forecast | C96: 5500549962 | D96: 45553 | E96: 1818509508 | F96: =IFERROR(VLOOKUP(Table1[[#This Row],[Part Number]],DATABASE_FG!$C$6:D10085,2,FALSE)," ") -> VALVE BODY | G96: =IFERROR(_xlfn.XLOOKUP(Table1[[#This Row],[Part Number]],Table3[Part number],Table3[Drawing Revision]),"") -> 1 | H96: {=IFERROR(INDEX(PDB!$C:$AT,MATCH(E96,PDB!$B:$B,0),MATCH(YEAR(K96),0+PDB!$C$1:$AT$1,0)),"")} -> 0 | I96: 105 | J96: =IFERROR(Table1[[#This Row],[Quantity]]*Table1[[#This Row],[Price/Unit EUR]]," ") -> 0 | K96: 46225 | L96: =WEEKNUM(Table1[[#This Row],[ETA As requested dd.mm.yyyy]]) -> 30 | M96: =YEAR(Table1[[#This Row],[ETA As requested dd.mm.yyyy]]) -> 2026 | N96: =IFERROR(INDEX(DATABASE_FG!$H$5:$H$367, MATCH(E96, DATABASE_FG!$C$5:$C$367, 0)), " ") -> 0 | O96: =IF(E96<>"", _xlfn.XLOOKUP(E96, DATABASE_FG!C:C, DATABASE_FG!F:F), " ") -> Ventilkoerper | P96: =IFERROR(INDEX(DATABASE_FG!$G$5:$G$367, MATCH(E96, DATABASE_FG!$C$5:$C$367, 0)), "Not Found") -> 105 | S96: =IFERROR(INDEX(DATABASE_FG!$L$5:$L$367, MATCH(E96, DATABASE_FG!$C$5:$C$367, 0)), " ") -> 56 | AA96: No | AD96: =IF(NOT(ISBLANK(AC96)), C96, "") | AE96: =IF(NOT(ISBLANK(AC96)), E96, "") | AG96: =AF96*H96 -> 0 | AK96: =IF(AB96="", IF(K96 < TODAY(), "Late", ""), IF(AB96 <= K96 + 2, "On Time", "Late")) | AL96: =TEXT(K96,"mmmm") -> July | AM96: =YEAR(Table1[[#This Row],[ETA As requested dd.mm.yyyy]]) -> 2026
A97: BOSCH Homburg | B97: forecast | C97: 5500549962 | D97: 45553 | E97: 1818509508 | F97: =IFERROR(VLOOKUP(Table1[[#This Row],[Part Number]],DATABASE_FG!$C$6:D10086,2,FALSE)," ") -> VALVE BODY | G97: =IFERROR(_xlfn.XLOOKUP(Table1[[#This Row],[Part Number]],Table3[Part number],Table3[Drawing Revision]),"") -> 1 | H97: {=IFERROR(INDEX(PDB!$C:$AT,MATCH(E97,PDB!$B:$B,0),MATCH(YEAR(K97),0+PDB!$C$1:$AT$1,0)),"")} -> 0 | I97: 105 | J97: =IFERROR(Table1[[#This Row],[Quantity]]*Table1[[#This Row],[Price/Unit EUR]]," ") -> 0 | K97: 46267 | L97: =WEEKNUM(Table1[[#This Row],[ETA As requested dd.mm.yyyy]]) -> 36 | M97: =YEAR(Table1[[#This Row],[ETA As requested dd.mm.yyyy]]) -> 2026 | N97: =IFERROR(INDEX(DATABASE_FG!$H$5:$H$367, MATCH(E97, DATABASE_FG!$C$5:$C$367, 0)), " ") -> 0 | O97: =IF(E97<>"", _xlfn.XLOOKUP(E97, DATABASE_FG!C:C, DATABASE_FG!F:F), " ") -> Ventilkoerper | P97: =IFERROR(INDEX(DATABASE_FG!$G$5:$G$367, MATCH(E97, DATABASE_FG!$C$5:$C$367, 0)), "Not Found") -> 105 | S97: =Table1[[#This Row],[Quantity]]/48 -> 2.1875 | AA97: No | AD97: =IF(NOT(ISBLANK(AC97)), C97, "") | AE97: =IF(NOT(ISBLANK(AC97)), E97, "") | AG97: =AF97*H97 -> 0 | AK97: =IF(AB97="", IF(K97 < TODAY(), "Late", ""), IF(AB97 <= K97 + 2, "On Time", "Late")) | AL97: =TEXT(K97,"mmmm") -> September | AM97: =YEAR(Table1[[#This Row],[ETA As requested dd.mm.yyyy]]) -> 2026
A98: BOSCH Homburg | B98: forecast | C98: 5500549962 | D98: 45553 | E98: 1818509508 | F98: =IFERROR(VLOOKUP(Table1[[#This Row],[Part Number]],DATABASE_FG!$C$6:D10087,2,FALSE)," ") -> VALVE BODY | G98: =IFERROR(_xlfn.XLOOKUP(Table1[[#This Row],[Part Number]],Table3[Part number],Table3[Drawing Revision]),"") -> 1 | H98: {=IFERROR(INDEX(PDB!$C:$AT,MATCH(E98,PDB!$B:$B,0),MATCH(YEAR(K98),0+PDB!$C$1:$AT$1,0)),"")} -> 0 | I98: 105 | J98: =IFERROR(Table1[[#This Row],[Quantity]]*Table1[[#This Row],[Price/Unit EUR]]," ") -> 0 | K98: 46358 | L98: =WEEKNUM(Table1[[#This Row],[ETA As requested dd.mm.yyyy]]) -> 49 | M98: =YEAR(Table1[[#This Row],[ETA As requested dd.mm.yyyy]]) -> 2026 | N98: =IFERROR(INDEX(DATABASE_FG!$H$5:$H$367, MATCH(E98, DATABASE_FG!$C$5:$C$367, 0)), " ") -> 0 | O98: =IF(E98<>"", _xlfn.XLOOKUP(E98, DATABASE_FG!C:C, DATABASE_FG!F:F), " ") -> Ventilkoerper | P98: =IFERROR(INDEX(DATABASE_FG!$G$5:$G$367, MATCH(E98, DATABASE_FG!$C$5:$C$367, 0)), "Not Found") -> 105 | S98: =IFERROR(INDEX(DATABASE_FG!$L$5:$L$367, MATCH(E98, DATABASE_FG!$C$5:$C$367, 0)), " ") -> 56 | AA98: No | AD98: =IF(NOT(ISBLANK(AC98)), C98, "") | AE98: =IF(NOT(ISBLANK(AC98)), E98, "") | AG98: =AF98*H98 -> 0 | AK98: =IF(AB98="", IF(K98 < TODAY(), "Late", ""), IF(AB98 <= K98 + 2, "On Time", "Late")) | AL98: =TEXT(K98,"mmmm") -> December | AM98: =YEAR(Table1[[#This Row],[ETA As requested dd.mm.yyyy]]) -> 2026
A99: BOSCH Homburg | B99: firm | C99: 4508769328 | E99: 1818509512 | F99: =IFERROR(VLOOKUP(Table1[[#This Row],[Part Number]],DATABASE_FG!$C$6:D10088,2,FALSE)," ") -> VALVE BODY | G99: =IFERROR(_xlfn.XLOOKUP(Table1[[#This Row],[Part Number]],Table3[Part number],Table3[Drawing Revision]),"") -> AB | H99: {=IFERROR(INDEX(PDB!$C:$AT,MATCH(E99,PDB!$B:$B,0),MATCH(YEAR(K99),0+PDB!$C$1:$AT$1,0)),"")} -> 3.26 | I99: 5 | J99: =IFERROR(Table1[[#This Row],[Quantity]]*Table1[[#This Row],[Price/Unit EUR]]," ") -> 16.3 | K99: 45541 | L99: =WEEKNUM(Table1[[#This Row],[ETA As requested dd.mm.yyyy]]) -> 36 | M99: =YEAR(Table1[[#This Row],[ETA As requested dd.mm.yyyy]]) -> 2024 | N99: =IFERROR(INDEX(DATABASE_FG!$H$5:$H$367, MATCH(E99, DATABASE_FG!$C$5:$C$367, 0)), " ") -> 0 | O99: =IF(E99<>"", _xlfn.XLOOKUP(E99, DATABASE_FG!C:C, DATABASE_FG!F:F), " ") -> Ventilkoerper | P99: =IFERROR(INDEX(DATABASE_FG!$G$5:$G$367, MATCH(E99, DATABASE_FG!$C$5:$C$367, 0)), "Not Found") -> 300 | Q99: 60 | R99: project | S99: =IFERROR(INDEX(DATABASE_FG!$L$5:$L$367, MATCH(E99, DATABASE_FG!$C$5:$C$367, 0)), " ") -> 56 | T99: yes | Z99: 240906 | AA99: Yes | AB99: 45541 | AC99: 202401114 | AD99: =IF(NOT(ISBLANK(AC99)), C99, "") -> 4508769328 | AE99: =IF(NOT(ISBLANK(AC99)), E99, "") -> 1818509512 | AF99: 5 | AG99: =AF99*H99 -> 16.3 | AI99: PPAP | AJ99: 20230611-12.05.2023/20241159-09.09.2024/20241155-06.09.2024 | AK99: =IF(AB99="", IF(K99 < TODAY(), "Late", ""), IF(AB99 <= K99 + 2, "On Time", "Late")) -> On Time | AL99: =TEXT(K99,"mmmm") -> September | AM99: =YEAR(Table1[[#This Row],[ETA As requested dd.mm.yyyy]]) -> 2024
A100: BOSCH Homburg | B100: firm | C100: 4508769328 | E100: 1818509516 | F100: =IFERROR(VLOOKUP(Table1[[#This Row],[Part Number]],DATABASE_FG!$C$6:D10089,2,FALSE)," ") -> VALVE BODY | G100: =IFERROR(_xlfn.XLOOKUP(Table1[[#This Row],[Part Number]],Table3[Part number],Table3[Drawing Revision]),"") -> 1 | H100: {=IFERROR(INDEX(PDB!$C:$AT,MATCH(E100,PDB!$B:$B,0),MATCH(YEAR(K100),0+PDB!$C$1:$AT$1,0)),"")} -> 3.29 | I100: 5 | J100: 16.45 | K100: 45541 | L100: 36 | M100: 2024 | N100: 0 | O100: Ventilkoerper | P100: 300 | R100: project | S100: Yes | T100: 45770 | U100: 25658 | V100: 4508769328 | W100: 1818509516 | X100: 5 | Y100: 16.45 | AA100: Yes | AB100: 45930 | AC100: 251172 | AD100: =IF(NOT(ISBLANK(AC100)), C100, "") -> 4508769328 | AE100: =IF(NOT(ISBLANK(AC100)), E100, "") -> 1818509516 | AF100: 5 | AG100: =AF100*H100 -> 16.45 | AI100: PPAP | AJ100: 20251276-01.10.2025 | AK100: =IF(AB100="", IF(K100 < TODAY(), "Late", ""), IF(AB100 <= K100 + 2, "On Time", "Late")) -> Late | AL100: =TEXT(K100,"mmmm") -> September | AM100: =YEAR(Table1[[#This Row],[ETA As requested dd.mm.yyyy]]) -> 2024
A101: BOSCH Homburg | B101: firm | C101: 4508769328 | E101: 1818509516 | F101: =IFERROR(VLOOKUP(Table1[[#This Row],[Part Number]],DATABASE_FG!$C$6:D10090,2,FALSE)," ") -> VALVE BODY | G101: =IFERROR(_xlfn.XLOOKUP(Table1[[#This Row],[Part Number]],Table3[Part number],Table3[Drawing Revision]),"") -> 1 | H101: {=IFERROR(INDEX(PDB!$C:$AT,MATCH(E101,PDB!$B:$B,0),MATCH(YEAR(K101),0+PDB!$C$1:$AT$1,0)),"")} -> 3.29 | I101: 5 | J101: =IFERROR(Table1[[#This Row],[Quantity]]*Table1[[#This Row],[Price/Unit EUR]]," ") -> 16.45 | K101: 45541 | L101: =WEEKNUM(Table1[[#This Row],[ETA As requested dd.mm.yyyy]]) -> 36 | M101: =YEAR(Table1[[#This Row],[ETA As requested dd.mm.yyyy]]) -> 2024 | N101: =IFERROR(INDEX(DATABASE_FG!$H$5:$H$367, MATCH(E101, DATABASE_FG!$C$5:$C$367, 0)), " ") -> 0 | O101: =IF(E101<>"", _xlfn.XLOOKUP(E101, DATABASE_FG!C:C, DATABASE_FG!F:F), " ") -> Ventilkoerper | P101: =IFERROR(INDEX(DATABASE_FG!$G$5:$G$367, MATCH(E101, DATABASE_FG!$C$5:$C$367, 0)), "Not Found") -> 300 | R101: project | S101: =IFERROR(INDEX(DATABASE_FG!$L$5:$L$367, MATCH(E101, DATABASE_FG!$C$5:$C$367, 0)), " ") -> 56 | T101: yes | X101: project | Y101: yes | AA101: Yes | AB101: 45770 | AC101: 25658 | AD101: =IF(NOT(ISBLANK(AC101)), C101, "") -> 4508769328 | AE101: =IF(NOT(ISBLANK(AC101)), E101, "") -> 1818509516 | AF101: 5 | AG101: =AF101*H101 -> 16.45 | AI101: PPAP | AJ101: 20250553-23.04.2025 | AK101: =IF(AB101="", IF(K101 < TODAY(), "Late", ""), IF(AB101 <= K101 + 2, "On Time", "Late")) -> Late | AL101: =TEXT(K101,"mmmm") -> September | AM101: =YEAR(Table1[[#This Row],[ETA As requested dd.mm.yyyy]]) -> 2024
A102: BOSCH Homburg | B102: firm | C102: 4508771389 | E102: 1818509519 | F102: =IFERROR(VLOOKUP(Table1[[#This Row],[Part Number]],DATABASE_FG!$C$6:D10091,2,FALSE)," ") -> VALVE BODY | G102: =IFERROR(_xlfn.XLOOKUP(Table1[[#This Row],[Part Number]],Table3[Part number],Table3[Drawing Revision]),"") -> 1 | H102: {=IFERROR(INDEX(PDB!$C:$AT,MATCH(E102,PDB!$B:$B,0),MATCH(YEAR(K102),0+PDB!$C$1:$AT$1,0)),"")} -> 4.58 | I102: 5 | J102: =IFERROR(Table1[[#This Row],[Quantity]]*Table1[[#This Row],[Price/Unit EUR]]," ") -> 22.9 | K102: 45541 | L102: =WEEKNUM(Table1[[#This Row],[ETA As requested dd.mm.yyyy]]) -> 36 | M102: =YEAR(Table1[[#This Row],[ETA As requested dd.mm.yyyy]]) -> 2024 | N102: =IFERROR(INDEX(DATABASE_FG!$H$5:$H$367, MATCH(E102, DATABASE_FG!$C$5:$C$367, 0)), " ") -> 0 | O102: =IF(E102<>"", _xlfn.XLOOKUP(E102, DATABASE_FG!C:C, DATABASE_FG!F:F), " ") -> Ventilkoerper | P102: =IFERROR(INDEX(DATABASE_FG!$G$5:$G$367, MATCH(E102, DATABASE_FG!$C$5:$C$367, 0)), "Not Found") -> 216 | Q102: 60 | R102: project | S102: =IFERROR(INDEX(DATABASE_FG!$L$5:$L$367, MATCH(E102, DATABASE_FG!$C$5:$C$367, 0)), " ") -> 56 | T102: yes | Z102: 240616/240623 | AA102: Yes | AB102: 45527 | AC102: 202401056 | AD102: =IF(NOT(ISBLANK(AC102)), C102, "") -> 4508771389 | AE102: =IF(NOT(ISBLANK(AC102)), E102, "") -> 1818509519 | AF102: 5 | AG102: =AF102*H102 -> 22.9 | AI102: PPAP | AJ102: 20241099-26.08.2024 | AK102: =IF(AB102="", IF(K102 < TODAY(), "Late", ""), IF(AB102 <= K102 + 2, "On Time", "Late")) -> On Time | AL102: =TEXT(K102,"mmmm") -> September | AM102: =YEAR(Table1[[#This Row],[ETA As requested dd.mm.yyyy]]) -> 2024
A103: BOSCH Homburg | B103: firm | C103: 4508771613 | E103: 1818509554 | F103: =IFERROR(VLOOKUP(Table1[[#This Row],[Part Number]],DATABASE_FG!$C$6:D10092,2,FALSE)," ") -> VALVE BODY | G103: =IFERROR(_xlfn.XLOOKUP(Table1[[#This Row],[Part Number]],Table3[Part number],Table3[Drawing Revision]),"") -> 1 | H103: {=IFERROR(INDEX(PDB!$C:$AT,MATCH(E103,PDB!$B:$B,0),MATCH(YEAR(K103),0+PDB!$C$1:$AT$1,0)),"")} -> 23.43 | I103: 10 | J103: =IFERROR(Table1[[#This Row],[Quantity]]*Table1[[#This Row],[Price/Unit EUR]]," ") -> 234.3 | K103: 45541 | L103: =WEEKNUM(Table1[[#This Row],[ETA As requested dd.mm.yyyy]]) -> 36 | M103: =YEAR(Table1[[#This Row],[ETA As requested dd.mm.yyyy]]) -> 2024 | N103: =IFERROR(INDEX(DATABASE_FG!$H$5:$H$367, MATCH(E103, DATABASE_FG!$C$5:$C$367, 0)), " ") -> 0 | O103: =IF(E103<>"", _xlfn.XLOOKUP(E103, DATABASE_FG!C:C, DATABASE_FG!F:F), " ") -> Ventilkoerper | P103: =IFERROR(INDEX(DATABASE_FG!$G$5:$G$367, MATCH(E103, DATABASE_FG!$C$5:$C$367, 0)), "Not Found") -> 30 | R103: project | S103: =IFERROR(INDEX(DATABASE_FG!$L$5:$L$367, MATCH(E103, DATABASE_FG!$C$5:$C$367, 0)), " ") -> 56 | T103: yes | Z103: 240704/240714 | AA103: Yes | AB103: 45442 | AC103: 2024576 | AD103: =IF(NOT(ISBLANK(AC103)), C103, "") -> 4508771613 | AE103: =IF(NOT(ISBLANK(AC103)), E103, "") -> 1818509554 | AF103: 5 | AG103: =AF103*H103 -> 117.15 | AI103: Validare | AJ103: 20240639-30.05.2024 | AK103: =IF(AB103="", IF(K103 < TODAY(), "Late", ""), IF(AB103 <= K103 + 2, "On Time", "Late")) -> On Time | AL103: =TEXT(K103,"mmmm") -> September | AM103: =YEAR(Table1[[#This Row],[ETA As requested dd.mm.yyyy]]) -> 2024
A104: BOSCH Homburg | B104: firm | C104: 4508771613 | E104: 1818509554 | F104: =IFERROR(VLOOKUP(Table1[[#This Row],[Part Number]],DATABASE_FG!$C$6:D10093,2,FALSE)," ") -> VALVE BODY | G104: =IFERROR(_xlfn.XLOOKUP(Table1[[#This Row],[Part Number]],Table3[Part number],Table3[Drawing Revision]),"") -> 1 | H104: {=IFERROR(INDEX(PDB!$C:$AT,MATCH(E104,PDB!$B:$B,0),MATCH(YEAR(K104),0+PDB!$C$1:$AT$1,0)),"")} -> 23.43 | J104: =IFERROR(Table1[[#This Row],[Quantity]]*Table1[[#This Row],[Price/Unit EUR]]," ") -> 0 | K104: 45542 | L104: =WEEKNUM(Table1[[#This Row],[ETA As requested dd.mm.yyyy]]) -> 36 | M104: =YEAR(Table1[[#This Row],[ETA As requested dd.mm.yyyy]]) -> 2024 | N104: =IFERROR(INDEX(DATABASE_FG!$H$5:$H$367, MATCH(E104, DATABASE_FG!$C$5:$C$367, 0)), " ") -> 0 | O104: =IF(E104<>"", _xlfn.XLOOKUP(E104, DATABASE_FG!C:C, DATABASE_FG!F:F), " ") -> Ventilkoerper | P104: =IFERROR(INDEX(DATABASE_FG!$G$5:$G$367, MATCH(E104, DATABASE_FG!$C$5:$C$367, 0)), "Not Found") -> 30 | S104: =IFERROR(INDEX(DATABASE_FG!$L$5:$L$367, MATCH(E104, DATABASE_FG!$C$5:$C$367, 0)), " ") -> 56 | AA104: Yes | AB104: 45496 | AC104: 2024897 | AD104: =IF(NOT(ISBLANK(AC104)), C104, "") -> 4508771613 | AE104: =IF(NOT(ISBLANK(AC104)), E104, "") -> 1818509554 | AF104: 5 | AG104: =AF104*H104 -> 117.15 | AH104: COZAC LUCIAN | AI104: stornate*NU SE FACTUREAZA* | AJ104: 20240940-23.07.2024/20241043-13.08.2024 | AK104: =IF(AB104="", IF(K104 < TODAY(), "Late", ""), IF(AB104 <= K104 + 2, "On Time", "Late")) -> On Time | AL104: =TEXT(K104,"mmmm") -> September | AM104: =YEAR(Table1[[#This Row],[ETA As requested dd.mm.yyyy]]) -> 2024
A105: BOSCH Homburg | B105: firm | C105: 4508771613 | E105: 1818509555 | F105: =IFERROR(VLOOKUP(Table1[[#This Row],[Part Number]],DATABASE_FG!$C$6:D10094,2,FALSE)," ") -> VALVE BODY | G105: =IFERROR(_xlfn.XLOOKUP(Table1[[#This Row],[Part Number]],Table3[Part number],Table3[Drawing Revision]),"") -> 1 | H105: {=IFERROR(INDEX(PDB!$C:$AT,MATCH(E105,PDB!$B:$B,0),MATCH(YEAR(K105),0+PDB!$C$1:$AT$1,0)),"")} -> 27.16 | I105: 5 | J105: =IFERROR(Table1[[#This Row],[Quantity]]*Table1[[#This Row],[Price/Unit EUR]]," ") -> 135.8 | K105: 45541 | L105: =WEEKNUM(Table1[[#This Row],[ETA As requested dd.mm.yyyy]]) -> 36 | M105: =YEAR(Table1[[#This Row],[ETA As requested dd.mm.yyyy]]) -> 2024 | N105: =IFERROR(INDEX(DATABASE_FG!$H$5:$H$367, MATCH(E105, DATABASE_FG!$C$5:$C$367, 0)), " ") -> 0 | O105: =IF(E105<>"", _xlfn.XLOOKUP(E105, DATABASE_FG!C:C, DATABASE_FG!F:F), " ") -> Ventilkoerper | P105: =IFERROR(INDEX(DATABASE_FG!$G$5:$G$367, MATCH(E105, DATABASE_FG!$C$5:$C$367, 0)), "Not Found") -> 20 | R105: project | S105: =IFERROR(INDEX(DATABASE_FG!$L$5:$L$367, MATCH(E105, DATABASE_FG!$C$5:$C$367, 0)), " ") -> 56 | T105: yes | Z105: 240705/240803 | AA105: Yes | AB105: 45426 | AC105: 2024469 | AD105: =IF(NOT(ISBLANK(AC105)), C105, "") -> 4508771613 | AE105: =IF(NOT(ISBLANK(AC105)), E105, "") -> 1818509555 | AF105: 5 | AG105: =AF105*H105 -> 135.8 | AI105: validare | AJ105: 20240539-14.05.2024 | AK105: =IF(AB105="", IF(K105 < TODAY(), "Late", ""), IF(AB105 <= K105 + 2, "On Time", "Late")) -> On Time | AL105: =TEXT(K105,"mmmm") -> September | AM105: =YEAR(Table1[[#This Row],[ETA As requested dd.mm.yyyy]]) -> 2024
...

Sheet All OTD
B6: Count of Quantity | C6: Column Labels | I6: Count of Quantity | J6: Column Labels
B7: Row Labels | C7: Late | D7: On Time | E7: Grand Total | I7: Row Labels | J7: Late | K7: On Time | L7: Grand Total
B8: 2025 | I8: 2025
B9: October | I9: October
B10: BOSCH Blaj | C10: 0.71428571 | D10: 0.28571429 | E10: 1 | I10: BOSCH Blaj | J10: 5 | K10: 2 | L10: 7
B11: BOSCH Homburg | C11: 1 | D11: 0 | E11: 1 | I11: BOSCH Homburg | J11: 1 | L11: 1
B12: BOSCH Lohr | C12: 0.56521739 | D12: 0.43478261 | E12: 1 | I12: BOSCH Lohr | J12: 13 | K12: 10 | L12: 23
B13: IGW | C13: 1 | D13: 0 | E13: 1 | I13: IGW | J13: 1 | L13: 1
B14: Schaeffler RO | C14: 0.13924051 | D14: 0.86075949 | E14: 1 | I14: Schaeffler RO | J14: 11 | K14: 68 | L14: 79
B15: October Total | C15: 0.27927928 | D15: 0.72072072 | E15: 1 | I15: October Total | J15: 31 | K15: 80 | L15: 111
B16: 2025 Total | C16: 0.27927928 | D16: 0.72072072 | E16: 1 | I16: 2025 Total | J16: 31 | K16: 80 | L16: 111
B17: Grand Total | C17: 0.27927928 | D17: 0.72072072 | E17: 1 | I17: Grand Total | J17: 31 | K17: 80 | L17: 111

Sheet PDB
A1: Client | B1: Reper | C1: 2022 | D1: 2023 | E1: 2024 | F1: 2025 | G1: 2026 | H1: 2027 | I1: 2028 | L1: 2025 Pret Alex Itu
A2: Schaeffler Inele Strunjire | B2: F-229209-12-WW1 | C2: 36.44 | D2: 36.44 | E2: 36.44 | F2: 36.44 | G2: 0 | H2: 0 | I2: 0
A3: Schaeffler Inele Strunjire | B3: F-229461-12-WW1 | C3: 18.37 | D3: 18.37 | E3: 18.37 | F3: 18.37 | G3: 0 | H3: 0 | I3: 0
A4: Schaeffler Inele Strunjire | B4: F-153924-12-WW1 | C4: 21.97 | D4: 21.97 | E4: 21.97 | F4: 21.97 | G4: 0 | H4: 0 | I4: 0
A5: Schaeffler Inele Strunjire | B5: F-556440-0013.AU.XU-WW1 | C5: 18.24 | D5: 18.24 | E5: 18.24 | F5: 18.24 | G5: 0 | H5: 0 | I5: 0
A6: Schaeffler Inele Strunjire | B6: F-155077-13-WW1 | C6: 24.97 | D6: 24.97 | E6: 24.97 | F6: 24.97 | G6: 0 | H6: 0 | I6: 0
A7: Schaeffler Inele Strunjire | B7: F-155077-43-WW1 | C7: 18.63 | D7: 18.63 | E7: 18.63 | F7: 18.63 | G7: 0 | H7: 0 | I7: 0
A8: Schaeffler Inele Strunjire | B8: F-235905-0013-WW1 | C8: 24.63 | D8: 24.63 | E8: 24.63 | F8: 24.63 | G8: 0 | H8: 0 | I8: 0
A9: Schaeffler Inele Strunjire | B9: F-235905-0042-WW1 | C9: 10.44 | D9: 10.44 | E9: 10.44 | F9: 10.44 | G9: 0 | H9: 0 | I9: 0
A10: Schaeffler Inele Strunjire | B10: F-552668-0024-DRE | C10: 12.5 | D10: 12.5 | E10: 12.5 | F10: 12.5 | G10: 0 | H10: 0 | I10: 0
A11: Schaeffler Inele Strunjire | B11: XU160260ZT-43-WW1 | C11: 9.89 | D11: 9.89 | E11: 9.89 | F11: 9.89 | G11: 0 | H11: 0 | I11: 0
A12: Schaeffler Inele Strunjire | B12: F-229209-0022-WW1 | C12: 23.79 | D12: 23.79 | E12: 23.79 | F12: 23.79 | G12: 0 | H12: 0 | I12: 0
A13: Schaeffler Inele Strunjire | B13: EDS F-556440-0012-ISB 004 AA | C13: 12.13 | D13: 12.13 | E13: 12.13 | F13: 12.13 | G13: 0 | H13: 0 | I13: 0
... A22: Schaeffler Inele Strunjire | B22: 154805.6-101 | C22: 5.32 | D22: 5.32 | E22: 5.32 | F22: 5.32 | G22: 0 | H22: 0 | I22: 0
A23: Schaeffler Inele Strunjire | B23: 154805.12 | C23: 5.32 | D23: 5.32 | E23: 5.32 | F23: 5.32 | G23: 0 | H23: 0 | I23: 0
A24: Schaeffler Alama | B24: EDS KUK.QJ215-C-MPA-3001B | C24: 150 | D24: 150 | E24: 150 | F24: 150 | G24: 0 | H24: 0 | I24: 0 | P24: preturi confirmare Alex Itu 07.02.2025
A25: Schaeffler Alama | B25: EDP KUH.6030-M-3001 004 | C25: 150 | D25: 150 | E25: 150 | F25: 150 | G25: 0 | H25: 0 | I25: 0 | Q25: Reper | R25: Eur/buc.
A26: Schaeffler Alama | B26: EDP KUH.6312-M-3001 004 | C26: 150 | D26: 150 | E26: 150 | F26: 150 | G26: 0 | H26: 0 | I26: 0 | P26: 050511742-0000 | Q26: KUH.6030-M-3001 | R26: 6.9
A27: Schaeffler Alama | B27: EDP KUK.QJ206-C-MPA-3001 004 | C27: 150 | D27: 150 | E27: 150 | F27: 150 | G27: 0 | H27: 0 | I27: 0 | P27: 050513575-0000 | Q27: KUH.6036-A-M-3001 | R27: 7.21
A28: Schaeffler Alama | B28: EDP KUK.QJ212-C-MPA-0031 000 | C28: 150 | D28: 150 | E28: 150 | F28: 150 | G28: 0 | H28: 0 | I28: 0 | P28: 050511750-0000 | Q28: KUH.6214-A-M-3001 | R28: 3,18
A29: Schaeffler Alama | B29: EDP KUH.6217-B-M-3001 004 | C29: 150 | D29: 150 | E29: 150 | F29: 150 | G29: 0 | H29: 0 | I29: 0 | P29: 050512315-0000 | Q29: KUH.6215-A-M-3001 | R29: 4,42
A30: Schaeffler Alama | B30: EDP KUH.6222-A-M-3001B | C30: 150 | D30: 150 | E30: 150 | F30: 150 | G30: 0 | H30: 0 | I30: 0 | P30: 051498022-0000 | Q30: KUH.6217-B-M-3001 | R30: 4,51
A31: Schaeffler Alama | B31: EDP KUH.6220-A-M-3001 004_ | C31: 150 | D31: 150 | E31: 150 | F31: 150 | G31: 0 | H31: 0 | I31: 0 | P31: 050511807-0000 | Q31: KUH.6220-A-M-3001 | R31: 4,78
A32: Schaeffler Alama | B32: EDP KUK.QJ207-C-MPA-3001 004 | C32: 150 | D32: 150 | E32: 150 | F32: 150 | G32: 0 | H32: 0 | I32: 0 | P32: 050513478-0000 | Q32: KUH.6312-M-3001 | R32: 4,5
A33: Schaeffler Alama | B33: RKDK.N222-EA-M3-0042 | C33: 150 | D33: 150 | E33: 150 | F33: 150 | G33: 0 | H33: 0 | I33: 0 | P33: 050512056-0000 | Q33: KUH.6315-A-M-3001 | R33: 4,92
A34: Schaeffler Alama | B34: RKDK.N317-EA-M3-0042 | C34: 150 | D34: 150 | E34: 150 | F34: 150 | G34: 0 | H34: 0 | I34: 0 | P34: 050512072-0000 | Q34: KUH.6316-A-M-3001 | R34: 3,44
A35: Schaeffler Alama | B35: KUH.6326-M-3001 | C35: 9.04 | D35: 9.04 | E35: 9.04 | F35: 9.04 | G35: 0 | H35: 0 | I35: 0 | P35: 050512064-0000 | Q35: KUH.6317-A-M-3001 | R35: 3,44
A36: Schaeffler Alama | B36: RKKM.N416-M3-0031 | C36: 8.83 | D36: 8.83 | E36: 8.83 | F36: 8.83 | G36: 0 | H36: 0 | I36: 0 | P36: 050619357-0000 | Q36: KUH.6326-M-3001 | R36: 9,04
A37: Schaeffler Alama | B37: EDP RKKM.N2220-EB-M3-0031 000 | C37: 8.83 | D37: 8.83 | E37: 8.83 | F37: 8.83 | G37: 0 | H37: 0 | I37: 0 | P37: 051499878-0000 | Q37: KUK.7220-B-MP-3001 | R37: 4,38
A38: Schaeffler Alama | B38: FAG KUH.6036-A-M-3001 | C38: 7.21 | D38: 7.21 | E38: 7.21 | F38: 7.21 | G38: 0 | H38: 0 | I38: 0 | P38: 050630300-0000 | Q38: KUK.QJ218-C-MPA-3001 | R38: 4,25
A39: Schaeffler Alama | B39: EDP KUH.6036-A-M-3001B _ | C39: 7.21 | D39: 7.21 | E39: 7.21 | F39: 7.21 | G39: 0 | H39: 0 | I39: 0
A40: Schaeffler Alama | B40: EDP KUH.6030-M-3001 004 | C40: 6.9 | D40: 6.9 | E40: 6.9 | F40: 6.9 | G40: 0 | H40: 0 | I40: 0
A41: Schaeffler Alama | B41: EDS F-801631-1031.RKKM.ZL-M3A | C41: 5.69 | D41: 5.69 | E41: 5.69 | F41: 5.69 | G41: 0 | H41: 0 | I41: 0
A42: Schaeffler Alama | B42: EDP KUH.6315-A-M-3001 004 | C42: 4.92 | D42: 4.92 | E42: 4.92 | F42: 4.92 | G42: 0 | H42: 0 | I42: 0
A43: Schaeffler Alama | B43: EDP KUH.6220-A-M-3001 004 | C43: 4.78 | D43: 4.78 | E43: 4.78 | F43: 4.78 | G43: 0 | H43: 0 | I43: 0
A44: Schaeffler Alama | B44: EDP KUH.6217-B-M-3001 004_ | C44: 4.51 | D44: 4.51 | E44: 4.51 | F44: 4.51 | G44: 0 | H44: 0 | I44: 0
A45: Schaeffler Alama | B45: FAG KUH.6312-M-3001 | C45: 4.5 | D45: 4.5 | E45: 4.5 | F45: 4.5 | G45: 0 | H45: 0 | I45: 0
A46: Schaeffler Alama | B46: FAG KUH.6215-A-M-3001 | C46: 4.42 | D46: 4.42 | E46: 4.42 | F46: 4.42 | G46: 0 | H46: 0 | I46: 0
A47: Schaeffler Alama | B47: KUK.7220-B-MP-3001 | C47: 4.38 | D47: 4.38 | E47: 4.38 | F47: 4.38 | G47: 0 | H47: 0 | I47: 0
A48: Schaeffler Alama | B48: EDP KUK.QJ218-C-MPA-3001 | C48: 4.25 | D48: 4.25 | E48: 4.25 | F48: 4.25 | G48: 0 | H48: 0 | I48: 0
A49: Schaeffler Alama | B49: EDS F-801632-1031.RKKM.ZL-M3A 000 | C49: 3.81 | D49: 3.81 | E49: 3.81 | F49: 3.81 | G49: 0 | H49: 0 | I49: 0
A50: Schaeffler Alama | B50: EDP KUH.6222-A-M-3001B | C50: 3.62 | D50: 3.62 | E50: 3.62 | F50: 3.62 | G50: 0 | H50: 0 | I50: 0
... A102: Schaeffler Ghidaje liniare | B102: TK.KWVE45-B-A-L-0031-BS | C102: 11.2 | D102: 11.2 | E102: 11.2 | F102: 11.2 | G102: 0 | H102: 0 | I102: 0
A103: Bosch Germania + Romania | B103: 1535100044 | C103: 8.25 | D103: 8.25 | E103: 8.25 | F103: 8.25 | G103: 0 | H103: 0 | I103: 0
A104: Bosch Germania + Romania | B104: 1535100045 | C104: 0.97 | D104: 0.97 | E104: 0.97 | F104: 0.97 | G104: 0 | H104: 0 | I104: 0
A105: Bosch Germania + Romania | B105: 1535100046 | C105: 5.31 | D105: 5.31 | E105: 5.31 | F105: 5.31 | G105: 0 | H105: 0 | I105: 0
A106: Bosch Germania + Romania | B106: 1810326006 | C106: 10 | D106: 10 | E106: 10 | F106: 10 | G106: 0 | H106: 0 | I106: 0
A107: Bosch Germania + Romania | B107: 1813218040 | C107: 9.37 | D107: 9.37 | E107: 9.37 | F107: 9.37 | G107: 0 | H107: 0 | I107: 0
A108: Bosch Germania + Romania | B108: 1813218042 | C108: 8.45 | D108: 8.45 | E108: 8.45 | F108: 8.45 | G108: 0 | H108: 0 | I108: 0
A109: Bosch Germania + Romania | B109: 1813218044 | C109: 14.17 | D109: 14.17 | E109: 14.17 | F109: 14.17 | G109: 0 | H109: 0 | I109: 0
A110: Bosch Germania + Romania | B110: 1813218046 | C110: 8.94 | D110: 8.94 | E110: 8.94 | F110: 8.94 | G110: 0 | H110: 0 | I110: 0
A111: Bosch Germania + Romania | B111: 1813218050 | C111: 7.46 | D111: 7.46 | E111: 7.46 | F111: 7.46 | G111: 0 | H111: 0 | I111: 0
A112: Bosch Germania + Romania | B112: 1813218081 | C112: 6.33 | D112: 6.33 | E112: 6.33 | F112: 6.33 | G112: 0 | H112: 0 | I112: 0
A113: Bosch Germania + Romania | B113: 1818509087 | C113: 4.66 | D113: 4.66 | E113: 4.66 | F113: 4.66 | G113: 0 | H113: 0 | I113: 0
A114: Bosch Germania + Romania | B114: 1818509091 | C114: 4.84 | D114: 4.84 | E114: 4.84 | F114: 4.84 | G114: 0 | H114: 0 | I114: 0
... A123: Bosch Germania + Romania | B123: 1818509276 | C123: 8.44 | D123: 8.44 | E123: 8.44 | F123: 8.44 | G123: 0 | H123: 0 | I123: 0
A124: Bosch Germania + Romania | B124: 1818509284 | C124: 8.45 | D124: 8.45 | E124: 8.45 | F124: 8.28 | G124: 0 | H124: 0 | I124: 0 | L124: =_xlfn.XLOOKUP(B124,'Pret Alex'!A:A,'Pret Alex'!B:B) -> 8.281
A125: Bosch Germania + Romania | B125: 1818509289 | C125: 10.99 | D125: 10.99 | E125: 10.99 | F125: 10.99 | G125: 0 | H125: 0 | I125: 0
A126: Bosch Germania + Romania | B126: 1818509439 | C126: 0.74 | D126: 0.74 | E126: 0.74 | F126: 0.74 | G126: 0 | H126: 0 | I126: 0
A127: Bosch Germania + Romania | B127: 1818509497 | C127: 5.19 | D127: 5.19 | E127: 5.19 | F127: 5.19 | G127: 0 | H127: 0 | I127: 0
A128: Bosch Germania + Romania | B128: 1818509503 | C128: 12.65 | D128: 12.65 | E128: 12.65 | F128: 12.65 | G128: 0 | H128: 0 | I128: 0
A129: Bosch Germania + Romania | B129: 1818509508 | C129: 9.32 | D129: 9.32 | E129: 9.32 | F129: 9.32 | G129: 0 | H129: 0 | I129: 0
A130: Bosch Germania + Romania | B130: 1818509509 | C130: 2.31 | D130: 2.31 | E130: 2.31 | F130: 2.31 | G130: 0 | H130: 0 | I130: 0
A131: Bosch Germania + Romania | B131: 1818509510 | C131: 2.52 | D131: 2.52 | E131: 2.52 | F131: 2.52 | G131: 0 | H131: 0 | I131: 0
A132: Bosch Germania + Romania | B132: 1818509512 | C132: 3.26 | D132: 3.26 | E132: 3.26 | F132: 3.26 | G132: 0 | H132: 0 | I132: 0
A133: Bosch Germania + Romania | B133: 1818509516 | C133: 3.29 | D133: 3.29 | E133: 3.29 | F133: 3.29 | G133: 0 | H133: 0 | I133: 0
A134: Bosch Germania + Romania | B134: 1818509519 | C134: 4.58 | D134: 4.58 | E134: 4.58 | F134: 4.58 | G134: 0 | H134: 0 | I134: 0
A135: Bosch Germania + Romania | B135: 1818509554 | C135: 23.43 | D135: 23.43 | E135: 23.43 | F135: 23.43 | G135: 0 | H135: 0 | I135: 0
A136: Bosch Germania + Romania | B136: 1818509555 | C136: 27.16 | D136: 27.16 | E136: 27.16 | F136: 27.16 | G136: 0 | H136: 0 | I136: 0
... A138: Bosch Germania + Romania | B138: 1818509618 | C138: 3.37 | D138: 3.37 | E138: 3.37 | F138: 3.37 | G138: 0 | H138: 0 | I138: 0
